Workbook

Sheet Checklist
A1: Rediseño Curricular 2026 · Control de entregas de las subcomisiones
A2: Carrera de Contaduría Pública · Facultad de Ciencias Económicas y Financieras · Universidad Mayor de San Andrés
A4: Código | B4: Punto del índice | C4: Responsable docente | D4: Responsable estudiantil | E4: Estado | F4: Fecha de recepción | G4: Formato recibido | H4: Adaptado al formato | I4: Observaciones | J4: Entregable | K4: Información extraída de internet (verificar)
A5: 1. | B5: Identificación del programa/carrera | C5: Edwin Gutiérrez Zapana | D5: Alarcon Pablo Alejandro | E5: =IF(SUMPRODUCT(($J$6:$J$18=1)*($E$6:$E$18<>"No aplica"))=0,"No aplica",IF(SUMPRODUCT(($J$6:$J$18=1)*($E$6:$E$18="Entregado"))=SUMPRODUCT(($J$6:$J$18=1)*($E$6:$E$18<>"No aplica")),"Completo",IF(SUMPRODUCT(($J$6:$J$18=1)*($E$6:$E$18="Pendiente"))=SUMPRODUCT(($J$6:$J$18=1)*($E$6:$E$18<>"No aplica")),"Pendiente","En proceso"))) | F5: =SUMPRODUCT(($J$6:$J$18=1)*($E$6:$E$18="Entregado"))&" de "&SUMPRODUCT(($J$6:$J$18=1)*($E$6:$E$18<>"No aplica")) | G5: — | H5: — | J5: 0
A6: 1.1 | B6: Facultad | C6: Edwin Gutiérrez Zapana | D6: Alarcon Pablo Alejandro | E6: Entregado | F6: 46308 | G6: Word | H6: Sí | I6: Fuentes: Plan 2027 (1.1) y Plan 2024 (1.1, párrafo sobre autonomía y cogobierno, redacción corregida). La mención de las Carreras de Economía y Administración de Empresas sale del membrete de la Res. HCF 1057/2026. | J6: 1
A7: 1.2 | B7: Programa/carrera | C7: Edwin Gutiérrez Zapana | D7: Alarcon Pablo Alejandro | E7: Entregado | F7: 46308 | G7: Word | H7: Sí | I7: Fuentes: Plan 2027 (1.2) y Plan 2024 (resoluciones de cambio de nombre: HCU 186/2000, HC Carrera 142/2011, HCF 613/2011 y HCU 438/2012), que en el Plan 2024 estaban dentro de 1.4. Error: en el Plan 2024 el punto 1.2 estaba vacío. | J7: 1
A8: 1.3 | B8: Fecha de creación y Resolución HCU | C8: Edwin Gutiérrez Zapana | D8: Alarcon Pablo Alejandro | E8: Entregado | F8: 46308 | G8: Word | H8: Sí | I8: Fuentes: Plan 2027 (fecha de fundación 25/08/1970) y Plan 2024 (texto de la Res. HCU 057/1974). Error: el Plan 2027 presentaba la Res. HCU 057/1974 como resolución de creación de 1970 sin explicar que es de 1974; se aclaró. El Plan 2024 transcribía la resolución completa; se resumió. Si se desea el texto íntegro, va como anexo. Error en el Plan 2024: "CONTADOR GENERA" por "CONTADOR GENERAL". | J8: 1 | K8: Origen en el Congreso Interno de 1970 y contexto de la Revolución Universitaria de abril de 1970. Fuente: página de historia de la Carrera (contaduriapublica.umsa.bo/carrera). Resaltado en verde.
A9: 1.4 | B9: Resolución(es) HCU que aprobaron planes de estudio anteriores | C9: Edwin Gutiérrez Zapana | D9: Alarcon Pablo Alejandro | E9: Entregado | F9: 46308 | G9: Word | H9: Sí | I9: Fuentes: Plan 2027 (planes 1999 y 2013) y Plan 2024 (II Congreso Interno, Res. HCU 438/2012). Errores en el Plan 2027: "Nª025/2013" y "Nª524/2004" corregidos a "N.º", y faltaba la resolución del Plan 2024. Error en el Plan 2024: el subtítulo "1.4 Organigrama funcional..." pertenece al punto 2.6 y se excluyó. Verificar por qué el Plan 1999 se aprobó recién en 2004. CORRECCIÓN (diagnóstico 2026): el plan vigente es el Plan 2013, no el Plan 2024. Se agregaron las Resoluciones HCC 162/2012 y HCF 929/2012 del Plan 2013. CONFIRMAR qué ocurrió con el Plan 2024 (Res. HCU 233/2024): el documento del Plan 2024 y la web lo mencionan, pero el diagnóstico aprobado por la Res. HCF 1057/2026 diagnostica el Plan 2013 como vigente. | J9: 1 | K9: Plan de Estudios 2024 aprobado con Res. HCU N.º 233/2024; la fecha no se pudo confirmar. Fuente: Reglamentos Internos de la Carrera 2024 (contaduriapublica.umsa.bo/documentos/2024/07_2024). Resaltado en verde.
A10: 1.5 | B10: Grado académico terminal | C10: Edwin Gutiérrez Zapana | D10: Alarcon Pablo Alejandro | E10: Entregado | F10: 46308 | G10: Word | H10: Sí | I10: Fuentes: Plan 2027 (Licenciatura) y Plan 2024 (sección 3.17.7, cinco años y modalidad de graduación). Confirmar con la subcomisión del punto 4.3.5 que la duración se mantiene en cinco años en el Plan 2027. Error en el Plan 2024: numeración 3.17.7 arrastrada de otro documento. CORRECCIÓN (diagnóstico 2026): se confirman los cinco años y se agregan las 6.000 horas académicas del Plan 2013. | J10: 1
A11: 1.6 | B11: Grado(s) académico(s) intermedio(s) | C11: Edwin Gutiérrez Zapana | D11: Alarcon Pablo Alejandro | E11: Entregado | F11: 46308 | G11: Word | H11: Sí | I11: Fuentes: Plan 2027 (Res. HCU 290/2016) y Plan 2024 (3.17.7: Técnico Medio en segundo año y Art. 4 del Reglamento General de Títulos y Grados). CONFIRMAR si el Plan 2027 mantiene el Técnico Medio (Auxiliar en Contabilidad General); el Plan 2027 no lo menciona. Denominación: el Plan 2024 dice "Técnico Superior" y la Res. HCU 290/2016 dice "Técnico Universitario Superior"; se usó la de la resolución. El texto del Plan 2024 sobre el examen de grado técnico superior (3.17.6) corresponde al punto 5.4 y se reserva para ese punto. Errores en el Plan 2027: "Grado (s) académicos intermedios (s)" y espacios dentro de los paréntesis. CORRECCIÓN (diagnóstico 2026): se quitó la frase "El Plan de Estudios 2024 reconoce...", porque el plan vigente es el 2013. El Técnico Medio se mantiene sin atribuirlo a un plan y sigue PENDIENTE de confirmación. CONFIRMADO por la fuente terciaria (propuesta de plan de estudios, puntos de grados intermedios): mantiene el Técnico Medio (Auxiliar en Contabilidad General) al concluir el segundo año. Esa fuente usa "Técnico Superior en Contabilidad General"; se mantiene "Técnico Universitario Superior" por la Res. HCU 290/2016. Unificar. | J11: 1
A12: 1.7 | B12: Sede(s) | C12: Edwin Gutiérrez Zapana | D12: Alarcon Pablo Alejandro | E12: Entregado | F12: 46308 | G12: Word | H12: Sí | I12: Fuente: Plan 2027 (CRU Yungas-Chulumani y SUL Caranavi). Error en el Plan 2027: no mencionaba la sede central de La Paz; se agregó. Error en el Plan 2024: 1.7 vacío. Confirmar si existen otras sedes o programas desconcentrados vigentes. CORRECCIÓN (diagnóstico 2026, puntos 3.1 y 7.1): se agregaron los edificios de la sede central (Nava Morales, Av. Montes esq. Pando, y Monoblock Central, Av. Villazón) y los 104 inscritos de las sedes desconcentradas en 2025. | J12: 1
A13: 1.8 | B13: Diploma académico terminal | C13: Edwin Gutiérrez Zapana | D13: Alarcon Pablo Alejandro | E13: Entregado | F13: 46308 | G13: Word | H13: Sí | I13: Fuentes: Plan 2027 y Res. HCU 438/2012 (Plan 2024). Se quitó la mayúscula sostenida "TÍTULO ACADÉMICO: LICENCIADO...". Error en el Plan 2024: 1.8 vacío. | J13: 1
A14: 1.9 | B14: Diploma(s) académico(s) intermedio(s) | C14: Edwin Gutiérrez Zapana | D14: Alarcon Pablo Alejandro | E14: Entregado | F14: 46308 | G14: Word | H14: Sí | I14: Fuentes: Plan 2027 y Res. HCU 290/2016. Error en el Plan 2027: "Diploma ( s) académico (s) intermedio". Error en el Plan 2024: 1.9 vacío. | J14: 1
A15: 1.10 | B15: Título Profesional | C15: Edwin Gutiérrez Zapana | D15: Alarcon Pablo Alejandro | E15: Entregado | F15: 46308 | G15: Word | H15: Sí | I15: Fuentes: Plan 2027 y Res. HCU 438/2012. Error en el Plan 2024: 1.10 vacío. | J15: 1
A16: 1.11 | B16: Título(s) profesional(es) intermedio(s) | C16: Edwin Gutiérrez Zapana | D16: Alarcon Pablo Alejandro | E16: Entregado | F16: 46308 | G16: Word | H16: Sí | I16: Fuentes: Plan 2027 y Res. HCU 290/2016. Error en el Plan 2027: "Título (s) profesional (s) intermedios". Error en el Plan 2024: 1.11 vacío. | J16: 1
A17: 1.12 | B17: Modalidad(es) de docencia | C17: Edwin Gutiérrez Zapana | D17: Alarcon Pablo Alejandro | E17: Entregado | F17: 46308 | G17: Word | H17: Sí | I17: Error en el Plan 2027: respondía con las categorías docentes en lugar de la modalidad que pide el Art. 12 de la Res. HCU 032/2025; ese texto se traslada al punto 11.2. Texto nuevo respaldado por el diagnóstico 2026: modalidad presencial y régimen anual (punto 6.1), turnos diurno y nocturno (punto 3.1) y plataforma virtual de apoyo (punto 7.1 g). Ya no requiere confirmación. | J17: 1
A18: 1.13 | B18: Otras características | C18: Edwin Gutiérrez Zapana | D18: Alarcon Pablo Alejandro | E18: Entregado | F18: 46308 | G18: Word | H18: Sí | I18: El Plan 2027 no tenía 1.13 y en el Plan 2024 estaba vacío. Contenido elaborado con los documentos base: acreditación Res. 09/2015 VI Conferencia Nacional Extraordinaria (membrete de la Res. HCF 1057/2026), Res. HCU 032/2025 (Arts. 5 y 16), Res. HCF 1057/2026 y documento de Misión, Visión y Perfil 2026 (Reunión Sectorial III-XIII, Res. 07/2024, IES). Error en la Res. HCF 1057/2026: en Vistos cita "Proyecto de Resolución ... N.º 269/202" (año incompleto) y en Considerando "N° 269/202"; debe ser 269/2026. Verificar la vigencia de la acreditación de 2015. ACTUALIZADO con la fuente terciaria (Plan de Desarrollo 2026-2030): la acreditación de 2015 está por renovar; la reacreditación CEUB y ARCU-SUR son metas del plan. | J18: 1
A19: 2. | B19: Antecedentes | C19: Sin asignar | D19: Sin asignar | E19: =IF(SUMPRODUCT(($J$20:$J$26=1)*($E$20:$E$26<>"No aplica"))=0,"No aplica",IF(SUMPRODUCT(($J$20:$J$26=1)*($E$20:$E$26="Entregado"))=SUMPRODUCT(($J$20:$J$26=1)*($E$20:$E$26<>"No aplica")),"Completo",IF(SUMPRODUCT(($J$20:$J$26=1)*($E$20:$E$26="Pendiente"))=SUMPRODUCT(($J$20:$J$26=1)*($E$20:$E$26<>"No aplica")),"Pendiente","En proceso"))) | F19: =SUMPRODUCT(($J$20:$J$26=1)*($E$20:$E$26="Entregado"))&" de "&SUMPRODUCT(($J$20:$J$26=1)*($E$20:$E$26<>"No aplica")) | G19: — | H19: — | J19: 0
A20: 2.1 | B20: Datos generales del programa/carrera | C20: Sin asignar | D20: Sin asignar | E20: Entregado | F20: 46308 | G20: Word | H20: Sí | I20: Fuentes: documento de la comisión (copia del Plan 2024), punto 1 ya trabajado, Res. HCF 1057/2026 (Director de Carrera) y diagnóstico (población estudiantil, docentes y personal). Como el párrafo de la comisión repetía el texto del punto 1.1, se reemplazó por un cuadro de datos generales para evitar duplicidad. Error en el documento de la comisión: nota interna "(COPIA DEL DOCUMENTO 2024)" dentro del texto; se eliminó. Error en el Plan 2024: el título "1. ANTECEDENTES / 1.1 DATOS GENERALES" estaba repetido dentro de 2.1 y el punto incluía los objetivos de la Carrera, que corresponden a 2.4. CORRECCIÓN (diagnóstico 2026): plan vigente Plan 2013 (antes decía Plan 2024); se agregaron 43 asignaturas y 6.000 horas, turnos diurno y nocturno, edificios, 3.247 inscritos totales (3.143 en La Paz y 104 en sedes), composición por género, estudiantes que trabajan, 82 docentes en ejercicio y 79 ítems de auxiliares. | J20: 1
A21: 2.2 | B21: Misión, visión de la carrera | C21: Sin asignar | D21: Sin asignar | E21: Entregado | F21: 46308 | G21: Word | H21: Sí | I21: Fuente priorizada: fuente terciaria, documento 1 (visión y misión), igual al documento base Misión, Visión y Perfil 2026. Se agregó 2.2.3 Valores, tomado del mismo documento base, para mantener la coherencia. La visión y la misión se conservaron textuales por ser texto socializado; solo en Valores se cambió el paréntesis "(IA, Big Data y automatización)" por redacción corrida. El paréntesis "(IA y analítica de datos)" de la misión se mantiene; si se desea quitarlo, debe hacerse también en el documento base. Error en el documento de la comisión: nota interna "(copia del documento recién socializado)" en el título. El Plan 2024 tenía otra visión y misión, ya reemplazadas. | J21: 1
A22: 2.3 | B22: Plan de desarrollo de la carrera | C22: Sin asignar | D22: Sin asignar | E22: Entregado | F22: 46308 | G22: Word | H22: Sí | I22: Fuente: fuente terciaria (Plan Estratégico de Desarrollo Institucional 2026-2030 de la Carrera), reescrita y resumida. Se quitaron los rasgos de redacción de IA (guiones largos, paréntesis, términos como "refundación", "baluarte" o "arquitectura programática"); la visión, la misión y los valores no se repitieron porque ya están en 2.2. Se armonizaron los cuatro ejes del plan con las cuatro áreas del PEI UMSA y con los seis ejes de los objetivos (2.4). ERRORES EN LA FUENTE: (1) atribuye al Art. 8 de la Res. HCU 032/2025 el "modelo humanista, flexible... por competencias", pero el Art. 8 trata la estructura de contenidos; se citó el Art. 12; (2) presenta como "brecha en inglés del 89 %" un dato que el diagnóstico registra como el 89 % de estudiantes que ve la demanda de idiomas y tecnología como amenaza; se corrigió; (3) líneas base sin respaldo, derivadas de otros porcentajes: inglés "11 %" (100 - 89), laboratorios "7 %" (100 - 93, que es una brecha de egresados, no de laboratorios), pasantías "12 %" y docentes capacitados "15 %" sin fuente; se reemplazaron por "Por establecer"; (4) unidades responsables que no existen en el organigrama (Jefatura de Estudios, Departamento de Idiomas, Unidad de Calidad Académica, Jefatura de Laboratorios); se asignaron a la Dirección de Carrera; (5) el nombre del plan es inconsistente: "Plan de Estudios CPA 2026" en la fuente y "Plan 2027" en otros documentos; (6) cita "ISSA 5000"; en español corresponde NIAS 5000. | J22: 1 | K22: PEI UMSA 2021-2025 con visión al 2030, Res. HCU 355/2023 (se mantiene en verde).
A23: 2.4 | B23: Objetivos del programa/carrera | C23: Sin asignar | D23: Sin asignar | E23: Entregado | F23: 46308 | G23: Word | H23: Sí | I23: Fuente priorizada: fuente terciaria, documento 2 (2.4.1, seis ejes), que es la versión más reciente: incluye "Código Internacional de Ética", "pasantías preprofesionales obligatorias" y "la incertidumbre". Cambios: "analítica de datos (Big Data)" se redactó "analítica de datos masivos", se completó el nombre del IESBA (Consejo de Normas Internacionales de Ética para Contadores) y se pasaron los rótulos a minúscula inicial. Error en el documento 2 de la fuente terciaria: las seis viñetas estaban dentro de un solo ítem; se separaron como incisos a-f. DIFERENCIA con el documento base Misión, Visión y Perfil 2026 (punto 3) y con el documento 1 de la fuente terciaria: estos dicen "pre-profesionales" sin "obligatorias" y "Código de Ética"; conviene actualizar el documento base para que coincida. Error en el documento 1 de la fuente terciaria: "pasantías pre-profesionales" con guion. | J23: 1
A24: 2.5 | B24: Características del programa/carrera | C24: Sin asignar | D24: Sin asignar | E24: Entregado | F24: 46308 | G24: Word | H24: Sí | I24: Fuente: Plan 2024 (1.3 Reseña histórica y 1.5 Unidades académicas); la comisión no incluyó este punto. Correcciones al Plan 2024: "culmino" por "culminó"; oración incompleta "El nuevo rol protagónico... que culmino con el golpe de estado", reescrita; "Carrera de Contaduría Auditoria ahora Contaduría Pública" corregido; frase colgante "Razón por la cual se dicta la siguiente resolución:" sin resolución, reemplazada por la remisión al punto 1.2; tildes faltantes en Auditoría y Maestría; título "2. Justificación del Diseño" fuera de lugar, eliminado. ACTUALIZAR las versiones de los programas de postgrado (datos del Plan 2024) y el estado del doctorado. La lista de reglamentos del Plan 2024 se traslada al punto 13.1. CORRECCIÓN (diagnóstico 2026, puntos 9.1 y 10): se reemplazó la lista de postgrado del Plan 2024, que tenía versiones desactualizadas, por los programas vigentes y los que se implementan en 2026; nombre completo del doctorado; datos del Instituto (320 h/mes, Director acéfalo desde 2022, sin personal administrativo). Error en el diagnóstico: "Diplomado en Auditoría Forense Virtual" se redactó "en modalidad virtual"; "esta de cargo" debe ser "está a cargo". | J24: 1
A25: 2.6 | B25: Organigrama del programa/carrera | C25: Sin asignar | D25: Sin asignar | E25: Entregado | F25: 46308 | G25: Word | H25: Sí | I25: Fuentes: organigrama (imagen) y descripción del documento de la comisión, igual al Plan 2024, y 2.6.1 Plantel administrativo del diagnóstico. Redacción ajustada y sin repeticiones. ERRORES EN LA IMAGEN DEL ORGANIGRAMA (no se pueden corregir en el Word, hay que rehacer la imagen): "KARDIXTA" por "KARDEXISTA", "TRANCRIPTOR" por "TRANSCRIPTOR"; dice "JEFATURA DE CARRERA" mientras el texto dice "Dirección de Carrera"; muestra la Unidad de Postgrado al mismo nivel que el Instituto, mientras el texto dice que depende del Instituto. Incoherencia: el texto del Plan 2024 sobre la Jefatura de Dirección hablaba de "dos secretarias, un profesional contable...", que no coincide con las tablas de personal; se redactó sin cantidades. En las tablas: "Kardixtas I" corregido a "Kardexista I", "Centro de Computo" a "Cómputo", "(item)" a "ítem", y se unificaron las filas repetidas de porteros y becarios. Nombre del Instituto unificado según la Res. HCU 457/2004. CORRECCIÓN POSTERIOR: la sigla PETAEG del diagnóstico se unificó a PETAENG (Plan Excepcional de Titulación para Antiguos Estudiantes No Graduados), como en la comisión y el Plan 2024. | J25: 1
A26: 2.7 | B26: Estadísticas del programa/carrera | C26: Sin asignar | D26: Sin asignar | E26: Entregado | F26: 46308 | G26: Word | H26: Sí | I26: Fuente: estadísticas del diagnóstico 2021-2025 (documento de la comisión), que reemplazan a las del Plan 2024. ERRORES CORREGIDOS: (1) se decía que los inscritos "se incrementaron en 378 equivalentes al 13,32 %", dato copiado del Plan 2024 (periodo 2019-2023); con los datos 2021-2025 bajan de 3.152 a 3.143 (-0,29 %); (2) 1.140/4.283 = 26,62 %, no 26,61 %; (3) en el Cuadro 11 la fila Paralelos repetía el promedio en las columnas PEIPAP; se reorganizó el cuadro; (4) el texto del Cuadro 11 decía "relativamente estable" y a la vez "se ha incrementado significativamente"; se aclaró que crece el total de inscripciones y no el promedio; (5) la fuente "Sistema de Registro Universitario -- SSA y Sistema de Seguimiento Académico - SSA" repetía la sigla. Se calculó y agregó que el examen de grado representa el 69,7 % de los titulados 2021-2025. INCOHERENCIAS POR ACLARAR con la comisión: (a) el Cuadro 5 da 82 docentes y los Cuadros 4 y 7 dan 183; se interpretó 183 como designaciones y no personas; la nota "El total de docentes corresponde a materias de 32 Hrs" no es clara y se omitió; (b) matriculados 2023: el diagnóstico dice 4.447 y el Plan 2024 dice 4.385; (c) titulados 2021: DSIE da 441 y Kárdex (Plan 2024) daba 514; (d) CEIPAP 2023: 22.636 frente a 22.641 en el Plan 2024. Se renumeraron los cuadros del 1 al 11 dentro del punto 2. CORRECCIÓN (diagnóstico 2026, puntos 3.1, 3.2, 3.3 y 11): se agregaron los inscritos totales, la composición por género, los estudiantes trabajadores, los nuevos inscritos 2023-2025, los estudiantes con 7 a 9 años de permanencia y las auxiliaturas. El diagnóstico tiene los mismos errores de los Cuadros 9 a 11 señalados arriba: "se incrementaron en 378, 13,32 %", 26,61 % y la fuente con la sigla SSA repetida. Además, en el punto 6.4 d) habla de "183 docentes disponibles" y en el Cuadro 6 de 82 docentes. | J26: 1
A27: 3. | B27: Justificación de la innovación curricular (solo para niveles de diseño, rediseño y ajustes) | C27: Alberto Mendoza Mendoza | D27: Ayrton Javier Quisbert Fernandez | E27: =IF(SUMPRODUCT(($J$28:$J$32=1)*($E$28:$E$32<>"No aplica"))=0,"No aplica",IF(SUMPRODUCT(($J$28:$J$32=1)*($E$28:$E$32="Entregado"))=SUMPRODUCT(($J$28:$J$32=1)*($E$28:$E$32<>"No aplica")),"Completo",IF(SUMPRODUCT(($J$28:$J$32=1)*($E$28:$E$32="Pendiente"))=SUMPRODUCT(($J$28:$J$32=1)*($E$28:$E$32<>"No aplica")),"Pendiente","En proceso"))) | F27: =SUMPRODUCT(($J$28:$J$32=1)*($E$28:$E$32="Entregado"))&" de "&SUMPRODUCT(($J$28:$J$32=1)*($E$28:$E$32<>"No aplica")) | G27: — | H27: — | J27: 0
A28: 3.1 | B28: Análisis de resultados obtenidos con anteriores planes de estudio (descripción estadística y cualitativa) | C28: Alberto Mendoza Mendoza | D28: Ayrton Javier Quisbert Fernandez | E28: Entregado | F28: 46308 | G28: Word | H28: Sí | I28: Fuente principal: documento de la comisión (3.1), con el Plan 2024 y el diagnóstico 2026 como respaldo. ACTUALIZACIÓN: la comisión usaba series 2018-2023 (Centro de Cómputo y Kárdex) y pedía actualizarlas; se reemplazaron por las del diagnóstico 2026: matrícula 2021-2025, titulados 2021-2025 DSIE (examen de grado 69,73 %, trabajo dirigido 14,58 %, tesis 0,16 %), dedicación docente 2026 (2 cargas de tiempo completo de 108, 58,33 % con carga mínima), interinos en Atestación 73,33 % y 106 estudiantes por paralelo en 2026. Se quitó la afirmación "concentración creciente en el examen", porque con los datos 2021-2025 el examen baja de 78,2 % a 68,6 %. Se mantuvo la observación técnica de la comisión sobre los porcentajes erróneos del Cuadro 4 del Documento 2013. Error de la comisión: el Cuadro 2 decía "Desarrollo y Comportamiento Organizacional"; el diagnóstico dice "Desarrollo Organizacional y Comportamiento Organizacional". "Álgebra y Programación Lineales" se corrigió a "Lineal". Del diagnóstico quedan pendientes los errores anotados antes (caída de matrícula con tres cifras distintas, entre otros); no se usaron esas cifras. | J28: 1
A29: 3.2 | B29: Análisis de las políticas y normas (internacionales, nacionales y universitarias) | C29: Alberto Mendoza Mendoza | D29: Ayrton Javier Quisbert Fernandez | E29: Entregado | F29: 46308 | G29: Word | H29: Sí | I29: Fuentes: comisión (3.2, completo) y fuente terciaria (3.2.1: procedimiento con las Res. HCF 1057/2026 y 1126/2026). INCOHERENCIA: la fuente terciaria dice que la Asamblea se realizó el 8/09/2026, pero la Res. HCF 1057/2026 la convoca para el 4/09/2026; se dejó la fecha de la resolución. VERIFICAR el número y la fecha de la Res. HCF 1126/2026 (solo figura en la fuente terciaria). Terminología unificada: la comisión usa "NIE" y la fuente terciaria "IES"; se usa IES en todo el documento. ISSA 5000 se nombra "NIAS 5000" en español (la comisión decía NIEA 5000). Se eliminó el Cuadro 16 de la comisión (NIE e implicancia), porque se fusionó con la tabla de la fuente terciaria en el Cuadro 30 (3.5.4). | J29: 1
A30: 3.3 | B30: Análisis del contexto económico, estudio de mercado laboral e inserción laboral | C30: Alberto Mendoza Mendoza | D30: Ayrton Javier Quisbert Fernandez | E30: Entregado | F30: 46308 | G30: Word | H30: Sí | I30: Fuente: comisión (3.3) y verificación directa en el informe Ipsos CIESMORI. CIFRAS VERIFICADAS EN IPSOS (láminas 18, 19, 38 y 39): Contaduría tiene 52 % dependientes, 31 % independientes o consultores y 14 % desempleados; el 41 % que usan el documento de Misión, Visión y Perfil, el diagnóstico y el Plan de Desarrollo corresponde a Economía. La "brecha del 93 %" de esos documentos es en realidad el porcentaje de egresados que considera "totalmente necesarias" las habilidades tecnológicas básicas; la brecha real es de 43 pp (98 % necesaria frente a 55 % aplicada) y de 51 pp en emergentes. Lo mismo ocurre con "gestión del tiempo 81 %" y "pensamiento crítico 78 %", que son valores de "totalmente necesaria"; las brechas son de 35 y 25 pp. Se corrigió también el punto 2.3. PENDIENTE: la propia comisión pide contrastar con los documentos originales las cifras macroeconómicas de 2026 (FMI, Banco Mundial, INE, BCB), que tomó de la prensa. | J30: 1
A31: 3.4 | B31: Análisis del contexto de cambios y tendencias de la ciencia y tecnología a nivel global | C31: Humberto Quintanilla Muñoz | D31: Beymar Adalid Paucara Marquez | E31: Entregado | F31: 46308 | G31: Word | H31: Sí | I31: Fuente: comisión (3.4). Solo cambió la redacción: se quitaron guiones largos y negritas excesivas, y los términos en inglés se tradujeron cuando hay equivalente (RPA: automatización robótica de procesos; ERP: sistemas de gestión empresarial). | J31: 1
A32: 3.5 | B32: Contextualización de la oferta curricular en la realidad nacional e internacional | C32: Humberto Quintanilla Muñoz | D32: Beymar Adalid Paucara Marquez | E32: Entregado | F32: 46308 | G32: Word | H32: Sí | I32: Fuentes: comisión (3.5) y fuente terciaria (3.5.1, tabla IES 1 a IES 8, fusionada en el Cuadro 30). ERROR GRAVE DE LA COMISIÓN CORREGIDO: afirmaba que la UMSA otorga el título de "Auditor Financiero" y que es la única del SUB que no otorga el de Contador Público Autorizado. Desde la Res. HCU 438/2012 el título en provisión nacional es Contador Público Autorizado (punto 1.10). Se corrigieron los Cuadros 17, 29 y 31 y el texto: lo desalineado es el perfil de egreso, no el título. Error de la comisión: en el Cuadro 31, "Salidas intermedias: Ausentes" en el Plan 2013; existe el Técnico Universitario Superior (Res. HCU 290/2016). Se agregó el dato del rango de horas SUB (4.500 a 6.000) del diagnóstico. Se trasladaron al punto 11 (implementación) y al 16.2 los Cuadros 33 a 35 de la comisión (paralelos requeridos, fases de implementación y riesgos), y se omitió el Cuadro 36 (verificación de cumplimiento del Art. 12), que es control interno. La comisión numeraba "3.6" la síntesis; el índice no tiene 3.6, así que pasó a 3.5.5. | J32: 1
A33: 4. | B33: Aspectos académicos | C33: Freddy Huanca Mamani | D33: Katherin Fabiola Ali Quispe | E33: =IF(SUMPRODUCT(($J$34:$J$71=1)*($E$34:$E$71<>"No aplica"))=0,"No aplica",IF(SUMPRODUCT(($J$34:$J$71=1)*($E$34:$E$71="Entregado"))=SUMPRODUCT(($J$34:$J$71=1)*($E$34:$E$71<>"No aplica")),"Completo",IF(SUMPRODUCT(($J$34:$J$71=1)*($E$34:$E$71="Pendiente"))=SUMPRODUCT(($J$34:$J$71=1)*($E$34:$E$71<>"No aplica")),"Pendiente","En proceso"))) | F33: =SUMPRODUCT(($J$34:$J$71=1)*($E$34:$E$71="Entregado"))&" de "&SUMPRODUCT(($J$34:$J$71=1)*($E$34:$E$71<>"No aplica")) | G33: — | H33: — | J33: 0
A34: 4.1 | B34: Fundamentos curriculares | C34: Freddy Huanca Mamani | D34: Katherin Fabiola Ali Quispe | E34: =IF(SUMPRODUCT(($J$35:$J$39=1)*($E$35:$E$39<>"No aplica"))=0,"No aplica",IF(SUMPRODUCT(($J$35:$J$39=1)*($E$35:$E$39="Entregado"))=SUMPRODUCT(($J$35:$J$39=1)*($E$35:$E$39<>"No aplica")),"Completo",IF(SUMPRODUCT(($J$35:$J$39=1)*($E$35:$E$39="Pendiente"))=SUMPRODUCT(($J$35:$J$39=1)*($E$35:$E$39<>"No aplica")),"Pendiente","En proceso"))) | F34: =SUMPRODUCT(($J$35:$J$39=1)*($E$35:$E$39="Entregado"))&" de "&SUMPRODUCT(($J$35:$J$39=1)*($E$35:$E$39<>"No aplica")) | G34: — | H34: — | J34: 0
A35: 4.1.1 | B35: Fundamentos epistemológicos | C35: Freddy Huanca Mamani | D35: Katherin Fabiola Ali Quispe | E35: Entregado | F35: 46308 | G35: Word | H35: Sí | I35: Fuente: fuente terciaria (Partes Complementarias y 4.1). Se agregó la ampliación epistemológica del objeto (sostenibilidad), tomada del punto 3.4 de la comisión. Error en la fuente: "entorno organización dinámico" por "organizacional". | J35: 1
A36: 4.1.2 | B36: Fundamentos sociológicos antropológicos | C36: Freddy Huanca Mamani | D36: Katherin Fabiola Ali Quispe | E36: Entregado | F36: 46308 | G36: Word | H36: Sí | I36: Fuente: fuente terciaria, con las cifras corregidas: "brecha del 93 %" por 43 y 51 pp (ver 3.3); "la principal barrera (25 %)" por "la segunda barrera" (la primera son las habilidades blandas, 26 %); y "el 88 % exige pasantías e inglés" se separó: 88 % pasantías y 89 % ven como amenaza la demanda de idiomas y tecnología. Se agregó el contexto sociocultural (modelo económico plural, informalidad, estudiante trabajador, 56 % mujeres) del diagnóstico y del punto 3. | J36: 1
A37: 4.1.3 | B37: Fundamentos psicológicos | C37: Jorge Cespedes Esteves | D37: Taiz Alejandra Cano Chuyma | E37: Entregado | F37: 46308 | G37: Word | H37: Sí | I37: Fuentes: fuente terciaria (roles del docente y del estudiante) y Plan 2024 (pedagogía dialogante constructivista, resumida). La fuente terciaria ponía como "fundamentos psicológicos" solo el marco normativo y los roles, sin fundamento psicológico; se agregó el enfoque constructivista y el aprendizaje significativo del Plan 2024. | J37: 1
A38: 4.1.4 | B38: Fundamentos educativos | C38: Jorge Cespedes Esteves | D38: Taiz Alejandra Cano Chuyma | E38: Entregado | F38: 46308 | G38: Word | H38: Sí | I38: Fuente: fuente terciaria. Para no duplicar, la tabla IES 1 a IES 8 queda solo en el punto 3.5.4 (Cuadro 30) y aquí se la remite. Error en la fuente: la tabla "Saber Conocer" tenía una fila suelta "Integrado" y la abreviatura "CGE NIA" sin separar. | J38: 1
A39: 4.1.5 | B39: Fundamentos axiológicos | C39: Jorge Cespedes Esteves | D39: Taiz Alejandra Cano Chuyma | E39: Entregado | F39: 46308 | G39: Word | H39: Sí | I39: Fuentes: fuente terciaria (4.1.5) y Plan de Desarrollo (tabla de impacto de los valores en el perfil). Para no repetir la definición de los valores de 2.2.3, aquí se usa la tabla de impacto. Se quitaron expresiones como "compromiso inquebrantable". | J39: 1
A40: 4.2 | B40: Referentes disciplinares | C40: Hinojosa | D40: Melany Sarah Chavez Condori | E40: =IF(SUMPRODUCT(($J$41:$J$47=1)*($E$41:$E$47<>"No aplica"))=0,"No aplica",IF(SUMPRODUCT(($J$41:$J$47=1)*($E$41:$E$47="Entregado"))=SUMPRODUCT(($J$41:$J$47=1)*($E$41:$E$47<>"No aplica")),"Completo",IF(SUMPRODUCT(($J$41:$J$47=1)*($E$41:$E$47="Pendiente"))=SUMPRODUCT(($J$41:$J$47=1)*($E$41:$E$47<>"No aplica")),"Pendiente","En proceso"))) | F40: =SUMPRODUCT(($J$41:$J$47=1)*($E$41:$E$47="Entregado"))&" de "&SUMPRODUCT(($J$41:$J$47=1)*($E$41:$E$47<>"No aplica")) | G40: — | H40: — | I40: Revisión final: "En conclusión" se cambió por "Así" para evitar una muletilla propia de textos generados. | J40: 0
A41: 4.2.1 | B41: Problemas que serán abordados por el profesional | C41: Hinojosa | D41: Melany Sarah Chavez Condori | E41: Entregado | F41: 46308 | G41: Word | H41: Sí | I41: Fuente: fuente terciaria (Partes Complementarias 4.2.1). Corregido "brecha digital (93 %)" y "ISSA 5000 / NIEA 3000" (se usa NIAS 5000). Se agregaron la informalidad y la recesión del punto 3.3. | J41: 1
A42: 4.2.2 | B42: Prospectiva de la profesión | C42: Hinojosa | D42: Melany Sarah Chavez Condori | E42: Entregado | F42: 46308 | G42: Word | H42: Sí | I42: Fuentes: fuente terciaria (4.2.2) y documento base Misión, Visión y Perfil 2026 (5.1: imperativo ético). Se agregó el dato del WEF del punto 3.4 para sustentar la prospectiva. | J42: 1
A43: 4.2.3 | B43: Caracterización de la práctica de la profesión (áreas de acción y funciones) | C43: Hinojosa | D43: Melany Sarah Chavez Condori | E43: Entregado | F43: 46308 | G43: Word | H43: Sí | I43: Fuentes: fuente terciaria 4.2_1 (entorno: roles profesional, organizacional e individual; sistema de acciones y herramientas) y 4.2 (áreas de desempeño, en el Cuadro 1). CORREGIDO: "41 % ejerce de forma independiente" por 31 % (Ipsos, lámina 18). Los tres pilares que la fuente ponía en 4.2.3 (Partes Complementarias) se trasladaron a 4.2.5 (objetivos específicos), como en el documento base, para no duplicar. | J43: 1
A44: 4.2.4 | B44: Objeto de la profesión | C44: Hinojosa | D44: Melany Sarah Chavez Condori | E44: Entregado | F44: 46308 | G44: Word | H44: Sí | I44: Fuente: fuente terciaria 4.2_1 y documento base 5.2. El ciclo de cinco fases del sistema de información se pasó a una tabla (Cuadro 2) para hacerlo más legible. | J44: 1
A45: 4.2.5 | B45: Objetivo de la profesión | C45: Hinojosa | D45: Melany Sarah Chavez Condori | E45: Entregado | F45: 46308 | G45: Word | H45: Sí | I45: Fuente: fuente terciaria y documento base 5.3. CORREGIDO: "NIEA 2400" por "NIER 2400" (revisión de estados financieros, ISRE 2400). | J45: 1
A46: 4.2.6 | B46: Competencias específicas de la profesión | C46: Hinojosa | D46: Melany Sarah Chavez Condori | E46: Entregado | F46: 46308 | G46: Word | H46: Sí | I46: Fuente: fuente terciaria 4.2_1 y documento base 5.6. CORREGIDO: "NICSC" por "NICSP"; coma faltante en "NCGA en Bolivia Normas NIIF"; "93 % de los egresados reporta brechas" por 43 a 51 pp; "brecha del 78 %" en pensamiento crítico por 25 pp; "principal actitud demandada" (adaptabilidad) se reemplazó por el dato real de Ipsos (70 % la recibió con baja frecuencia); "&amp;" en la matriz. Se quitaron "de forma intransigente" e "idoneidad ética inquebrantable". | J46: 1
A47: 4.2.7 | B47: Perfil profesional | C47: Hinojosa | D47: Melany Sarah Chavez Condori | E47: Entregado | F47: 46308 | G47: Word | H47: Sí | I47: Fuente: fuente terciaria (4.2.7, declaración sintética y atributos). Se mantuvo la declaración del perfil (socializada) con mínimos ajustes: "tales como:" por "como" y "analítica de Big Data" por "analítica de datos" (en Partes Complementarias decía "Big Data" y en 4.2 no). Error en la fuente: "Resolución Nª 07/2024" por N.º; "sector público y privado.;" con doble puntuación. "Certificaciones intermedias modulares" se cambió por "grados intermedios", porque el plan no define certificaciones modulares. | J47: 1
A48: 4.3 | B48: Plan de estudios propuesto | C48: Mendoza Elias | D48: Gisela Leila Fernandez Cazas | E48: =IF(SUMPRODUCT(($J$49:$J$53=1)*($E$49:$E$53<>"No aplica"))=0,"No aplica",IF(SUMPRODUCT(($J$49:$J$53=1)*($E$49:$E$53="Entregado"))=SUMPRODUCT(($J$49:$J$53=1)*($E$49:$E$53<>"No aplica")),"Completo",IF(SUMPRODUCT(($J$49:$J$53=1)*($E$49:$E$53="Pendiente"))=SUMPRODUCT(($J$49:$J$53=1)*($E$49:$E$53<>"No aplica")),"Pendiente","En proceso"))) | F48: =SUMPRODUCT(($J$49:$J$53=1)*($E$49:$E$53="Entregado"))&" de "&SUMPRODUCT(($J$49:$J$53=1)*($E$49:$E$53<>"No aplica")) | G48: — | H48: — | J48: 0
A49: 4.3.1 | B49: Modelo curricular | C49: Mendoza Elias | D49: Gisela Leila Fernandez Cazas | E49: Entregado | F49: 46308 | G49: Word | H49: Sí | I49: Fuente: comisión (4.3.1, completa). Corregido "brecha tecnológica del 93 %". Se agregó la Res. HCF 1057/2026. VERIFICAR: la comisión afirma que las IES revisadas están "vigentes desde el 1 de julio de 2026"; se omitió la fecha hasta confirmarla. | J49: 1
A50: 4.3.2 | B50: Principios del modelo | C50: Mendoza Elias | D50: Gisela Leila Fernandez Cazas | E50: Entregado | F50: 46308 | G50: Word | H50: Sí | I50: Fuente: comisión. CORREGIDO: "c) Integridad" por "Integralidad" (así dice el Art. 12 de la Res. HCU 032/2025). Se eliminó la marca interna "[Verificar]" sobre "asignaturas electivas y certificaciones modulares"; la malla 2027 no tiene electivas, así que se redactó con los grados intermedios y la graduación por diplomado. | J50: 1
A51: 4.3.3 | B51: Objetivo general del diseño, rediseño o ajuste | C51: Madeny | D51: Melisa Canaviri | E51: Entregado | F51: 46308 | G51: Word | H51: Sí | I51: Fuentes: comisión (objetivo general) y fuente terciaria (4.3.3: alcance y cinco campos del nuevo paradigma). Corregido "(NIEA 3000 y NIAS 5000 del IAASB) adoptadas plenamente en Bolivia": no consta su adopción plena en Bolivia, se quitó. | J51: 1
A52: 4.3.4 | B52: Objetivos específicos del diseño, rediseño o ajuste | C52: Madeny | D52: Melisa Canaviri | E52: Entregado | F52: 46308 | G52: Word | H52: Sí | I52: Fuentes: comisión (nueve objetivos, en tabla) y fuente terciaria (propósitos formativos). CORREGIDO: "brecha del 93 %", "gestión del tiempo (81 %) y pensamiento crítico (78 %)" y "NIEA 5000". | J52: 1
A53: 4.3.5 | B53: Duración de la carrera en años o semestres | C53: Madeny | D53: Melisa Canaviri | E53: Entregado | F53: 46308 | G53: Word | H53: Sí | I53: Fuente: comisión. Se eliminó la duplicación del documento de la comisión (los ciclos y el párrafo de créditos aparecían dos veces). Se agregaron los grados intermedios (coherencia con los puntos 1.6 y 5.4). | J53: 1
A54: 4.4 | B54: Estructura curricular | C54: Comisión Supra | D54: Comisión Supra | E54: =IF(SUMPRODUCT(($J$55:$J$58=1)*($E$55:$E$58<>"No aplica"))=0,"No aplica",IF(SUMPRODUCT(($J$55:$J$58=1)*($E$55:$E$58="Entregado"))=SUMPRODUCT(($J$55:$J$58=1)*($E$55:$E$58<>"No aplica")),"Completo",IF(SUMPRODUCT(($J$55:$J$58=1)*($E$55:$E$58="Pendiente"))=SUMPRODUCT(($J$55:$J$58=1)*($E$55:$E$58<>"No aplica")),"Pendiente","En proceso"))) | F54: =SUMPRODUCT(($J$55:$J$58=1)*($E$55:$E$58="Entregado"))&" de "&SUMPRODUCT(($J$55:$J$58=1)*($E$55:$E$58<>"No aplica")) | G54: — | H54: — | J54: 0
A55: 4.4.1 | B55: Descripción de la organización curricular (organización de la asignatura por áreas o ejes de conocimiento) | C55: Comisión Supra | D55: Comisión Supra | E55: Entregado | F55: 46308 | G55: Word | H55: Sí | I55: Fuente: fuente terciaria (4.4.1). CORREGIDO: contextuales 33,33 % (decía 32,33 %); "480 nrs"; letra inicial faltante ("e acuerdo"); la tabla tenía las áreas desalineadas con sus cifras. Se unificaron los ejes transversales: la comisión (4.3.1) tenía cinco y la fuente terciaria cuatro; se usaron los cinco de la comisión con las asignaturas de la fuente terciaria. INCOHERENCIA: el Plan de Desarrollo (2.3) usaba otros nombres para CPA-505, 506 y 508; se corrigió el 2.3 según la malla. | J55: 1
A56: 4.4.2 | B56: Mapa de competencia (competencia y unidades de competencia) | C56: Comisión Supra | D56: Comisión Supra | E56: Parcial | F56: 46308 | G56: Word | H56: Sí | I56: Fuente: fuente terciaria (atributos del egresado). La fuente no presentaba la competencia global ni las competencias por área que pide el Art. 8; se redactaron como PROPUESTA a partir del perfil y de la descripción de áreas, y se indica que las unidades de competencia por asignatura van en los planes de asignatura (4.5). VALIDAR la redacción con la comisión. | J56: 1
A57: 4.4.3 | B57: Malla curricular (siglas, nombres de la asignatura, carga horaria, créditos, prerrequisitos) por ciclos y semestres/año | C57: Comisión Supra | D57: Comisión Supra | E57: Entregado | F57: 46308 | G57: Word | H57: Sí | I57: Fuente: fuente terciaria (malla 2027). Verificada: 43 asignaturas, 150 h/semana, 6.000 h, 16/13/3/3/3/5 por área, coherente con el Cuadro 1. La fuente no tenía créditos; se calcularon con el método de la comisión (4.3.5): hora académica de 45 min, 1 hora autónoma por hora presencial, 30 h por crédito; resultado: asignatura de 4 h/sem = 8 créditos y de 2 h/sem = 4; total 300. VALIDAR el método. Nombre corregido: "Auditoría de Proyectos Público y Privado" por "Públicos y Privados". OBSERVACIÓN: la malla 2027 es casi igual a la del Plan 2024 (que ya tenía CPA-204 y CPA-406 Ética e Independencia); confirmar si el Plan 2024 fue un ajuste aprobado. | J57: 1
A58: 4.4.4 | B58: Cuadro de asignación de cargas horarias presenciales, no presenciales, (según formato) | C58: Comisión Supra | D58: Comisión Supra | E58: Entregado | F58: 46308 | G58: Word | H58: Sí | I58: Fuente: fuente terciaria (4.4.4.1), ampliada con horas presenciales, no presenciales y créditos. Error en la fuente: primer año 17,34 % (correcto: 17,33 %). Los créditos por año quedan en 52, 60, 64, 64 y 60 (total 300); el normalizador UMSA indica 60 por año, así que la comisión debe decidir si redistribuye la carga. | J58: 1
A59: 4.5 | B59: Planes de asignatura (descripción de la asignatura) | C59: Subcomisiones por área | D59: Subcomisiones por área | E59: =IF(SUMPRODUCT(($J$60:$J$68=1)*($E$60:$E$68<>"No aplica"))=0,"No aplica",IF(SUMPRODUCT(($J$60:$J$68=1)*($E$60:$E$68="Entregado"))=SUMPRODUCT(($J$60:$J$68=1)*($E$60:$E$68<>"No aplica")),"Completo",IF(SUMPRODUCT(($J$60:$J$68=1)*($E$60:$E$68="Pendiente"))=SUMPRODUCT(($J$60:$J$68=1)*($E$60:$E$68<>"No aplica")),"Pendiente","En proceso"))) | F59: =SUMPRODUCT(($J$60:$J$68=1)*($E$60:$E$68="Entregado"))&" de "&SUMPRODUCT(($J$60:$J$68=1)*($E$60:$E$68<>"No aplica")) | G59: — | H59: — | J59: 0
A60: 4.5-a | B60: Subcomisión Información Financiera General | C60: Gonzalo Terán Gandarillas / Edwin Gutiérrez Zapana | D60: Jose David Huanca Callizaya / Elva Danitza Cachaga Alanoca | E60: Entregado | F60: 46309 | G60: Word | H60: Revisado | I60: Observado. 6 itinerarios (CPA-101, 201, 202, 203, 301, 302). Estado: 5 ajustes menores y CPA-301 requiere ajustes. Sin cambios de nombre. Horas llenadas en los 6; CPA-301 sin columna «En clase». El informe de la subcomisión declara cambios en CPA-201 que el itinerario solo refleja en parte. Revisado en «4.5 Informe de revisión de los itinerarios formativos.docx» (matriz de cumplimiento de la guía, resumen y detalle por asignatura). Correcciones ortográficas y de forma con control de cambios en la carpeta «4.5 Itinerarios corregidos». | J60: 1
A61: 4.5-b | B61: Subcomisión Información Financiera Especializada | C61: Edith Esther López Mamani / Guido Rogelio Yujra Segales | D61: Leonardo Fabio Oblitas Flores / Marco Marcelo Escobar Bozo | E61: Entregado | F61: 46309 | G61: Word | H61: Revisado | I61: Observado. 7 itinerarios (CPA-303, 304, 401 a 405). Estado: CPA-303 y CPA-404 requieren reformulación parcial; CPA-402 y CPA-403 requieren ajustes; el resto, ajustes menores. Cambios de nombre: CPA-304 («Presupuesto y Contabilidad Gubernamental») y sigla CPA-406 dentro de CPA-405. CPA-404 entregado con 992 cambios controlados sin resolver. Revisado en «4.5 Informe de revisión de los itinerarios formativos.docx» (matriz de cumplimiento de la guía, resumen y detalle por asignatura). Correcciones ortográficas y de forma con control de cambios en la carpeta «4.5 Itinerarios corregidos». | J61: 1
A62: 4.5-c | B62: Subcomisión Servicios de Aseguramiento y No Aseguramiento | C62: Martin Calani / Víctor Delfín Pelaez Mariscal | D62: Valery Tatiana Chuquimia Rojas / Rocio del Alba Flores Colque | E62: Entregado | F62: 46309 | G62: Word | H62: Revisado | I62: Observado. 11 itinerarios (CPA-406 a 408, 501 a 504, 506 a 509). Estado: CPA-407 requiere reformulación parcial; CPA-408, 502, 504, 506, 507 y 508 requieren ajustes. Cambios de nombre sin justificar: CPA-408, 506, 507 y 508. CPA-504 tiene pegado en la bibliografía un mensaje de un asistente de IA. CPA-507 está todo en fuente Inter. Revisado en «4.5 Informe de revisión de los itinerarios formativos.docx» (matriz de cumplimiento de la guía, resumen y detalle por asignatura). Correcciones ortográficas y de forma con control de cambios en la carpeta «4.5 Itinerarios corregidos». | J62: 1
A63: 4.5-d | B63: Subcomisión Sistemas | C63: Juan Carlos Lea Plaza Lopez / Miguel Cotaña Mier | D63: Pillco Yana Camila / Zambrana Barrionuevo Jheferson | E63: Entregado | F63: 46309 | G63: Word | H63: Revisado | I63: Observado. 3 itinerarios (CPA-102, 305, 505). Estado: CPA-305 requiere reformulación parcial (no desarrolla ERP ni análisis de datos), CPA-102 requiere ajustes, CPA-505 ajustes menores. Cambios de nombre: CPA-102 y CPA-305. Créditos llenados en los 3. Sin informe de subcomisión. Revisado en «4.5 Informe de revisión de los itinerarios formativos.docx» (matriz de cumplimiento de la guía, resumen y detalle por asignatura). Correcciones ortográficas y de forma con control de cambios en la carpeta «4.5 Itinerarios corregidos». | J63: 1
A64: 4.5-e | B64: Subcomisión Administración | C64: Juan Carlos Sánchez Bolaños / Orlando Alfato | D64: Luz Alejandra Chavez Conde / Nicol Tatiana Cornejo Choque | E64: Entregado | F64: 46309 | G64: PDF | H64: Revisado | I64: Observado. 3 itinerarios entregados en PDF, no en Word; deben entregarse en Word editable. Estado: ADM-201 requiere reformulación parcial, ADM-301 requiere ajustes, ADM-101 ajustes menores. Correcciones de ADM-201 listadas en el Anexo A del informe. Sin informe de subcomisión. Revisado en «4.5 Informe de revisión de los itinerarios formativos.docx» (matriz de cumplimiento de la guía, resumen y detalle por asignatura). Correcciones ortográficas y de forma con control de cambios en la carpeta «4.5 Itinerarios corregidos». | J64: 1
A65: 4.5-f | B65: Subcomisión Derecho | C65: Walter Marcelo Torrez Quispe / Ricardo Ramiro Tola Fernández | D65: Anthony Alexander Espinoza Gutierrez / Fernanda Camila Gonzales Quispe | E65: Entregado | F65: 46309 | G65: Word | H65: Revisado | I65: Observado. 3 itinerarios (DER-101, 102, 201). Estado: DER-201 requiere ajustes; el resto, ajustes menores. Sin cambios de nombre. Sin informe de subcomisión. Revisado en «4.5 Informe de revisión de los itinerarios formativos.docx» (matriz de cumplimiento de la guía, resumen y detalle por asignatura). Correcciones ortográficas y de forma con control de cambios en la carpeta «4.5 Itinerarios corregidos». | J65: 1
A66: 4.5-g | B66: Subcomisión Economía | C66: Luis Medina Rivero / Espejo Davalos Juvenal | D66: Carla Isabel Huiza Callisaya / Jhamil Sander Quispe Mamani | E66: Entregado | F66: 46309 | G66: Word | H66: Revisado | I66: Observado. 3 itinerarios (ECO-101, 201, 301). Estado: ECO-301 requiere ajustes; el resto, ajustes menores. Sin cambios de nombre. Los cambios que declara el informe de la subcomisión quedaron aplicados solo en parte. Revisado en «4.5 Informe de revisión de los itinerarios formativos.docx» (matriz de cumplimiento de la guía, resumen y detalle por asignatura). Correcciones ortográficas y de forma con control de cambios en la carpeta «4.5 Itinerarios corregidos». | J66: 1
A67: 4.5-h | B67: Subcomisión Metodología de la Investigación | C67: Sigfrido Ariel Burgoa Cortez / Jorge Cespedes Esteves | D67: Taiz Alejandra Cano Chuyma | E67: Entregado | F67: 46309 | G67: Word | H67: Revisado | I67: Observado. 2 itinerarios (CPA-204, 510). Estado: CPA-510 requiere ajustes (sigla HTC, rótulo «Clases», sin trabajo dirigido, diplomado ni PETAENG); CPA-204, ajustes menores y único que dejó las horas en blanco. Sin informe de subcomisión. Revisado en «4.5 Informe de revisión de los itinerarios formativos.docx» (matriz de cumplimiento de la guía, resumen y detalle por asignatura). Correcciones ortográficas y de forma con control de cambios en la carpeta «4.5 Itinerarios corregidos». | J67: 1
A68: 4.5-i | B68: Subcomisión Matemática | C68: Darío David Yujra Crespo / Domingo Julio Pérez Centellas | D68: Eileen Juarez Flores / Jaime Andres Patty Lazcano | E68: Entregado | F68: 46309 | G68: Word | H68: Revisado | I68: Observado. 5 itinerarios (MAT-101, 102, 201, 301, 401). Estado: MAT-201 y MAT-301 requieren reformulación parcial, MAT-401 requiere ajustes, MAT-101 y MAT-102 ajustes menores. Cambio de nombre: MAT-201 («Álgebra y Programación Lineales»). Sin informe de subcomisión. Revisado en «4.5 Informe de revisión de los itinerarios formativos.docx» (matriz de cumplimiento de la guía, resumen y detalle por asignatura). Correcciones ortográficas y de forma con control de cambios en la carpeta «4.5 Itinerarios corregidos». | J68: 1
A69: 4.6 | B69: Estrategias de aprendizaje y estrategias de enseñanza (estrategias, métodos, tipos, recursos) | C69: Sin asignar | D69: Sin asignar | E69: Entregado | F69: 46308 | G69: Word | H69: Sí | I69: Fuentes: Plan 2024 (4.6: métodos y medios, que estaban duplicados en el documento), comisión (4.3.1: modelo pedagógico), Plan 2024 (4.1.4: componentes del modelo dialogante) y diagnóstico (7.1: plataforma virtual y bases de datos). Ningún documento separaba las estrategias de aprendizaje de las de enseñanza, como exige el Art. 12; se organizaron en cinco subpuntos: aprendizaje, enseñanza, métodos, tipos y recursos. | J69: 1
A70: 4.7 | B70: Evaluación de aprendizajes (estrategias, métodos, tipos, procedimientos, instrumentos y pruebas a desarrollar) | C70: Sin asignar | D70: Sin asignar | E70: Entregado | F70: 46308 | G70: Word | H70: Sí | I70: Fuentes: fuente terciaria (4.7), Plan 2024 (3.16, escala y mesas) y comisión (evidencias). CORREGIDO: la fuente terciaria citaba el "Artículo 10 de la Res. HCU 032/2025" para la evaluación de aprendizajes, pero el Art. 10 trata la evaluación ex ante del plan; se citaron los Arts. 9 y 12. VERIFICAR la "Res. HCU 424/2023, Reglamento de Evaluación y Acreditación Académica del Pregrado" (solo en la fuente terciaria; no se usó). "Casos clínicos" se cambió por "casos". Lista de mesas de examen actualizada a los nombres de la malla 2027 (DER-101 y DER-201 tenían nombres antiguos). | J70: 1
A71: 4.8 | B71: Prácticas preprofesionales | C71: Sin asignar | D71: Sin asignar | E71: Parcial | F71: 46308 | G71: Word | H71: Sí | I71: Ningún documento desarrollaba las prácticas preprofesionales (el 4.8 del Plan 2024 solo trataba de trabajos de aplicación). Redactado con: Art. 12 de la Res. HCU 032/2025, IES 5, diagnóstico (88 %, BID 25 %), Ipsos (42 %), Plan de Desarrollo (pasantías desde 3.er año, convenios, consultoría social contable, meta del 100 %) y Plan 2024 (prácticas formativas). PENDIENTE de decisión de la Comisión: carga horaria mínima de la práctica, requisitos y reglamento específico; la malla de 6.000 h no tiene horas propias para la práctica, así que se propuso registrarla como horas no presenciales. | J71: 1
A72: 5. | B72: Admisión, promoción y graduación | C72: Daniel Laura Choque | D72: Sandra Alison Maidana Mamani | E72: =IF(SUMPRODUCT(($J$73:$J$76=1)*($E$73:$E$76<>"No aplica"))=0,"No aplica",IF(SUMPRODUCT(($J$73:$J$76=1)*($E$73:$E$76="Entregado"))=SUMPRODUCT(($J$73:$J$76=1)*($E$73:$E$76<>"No aplica")),"Completo",IF(SUMPRODUCT(($J$73:$J$76=1)*($E$73:$E$76="Pendiente"))=SUMPRODUCT(($J$73:$J$76=1)*($E$73:$E$76<>"No aplica")),"Pendiente","En proceso"))) | F72: =SUMPRODUCT(($J$73:$J$76=1)*($E$73:$E$76="Entregado"))&" de "&SUMPRODUCT(($J$73:$J$76=1)*($E$73:$E$76<>"No aplica")) | G72: — | H72: — | J72: 0
A73: 5.1 | B73: Perfil del postulante | C73: Daniel Laura Choque | D73: Sandra Alison Maidana Mamani | E73: Entregado | F73: 46308 | G73: Word | H73: Sí | I73: Fuentes: fuente terciaria (5.1.1, perfil de ingreso; base del texto), Plan 2024 (5.1) y comisión (5.1: brecha con el perfil real). Se quitó "Mecanismos de admisión (IES 1)" del perfil, porque corresponde a 5.2. | J73: 1
A74: 5.2 | B74: Modalidades de admisión | C74: Daniel Laura Choque | D74: Sandra Alison Maidana Mamani | E74: Entregado | F74: 46308 | G74: Word | H74: Sí | I74: Fuentes: fuente terciaria (5.2.1: tres modalidades con detalle de la Admisión Especial) y comisión (diagnóstico y propuestas 1.1 a 1.3, resumidas en 5.2.1 y 5.2.2). ERROR de la comisión: llama a la PSA "Examen de Suficiencia Académica"; se unificó como Prueba de Suficiencia Académica, igual que en la malla (4.4.3) y en el punto 3. Además, la comisión describe la Admisión Especial como "traspasos de carrera", lo que no coincide con la fuente terciaria ni con la normativa; se usó la lista de la fuente terciaria. Dato agregado: 26,62 % de matrícula no activada (diagnóstico). | J74: 1
A75: 5.3 | B75: Condiciones de permanencia, licencias, suspensiones, plazo máximo de reincorporación, abandono, etc. | C75: Jorge Ordoñez Oporto | D75: Josue Pilco Tito | E75: Parcial | F75: 46308 | G75: Word | H75: Sí | I75: Fuentes: fuente terciaria (5.3.1: régimen, cursos de temporada y mesas de examen), comisión (5.3: diagnóstico y propuestas 2.1 a 2.4) y Plan 2024. FALTABA en todas las fuentes el contenido sobre licencias, suspensiones, reincorporación y abandono que pide el índice; se redactó con el Art. 16 del Reglamento del Régimen Estudiantil (en verde) y reglas generales, sin plazos. PENDIENTE: plazos máximos de suspensión y reincorporación según el reglamento de la UMSA. DECISIONES POR CONFIRMAR: (1) nota previa para recuperar una troncal en verano: Plan 2024 = 20, fuente terciaria = 30, comisión propone eliminarla con tutoría obligatoria; se adoptó la propuesta de la comisión; (2) la comisión habla de un límite de "160 horas" y de "80 horas" para troncales en verano; la norma vigente (Plan 2024) y la fuente terciaria dicen 80 horas, que es lo que se usó; (3) la comisión propone ampliar las mesas de examen a materias prácticas, pero la Res. HCU 352/2021 las limita a materias teóricas; no se incluyó y solo se dejaron los seminarios previos. | J75: 1 | K75: Art. 16 del Reglamento del Régimen Estudiantil de la Universidad Boliviana (régimen académico: permanencia, traspaso, cambio de carrera, suspensión voluntaria, estudio simultáneo, readmisiones) y definición de readmisión. Fuente: copia del reglamento en faadu.umsa.bo, según los resultados del buscador; no se pudo abrir el PDF. Resaltado en verde.
A76: 5.4 | B76: Modalidades de graduación | C76: Jorge Ordoñez Oporto | D76: Josue Pilco Tito | E76: Entregado | F76: 46308 | G76: Word | H76: Sí | I76: Fuentes: fuente terciaria (5.4: grados y siete modalidades, base de la propuesta) y comisión (5.4: requisitos y plazos actuales, problemas y propuestas 3.1 a 3.4). DECISIONES Y COHERENCIA POR CONFIRMAR: (1) diplomado como modalidad: 800 h (20 créditos, que da 40 h por crédito, distinto de las 30 h del sistema de créditos) en la fuente terciaria y 400 h en el Plan de Desarrollo; se redactó sin cifra ("según la normativa de postgrado"); (2) examen de grado: la comisión dice 4 convocatorias anuales y sorteo de bolos 1 hora antes; la fuente terciaria dice al menos 3 convocatorias y 24 horas; se usaron 4 convocatorias y 24 horas; (3) proyecto de grado: 40/30/30 (comisión, vigente) frente a 45/30/25 (fuente terciaria); se usó la fuente terciaria; (4) trabajo dirigido: se mantiene 85/15 según la Res. HCU 330/2022; la comisión propone reequilibrarlo sin dar cifras; (5) excelencia: se usaron los 75 puntos de la comisión. SIGLA: el diagnóstico decía PETAEG y la comisión y el Plan 2024 PETAENG; se unificó PETAENG (también en el punto 2). Asignatura del examen técnico: "Presupuesto y Contabilidad Gubernamental" se actualizó al nombre de la malla, "Contabilidad y Presupuestos Gubernamental". La fuente terciaria titula al técnico "Técnico Superior en Contabilidad General"; se usó "Técnico Universitario Superior" (Res. HCU 290/2016). | J76: 1
A77: 6. | B77: Investigación (articulada con los institutos o unidades de investigación relacionados con la carrera/programa) | C77: Jorge Cespedes Esteves | D77: Gustavo Adolfo Aguilar Huanca | E77: =IF(SUMPRODUCT(($J$78:$J$79=1)*($E$78:$E$79<>"No aplica"))=0,"No aplica",IF(SUMPRODUCT(($J$78:$J$79=1)*($E$78:$E$79="Entregado"))=SUMPRODUCT(($J$78:$J$79=1)*($E$78:$E$79<>"No aplica")),"Completo",IF(SUMPRODUCT(($J$78:$J$79=1)*($E$78:$E$79="Pendiente"))=SUMPRODUCT(($J$78:$J$79=1)*($E$78:$E$79<>"No aplica")),"Pendiente","En proceso"))) | F77: =SUMPRODUCT(($J$78:$J$79=1)*($E$78:$E$79="Entregado"))&" de "&SUMPRODUCT(($J$78:$J$79=1)*($E$78:$E$79<>"No aplica")) | G77: — | H77: — | J77: 0
A78: 6.1 | B78: Políticas de investigación | C78: Jorge Cespedes Esteves | D78: Gustavo Adolfo Aguilar Huanca | E78: Entregado | F78: 46308 | G78: Word | H78: Sí | I78: Fuente: comisión (6.1), reorganizada en cuadro y listas. Se agregaron la articulación con el plan (CPA-204, CPA-510, investigación formativa y graduación; base: Plan 2024 "trabajos de aplicación e investigación") y la situación del Instituto y sus metas (diagnóstico 2026 y Plan de Desarrollo). INCOHERENCIA DE LA COMISIÓN: el texto cita la Política de Investigación con la Res. HCU 90/2021, pero la referencia dice 90/2026, y las citas dicen "(UMSA, 2025)" y "(UMSA, 2026)"; se usó 90/2021. VERIFICAR el número y el año. "Emprendedurismo" se cambió por "emprendimiento". El Plan 2024 tenía el 6.1 vacío. | J78: 1
A79: 6.2 | B79: Líneas de investigación | C79: Jorge Cespedes Esteves | D79: Gustavo Adolfo Aguilar Huanca | E79: Parcial | F79: 46308 | G79: Word | H79: Sí | I79: Fuentes: comisión (6.2: concepto, Arts. 7 y 8 del Estatuto, principios y metodología de siete etapas) y fuente terciaria (Plan de Desarrollo: cuatro líneas prioritarias del IICCFA, vinculadas aquí con asignaturas de la malla 2027). La comisión no propone líneas concretas: indica que deben ser un producto del rediseño. Se presentan las cuatro líneas del Plan de Desarrollo como prioritarias, con la metodología para formalizarlas. PENDIENTE: validar las líneas y ver si se agregan líneas del núcleo (información financiera, sector público, educación contable), que hoy no figuran. El Plan 2024 tenía el 6.2 vacío. Error de la comisión: la última oración del 6.2 quedó incompleta ("recoge la actualización del manejo del conocimiento"). | J79: 1
A80: 7. | B80: Interacción social y extensión universitaria | C80: Edith Esther López Mamani | D80: Analia Calle Mita | E80: =IF(SUMPRODUCT(($J$81:$J$82=1)*($E$81:$E$82<>"No aplica"))=0,"No aplica",IF(SUMPRODUCT(($J$81:$J$82=1)*($E$81:$E$82="Entregado"))=SUMPRODUCT(($J$81:$J$82=1)*($E$81:$E$82<>"No aplica")),"Completo",IF(SUMPRODUCT(($J$81:$J$82=1)*($E$81:$E$82="Pendiente"))=SUMPRODUCT(($J$81:$J$82=1)*($E$81:$E$82<>"No aplica")),"Pendiente","En proceso"))) | F80: =SUMPRODUCT(($J$81:$J$82=1)*($E$81:$E$82="Entregado"))&" de "&SUMPRODUCT(($J$81:$J$82=1)*($E$81:$E$82<>"No aplica")) | G80: — | H80: — | J80: 0
A81: 7.1 | B81: Políticas y líneas de interacción social | C81: Edith Esther López Mamani | D81: Analia Calle Mita | E81: Parcial | F81: 46308 | G81: Word | H81: Sí | I81: NO ELABORADO POR LAS SUBCOMISIONES (el Plan 2024 lo tenía vacío). Redactado con: Art. 12 de la Res. HCU 032/2025, Plan de Desarrollo Eje 3 (consultoría social contable, Código IESBA, pasantías, convenios, metas 2030), objetivo f de 2.4, punto 3.3 (84,2 % de informalidad), punto 4.8 y punto 6. Las seis políticas y cinco líneas son una PROPUESTA de redacción para validar. PENDIENTE: carga horaria mínima de interacción social por estudiante y Reglamento de Interacción Social de la Carrera. | J81: 1 | K81: Primer Congreso de 1988 (denominación "interacción social"), Res. N.º 088/2014 del XII Congreso Nacional de Universidades (reglamentación de Interacción Social y Extensión) y lineamiento del DIPGIS sobre integrar la investigación con la interacción social. Fuente: dipgis.umsa.bo (memoria del Seminario de Extensión Universitaria y página de Interacción Social), según los resultados del buscador; no se pudo abrir el PDF. Resaltado en verde.
A82: 7.2 | B82: Políticas y líneas de extensión universitaria | C82: Edith Esther López Mamani | D82: Analia Calle Mita | E82: Parcial | F82: 46308 | G82: Word | H82: Sí | I82: NO ELABORADO POR LAS SUBCOMISIONES (el Plan 2024 lo tenía vacío). Redactado con: IES 7 (desarrollo profesional continuo), diagnóstico 9.1 (programas de postgrado vigentes y de 2026, curso de metodología, doctorado), punto 5.4.2 (diplomado como graduación) y punto 7.1 (plataforma virtual). Las políticas y líneas son una PROPUESTA para validar. | J82: 1 | K82: Campus Virtual UMSA-Coursera, Res. HCU 538/2022 (reglamento específico). Fuente: dipgis.umsa.bo, según los resultados del buscador. Resaltado en verde.
A83: 8. | B83: Organización del proceso curricular | C83: Comisión Supra | D83: Comisión Supra | E83: =IF(SUMPRODUCT(($J$84:$J$89=1)*($E$84:$E$89<>"No aplica"))=0,"No aplica",IF(SUMPRODUCT(($J$84:$J$89=1)*($E$84:$E$89="Entregado"))=SUMPRODUCT(($J$84:$J$89=1)*($E$84:$E$89<>"No aplica")),"Completo",IF(SUMPRODUCT(($J$84:$J$89=1)*($E$84:$E$89="Pendiente"))=SUMPRODUCT(($J$84:$J$89=1)*($E$84:$E$89<>"No aplica")),"Pendiente","En proceso"))) | F83: =SUMPRODUCT(($J$84:$J$89=1)*($E$84:$E$89="Entregado"))&" de "&SUMPRODUCT(($J$84:$J$89=1)*($E$84:$E$89<>"No aplica")) | G83: — | H83: — | J83: 0
A84: 8.1 | B84: Número de semanas lectivas por semestre/año | C84: Comisión Supra | D84: Comisión Supra | E84: Entregado | F84: 46308 | G84: Word | H84: Sí | I84: NO ELABORADO POR LAS SUBCOMISIONES. Fuente: Plan 2024 (5.1: 40 semanas en 10 meses) y fuente terciaria (40 semanas lectivas). Se agregaron las 200 semanas del plan y la referencia a los cursos de temporada. | J84: 1
A85: 8.2 | B85: Número de horas cronológicas por semana | C85: Comisión Supra | D85: Comisión Supra | E85: Entregado | F85: 46308 | G85: Word | H85: Sí | I85: NO ELABORADO POR LAS SUBCOMISIONES. El Plan 2024 decía "30 horas académicas por semana" para todos los años (6 h diarias de lunes a sábado), pero su propia malla tiene 26, 30, 32, 32 y 30 h. Se presentan las horas reales por año, convertidas a horas cronológicas (×0,75) y con su equivalente no presencial (método del punto 4.3.5). El título del índice pide horas cronológicas; el Plan 2024 daba horas académicas. | J85: 1
A86: 8.3 | B86: Total de horas planificadas | C86: Comisión Supra | D86: Comisión Supra | E86: Entregado | F86: 46308 | G86: Word | H86: Sí | I86: NO ELABORADO POR LAS SUBCOMISIONES. Fuente: Plan 2024 (5.3) y malla 2027. CORREGIDO: el Plan 2024 decía "como mínimo 6.000 horas"; el Art. 28 del Reglamento General de Títulos y Grados fija 6.000 como máximo (así lo dicen el diagnóstico y la comisión). Se agregaron las horas cronológicas presenciales, no presenciales y de trabajo. | J86: 1
A87: 8.4 | B87: Carga horaria cronológica en actividades de investigación | C87: Comisión Supra | D87: Comisión Supra | E87: Entregado | F87: 46308 | G87: Word | H87: Sí | I87: NO ELABORADO POR LAS SUBCOMISIONES (el Plan 2024 lo tenía vacío). Calculado con la malla 2027: CPA-204 y CPA-510 = 240 h de trabajo (8 créditos); la investigación formativa en las demás asignaturas se define en cada plan de asignatura; 320 h/mes del Instituto (diagnóstico). | J87: 1
A88: 8.5 | B88: Sistema de créditos | C88: Comisión Supra | D88: Comisión Supra | E88: Entregado | F88: 46308 | G88: Word | H88: Sí | I88: NO ELABORADO POR LAS SUBCOMISIONES. Fuentes: Plan 2024 (5.5: 300 créditos), comisión 4.3.5 (método) y cálculo por asignatura del punto 4.4.3. Créditos por año: 52, 60, 64, 64 y 60 = 300. | J88: 1
A89: 8.6 | B89: Número de estudiantes por asignatura | C89: Comisión Supra | D89: Comisión Supra | E89: Parcial | F89: 46308 | G89: Word | H89: Sí | I89: NO ELABORADO POR LAS SUBCOMISIONES. Fuentes: diagnóstico (Cuadro 11, 2023-2026), comisión del punto 3 (escenarios de 80 y 60 estudiantes por paralelo, recalculados con 2026: 302 y 402 paralelos) y diagnóstico 7.1 (laboratorios de 70 y 39 equipos). El Art. 12 exige un mínimo y un máximo: los máximos son una PROPUESTA basada en la comisión y el mínimo se remite a la reglamentación universitaria. PENDIENTE: fijar el número mínimo para abrir un paralelo. Nota posterior (punto 10.7): el inventario de la comisión registra 20 puestos completos en el laboratorio del Monoblock (39 según el diagnóstico); si se confirma, actualizar la cifra de este punto. ACTUALIZADO: "70 y 39 equipos" se cambió por "capacidad para 70 y 36 estudiantes", porque la cifra de 39 equipos no se sostiene con los relevamientos de las comisiones de los puntos 10 y 15. | J89: 1
A90: 9. | B90: Material Bibliográfico | C90: Demetrio Ancalle Choque | D90: Wendy Callizaya Pocoaca | E90: =IF(SUMPRODUCT(($J$91:$J$94=1)*($E$91:$E$94<>"No aplica"))=0,"No aplica",IF(SUMPRODUCT(($J$91:$J$94=1)*($E$91:$E$94="Entregado"))=SUMPRODUCT(($J$91:$J$94=1)*($E$91:$E$94<>"No aplica")),"Completo",IF(SUMPRODUCT(($J$91:$J$94=1)*($E$91:$E$94="Pendiente"))=SUMPRODUCT(($J$91:$J$94=1)*($E$91:$E$94<>"No aplica")),"Pendiente","En proceso"))) | F90: =SUMPRODUCT(($J$91:$J$94=1)*($E$91:$E$94="Entregado"))&" de "&SUMPRODUCT(($J$91:$J$94=1)*($E$91:$E$94<>"No aplica")) | G90: Word | H90: Sí | I90: Archivos: "9. Material bibliográfico.docx" y "9. Anexo. Listado bibliográfico.docx" (158 páginas). Fuentes: comisión (listado del catálogo KOHA por asignatura y de trabajos de grado), diagnóstico 2026 (acervo, biblioteca, bases de datos) y Plan 2024 (9.2 y 9.3). La comisión solo entregó el listado del 9.1, sin análisis ni los puntos 9.2 a 9.4; el análisis de suficiencia se elaboró aquí. El listado de la comisión usa siglas y nombres del Plan 2013; se trasladó a la malla 2027 según la tabla de convalidación de la fuente terciaria (punto 16). | J90: 0
A91: 9.1 | B91: Textos físicos y digitales (suficiencia cuantitativa y cualitativa) | C91: Demetrio Ancalle Choque | D91: Wendy Callizaya Pocoaca | E91: Entregado | F91: 46308 | G91: Word | H91: Sí | I91: Fuentes: comisión (listado), diagnóstico 2026 y Plan 2024. Análisis propio: 3.108 ejemplares asignados, 948 títulos distintos, solo 458 ejemplares (14,7 %) editados desde 2015; 22 asignaturas con bibliografía actualizada, 14 por actualizar y 7 desactualizadas; CPA-305 ERP solo tiene 2 ejemplares (1974 y 1985). Criterio de vigencia definido aquí (≥5 ejemplares desde 2015 y edición ≥2020): VALIDAR. ERRORES Y DIFERENCIAS: (1) los listados de CPA-407 Auditoría Financiera y CPA-502 Gabinete de Auditoría Financiera de la comisión son idénticos, posible copia; (2) el diagnóstico dice 87 tesis, 668 proyectos y 1.530 trabajos dirigidos, y el catálogo 63, 619 y 1.710; (3) el diagnóstico menciona "1.951 memorias", cifra que no cuadra con ninguna otra y se omitió; (4) libros: 6.173 en el diagnóstico frente a 5.702 en el Plan 2024. Los títulos del catálogo de trabajos de grado vienen truncados por KOHA (por ejemplo "La evidencia") y se transcriben tal cual en el anexo. Se propone una política de actualización bibliográfica (9.1.4) que no estaba en ninguna fuente. | J91: 1
A92: 9.2 | B92: Suscripción a revistas de reconocido prestigio especializado | C92: Demetrio Ancalle Choque | D92: Wendy Callizaya Pocoaca | E92: Entregado | F92: 46308 | G92: Word | H92: Sí | I92: Fuente: Plan 2024 (sin suscripciones; acceso libre a IFAC, Fundación IFRS e IIA), completado con normativa nacional y una recomendación de revistas de acceso abierto. La comisión no trabajó este punto. | J92: 1 | K92: Registro gratuito en la Fundación IFRS: normas emitidas del año, CINIIF, Marco Conceptual y traducciones (sin ejemplos ni fundamentos, que son de pago) (ifrs.org). Descarga gratuita de los manuales del IAASB, IESBA e IAESB. Revistas de acceso abierto sugeridas: Contaduría y Administración (UNAM), Cuadernos de Contabilidad (Javeriana), Contaduría Universidad de Antioquia, Revista de Contabilidad - Spanish Accounting Review.
A93: 9.3 | B93: Conexión a sistemas de información nacional o internacional | C93: Maria del Carmen Pinell Varcarcel | D93: Alex Jesus Huanca Uscamayta | E93: Entregado | F93: 46308 | G93: Word | H93: Sí | I93: Fuentes: Plan 2024 (KOHA desde 2008, biométrico, PERI con EBSCO, Cambridge, Emerald, Oxford, Palgrave, Springer, Royal Society, Chicago, Wiley; HINARI) y diagnóstico 2026 (repositorio UMSA, Research4Life, SciELO, Scopus, Dialnet). VERIFICAR con la Biblioteca Central si sigue vigente el acceso a los recursos del programa PERI (dato de 2024). La comisión no trabajó este punto. | J93: 1 | K93: HINARI forma parte de Research4Life. Scopus: especificación técnica de contratación del DIPGIS-UMSA (2023), orientada a docentes e investigadores (dipgis.umsa.bo); no se confirmó el acceso de estudiantes.
A94: 9.4 | B94: Internet, sistema de red o wifi | C94: Maria del Carmen Pinell Varcarcel | D94: Alex Jesus Huanca Uscamayta | E94: Entregado | F94: 46308 | G94: Word | H94: Sí | I94: Fuentes: comisión punto 10 (dos salidas de internet, 385 Mbps Montes y 165 Mbps Monoblock, wifi para estudiantes, docentes y administrativos) y diagnóstico 2026 (gabinete de red en el Centro de Cómputo, Av. Villazón; pool de servidores con respaldo de energía). Ni la comisión ni el Plan 2024 desarrollaron el 9.4. | J94: 1
A95: 10. | B95: Recursos educativos | C95: Miguel Cotaña Mier | D95: Camila Lampa Choque | E95: =IF(SUMPRODUCT(($J$96:$J$107=1)*($E$96:$E$107<>"No aplica"))=0,"No aplica",IF(SUMPRODUCT(($J$96:$J$107=1)*($E$96:$E$107="Entregado"))=SUMPRODUCT(($J$96:$J$107=1)*($E$96:$E$107<>"No aplica")),"Completo",IF(SUMPRODUCT(($J$96:$J$107=1)*($E$96:$E$107="Pendiente"))=SUMPRODUCT(($J$96:$J$107=1)*($E$96:$E$107<>"No aplica")),"Pendiente","En proceso"))) | F95: =SUMPRODUCT(($J$96:$J$107=1)*($E$96:$E$107="Entregado"))&" de "&SUMPRODUCT(($J$96:$J$107=1)*($E$96:$E$107<>"No aplica")) | G95: Word | H95: Sí | I95: Archivo: "10. Recursos educativos.docx". Fuentes: comisión (base principal, con fotografías y capturas), Plan 2024 y diagnóstico 2026. Se eliminó la duplicación de la comisión, que repetía el texto de computadoras en red en 10.2 y 10.10 y el de redes sociales en 10.3 y 10.11. Las capturas se recortaron para quitar la barra del navegador y del sistema operativo. Se agregaron análisis de brechas frente al Plan 2027 (software requerido, capacidad de laboratorios y de la plataforma virtual). | J95: 0
A96: 10.1 | B96: Equipos multimedia | C96: Miguel Cotaña Mier | D96: Camila Lampa Choque | E96: Entregado | F96: 46308 | G96: Word | H96: Sí | I96: Fuentes: comisión y Plan 2024. Se agregó el aula multipropósito (la comisión del punto 11 indica que tiene proyector). DIFERENCIAS: el Plan 2024 registraba un proyector en el auditorio y el equipo portátil con tres micrófonos inalámbricos y un pedestal de mesa, que la comisión ya no menciona; VERIFICAR si se dieron de baja. | J96: 1
A97: 10.2 | B97: Computadora en red | C97: Miguel Cotaña Mier | D97: Camila Lampa Choque | E97: Entregado | F97: 46308 | G97: Word | H97: Sí | I97: Fuente: comisión (dos servidores propios, sistemas alojados, copias semanales, pool del Monoblock). "Contante" se corrigió por "constante". | J97: 1
A98: 10.3 | B98: Software | C98: Miguel Cotaña Mier | D98: Camila Lampa Choque | E98: Entregado | F98: 46308 | G98: Word | H98: Sí | I98: Fuentes: comisión (categorías de software) y comisión punto 11 (software requerido: ERP, ACL/IDEA, Power BI, Tableau, Python). Se agregó el cuadro de brechas entre el software requerido por el Plan 2027 y el disponible. | J98: 1
A99: 10.4 | B99: Laboratorios | C99: Miguel Cotaña Mier | D99: Camila Lampa Choque | E99: Entregado | F99: 46308 | G99: Word | H99: Sí | I99: Fuentes: comisión y Plan 2024. DIFERENCIAS: la sala de computación de Nava Morales tiene 61 m² según la comisión y 93 m² según el Plan 2024 (se usó 61); la sala de servidores y la oficina, 12 m² frente a 16 m². El auditorio (247 m², 220 personas) se incorporó en este cuadro. | J99: 1
A100: 10.5 | B100: Material audiovisual | C100: Freddy Huanca Mamani | D100: Maria Joaquina Salinas Terceros | E100: Entregado | F100: 46308 | G100: Word | H100: Sí | I100: Fuente: comisión. ERROR: el pie de la foto del Monoblock decía "laboratorio 4to piso", pero el laboratorio está en planta baja; se corrigió. Las fotos se reubicaron en 10.4. | J100: 1
A101: 10.6 | B101: Medios didácticos informáticos | C101: Freddy Huanca Mamani | D101: Maria Joaquina Salinas Terceros | E101: Entregado | F101: 46308 | G101: Word | H101: Sí | I101: Fuente: comisión; se unificaron las dos listas, que eran casi iguales. | J101: 1
...

Sheet Resumen
A1: Resumen de avance por punto
A2: Se calcula solo con los ítems entregables de la hoja Checklist. Los ítems marcados «No aplica» no cuentan en el total ni en el avance.
A4: Punto | B4: Título | C4: Ítems | D4: Entregados | E4: Parciales | F4: Observados | G4: Pendientes | H4: Avance | I4: No aplica
A5: 1 | B5: Identificación del programa/carrera | C5: =COUNTIFS(Checklist!$A$5:$A$137,"1.*",Checklist!$J$5:$J$137,1,Checklist!$E$5:$E$137,"<>No aplica") | D5: =COUNTIFS(Checklist!$A$5:$A$137,"1.*",Checklist!$J$5:$J$137,1,Checklist!$E$5:$E$137,"Entregado") | E5: =COUNTIFS(Checklist!$A$5:$A$137,"1.*",Checklist!$J$5:$J$137,1,Checklist!$E$5:$E$137,"Parcial") | F5: =COUNTIFS(Checklist!$A$5:$A$137,"1.*",Checklist!$J$5:$J$137,1,Checklist!$E$5:$E$137,"Observado") | G5: =COUNTIFS(Checklist!$A$5:$A$137,"1.*",Checklist!$J$5:$J$137,1,Checklist!$E$5:$E$137,"Pendiente") | H5: =IF(C5=0,IF(I5>0,1,0),D5/C5) | I5: =COUNTIFS(Checklist!$A$5:$A$137,"1.*",Checklist!$J$5:$J$137,1,Checklist!$E$5:$E$137,"No aplica")
A6: 2 | B6: Antecedentes | C6: =COUNTIFS(Checklist!$A$5:$A$137,"2.*",Checklist!$J$5:$J$137,1,Checklist!$E$5:$E$137,"<>No aplica") | D6: =COUNTIFS(Checklist!$A$5:$A$137,"2.*",Checklist!$J$5:$J$137,1,Checklist!$E$5:$E$137,"Entregado") | E6: =COUNTIFS(Checklist!$A$5:$A$137,"2.*",Checklist!$J$5:$J$137,1,Checklist!$E$5:$E$137,"Parcial") | F6: =COUNTIFS(Checklist!$A$5:$A$137,"2.*",Checklist!$J$5:$J$137,1,Checklist!$E$5:$E$137,"Observado") | G6: =COUNTIFS(Checklist!$A$5:$A$137,"2.*",Checklist!$J$5:$J$137,1,Checklist!$E$5:$E$137,"Pendiente") | H6: =IF(C6=0,IF(I6>0,1,0),D6/C6) | I6: =COUNTIFS(Checklist!$A$5:$A$137,"2.*",Checklist!$J$5:$J$137,1,Checklist!$E$5:$E$137,"No aplica")
A7: 3 | B7: Justificación de la innovación curricular (solo para niveles de diseño, rediseño y ajustes) | C7: =COUNTIFS(Checklist!$A$5:$A$137,"3.*",Checklist!$J$5:$J$137,1,Checklist!$E$5:$E$137,"<>No aplica") | D7: =COUNTIFS(Checklist!$A$5:$A$137,"3.*",Checklist!$J$5:$J$137,1,Checklist!$E$5:$E$137,"Entregado") | E7: =COUNTIFS(Checklist!$A$5:$A$137,"3.*",Checklist!$J$5:$J$137,1,Checklist!$E$5:$E$137,"Parcial") | F7: =COUNTIFS(Checklist!$A$5:$A$137,"3.*",Checklist!$J$5:$J$137,1,Checklist!$E$5:$E$137,"Observado") | G7: =COUNTIFS(Checklist!$A$5:$A$137,"3.*",Checklist!$J$5:$J$137,1,Checklist!$E$5:$E$137,"Pendiente") | H7: =IF(C7=0,IF(I7>0,1,0),D7/C7) | I7: =COUNTIFS(Checklist!$A$5:$A$137,"3.*",Checklist!$J$5:$J$137,1,Checklist!$E$5:$E$137,"No aplica")
A8: 4 | B8: Aspectos académicos | C8: =COUNTIFS(Checklist!$A$5:$A$137,"4.*",Checklist!$J$5:$J$137,1,Checklist!$E$5:$E$137,"<>No aplica") | D8: =COUNTIFS(Checklist!$A$5:$A$137,"4.*",Checklist!$J$5:$J$137,1,Checklist!$E$5:$E$137,"Entregado") | E8: =COUNTIFS(Checklist!$A$5:$A$137,"4.*",Checklist!$J$5:$J$137,1,Checklist!$E$5:$E$137,"Parcial") | F8: =COUNTIFS(Checklist!$A$5:$A$137,"4.*",Checklist!$J$5:$J$137,1,Checklist!$E$5:$E$137,"Observado") | G8: =COUNTIFS(Checklist!$A$5:$A$137,"4.*",Checklist!$J$5:$J$137,1,Checklist!$E$5:$E$137,"Pendiente") | H8: =IF(C8=0,IF(I8>0,1,0),D8/C8) | I8: =COUNTIFS(Checklist!$A$5:$A$137,"4.*",Checklist!$J$5:$J$137,1,Checklist!$E$5:$E$137,"No aplica")
A9: 5 | B9: Admisión, promoción y graduación | C9: =COUNTIFS(Checklist!$A$5:$A$137,"5.*",Checklist!$J$5:$J$137,1,Checklist!$E$5:$E$137,"<>No aplica") | D9: =COUNTIFS(Checklist!$A$5:$A$137,"5.*",Checklist!$J$5:$J$137,1,Checklist!$E$5:$E$137,"Entregado") | E9: =COUNTIFS(Checklist!$A$5:$A$137,"5.*",Checklist!$J$5:$J$137,1,Checklist!$E$5:$E$137,"Parcial") | F9: =COUNTIFS(Checklist!$A$5:$A$137,"5.*",Checklist!$J$5:$J$137,1,Checklist!$E$5:$E$137,"Observado") | G9: =COUNTIFS(Checklist!$A$5:$A$137,"5.*",Checklist!$J$5:$J$137,1,Checklist!$E$5:$E$137,"Pendiente") | H9: =IF(C9=0,IF(I9>0,1,0),D9/C9) | I9: =COUNTIFS(Checklist!$A$5:$A$137,"5.*",Checklist!$J$5:$J$137,1,Checklist!$E$5:$E$137,"No aplica")
A10: 6 | B10: Investigación (articulada con los institutos o unidades de investigación relacionados con la carrera/programa) | C10: =COUNTIFS(Checklist!$A$5:$A$137,"6.*",Checklist!$J$5:$J$137,1,Checklist!$E$5:$E$137,"<>No aplica") | D10: =COUNTIFS(Checklist!$A$5:$A$137,"6.*",Checklist!$J$5:$J$137,1,Checklist!$E$5:$E$137,"Entregado") | E10: =COUNTIFS(Checklist!$A$5:$A$137,"6.*",Checklist!$J$5:$J$137,1,Checklist!$E$5:$E$137,"Parcial") | F10: =COUNTIFS(Checklist!$A$5:$A$137,"6.*",Checklist!$J$5:$J$137,1,Checklist!$E$5:$E$137,"Observado") | G10: =COUNTIFS(Checklist!$A$5:$A$137,"6.*",Checklist!$J$5:$J$137,1,Checklist!$E$5:$E$137,"Pendiente") | H10: =IF(C10=0,IF(I10>0,1,0),D10/C10) | I10: =COUNTIFS(Checklist!$A$5:$A$137,"6.*",Checklist!$J$5:$J$137,1,Checklist!$E$5:$E$137,"No aplica")
A11: 7 | B11: Interacción social y extensión universitaria | C11: =COUNTIFS(Checklist!$A$5:$A$137,"7.*",Checklist!$J$5:$J$137,1,Checklist!$E$5:$E$137,"<>No aplica") | D11: =COUNTIFS(Checklist!$A$5:$A$137,"7.*",Checklist!$J$5:$J$137,1,Checklist!$E$5:$E$137,"Entregado") | E11: =COUNTIFS(Checklist!$A$5:$A$137,"7.*",Checklist!$J$5:$J$137,1,Checklist!$E$5:$E$137,"Parcial") | F11: =COUNTIFS(Checklist!$A$5:$A$137,"7.*",Checklist!$J$5:$J$137,1,Checklist!$E$5:$E$137,"Observado") | G11: =COUNTIFS(Checklist!$A$5:$A$137,"7.*",Checklist!$J$5:$J$137,1,Checklist!$E$5:$E$137,"Pendiente") | H11: =IF(C11=0,IF(I11>0,1,0),D11/C11) | I11: =COUNTIFS(Checklist!$A$5:$A$137,"7.*",Checklist!$J$5:$J$137,1,Checklist!$E$5:$E$137,"No aplica")
A12: 8 | B12: Organización del proceso curricular | C12: =COUNTIFS(Checklist!$A$5:$A$137,"8.*",Checklist!$J$5:$J$137,1,Checklist!$E$5:$E$137,"<>No aplica") | D12: =COUNTIFS(Checklist!$A$5:$A$137,"8.*",Checklist!$J$5:$J$137,1,Checklist!$E$5:$E$137,"Entregado") | E12: =COUNTIFS(Checklist!$A$5:$A$137,"8.*",Checklist!$J$5:$J$137,1,Checklist!$E$5:$E$137,"Parcial") | F12: =COUNTIFS(Checklist!$A$5:$A$137,"8.*",Checklist!$J$5:$J$137,1,Checklist!$E$5:$E$137,"Observado") | G12: =COUNTIFS(Checklist!$A$5:$A$137,"8.*",Checklist!$J$5:$J$137,1,Checklist!$E$5:$E$137,"Pendiente") | H12: =IF(C12=0,IF(I12>0,1,0),D12/C12) | I12: =COUNTIFS(Checklist!$A$5:$A$137,"8.*",Checklist!$J$5:$J$137,1,Checklist!$E$5:$E$137,"No aplica")
A13: 9 | B13: Material Bibliográfico | C13: =COUNTIFS(Checklist!$A$5:$A$137,"9.*",Checklist!$J$5:$J$137,1,Checklist!$E$5:$E$137,"<>No aplica") | D13: =COUNTIFS(Checklist!$A$5:$A$137,"9.*",Checklist!$J$5:$J$137,1,Checklist!$E$5:$E$137,"Entregado") | E13: =COUNTIFS(Checklist!$A$5:$A$137,"9.*",Checklist!$J$5:$J$137,1,Checklist!$E$5:$E$137,"Parcial") | F13: =COUNTIFS(Checklist!$A$5:$A$137,"9.*",Checklist!$J$5:$J$137,1,Checklist!$E$5:$E$137,"Observado") | G13: =COUNTIFS(Checklist!$A$5:$A$137,"9.*",Checklist!$J$5:$J$137,1,Checklist!$E$5:$E$137,"Pendiente") | H13: =IF(C13=0,IF(I13>0,1,0),D13/C13) | I13: =COUNTIFS(Checklist!$A$5:$A$137,"9.*",Checklist!$J$5:$J$137,1,Checklist!$E$5:$E$137,"No aplica")
A14: 10 | B14: Recursos educativos | C14: =COUNTIFS(Checklist!$A$5:$A$137,"10.*",Checklist!$J$5:$J$137,1,Checklist!$E$5:$E$137,"<>No aplica") | D14: =COUNTIFS(Checklist!$A$5:$A$137,"10.*",Checklist!$J$5:$J$137,1,Checklist!$E$5:$E$137,"Entregado") | E14: =COUNTIFS(Checklist!$A$5:$A$137,"10.*",Checklist!$J$5:$J$137,1,Checklist!$E$5:$E$137,"Parcial") | F14: =COUNTIFS(Checklist!$A$5:$A$137,"10.*",Checklist!$J$5:$J$137,1,Checklist!$E$5:$E$137,"Observado") | G14: =COUNTIFS(Checklist!$A$5:$A$137,"10.*",Checklist!$J$5:$J$137,1,Checklist!$E$5:$E$137,"Pendiente") | H14: =IF(C14=0,IF(I14>0,1,0),D14/C14) | I14: =COUNTIFS(Checklist!$A$5:$A$137,"10.*",Checklist!$J$5:$J$137,1,Checklist!$E$5:$E$137,"No aplica")
A15: 11 | B15: Implementación del proyecto curricular | C15: =COUNTIFS(Checklist!$A$5:$A$137,"11.*",Checklist!$J$5:$J$137,1,Checklist!$E$5:$E$137,"<>No aplica") | D15: =COUNTIFS(Checklist!$A$5:$A$137,"11.*",Checklist!$J$5:$J$137,1,Checklist!$E$5:$E$137,"Entregado") | E15: =COUNTIFS(Checklist!$A$5:$A$137,"11.*",Checklist!$J$5:$J$137,1,Checklist!$E$5:$E$137,"Parcial") | F15: =COUNTIFS(Checklist!$A$5:$A$137,"11.*",Checklist!$J$5:$J$137,1,Checklist!$E$5:$E$137,"Observado") | G15: =COUNTIFS(Checklist!$A$5:$A$137,"11.*",Checklist!$J$5:$J$137,1,Checklist!$E$5:$E$137,"Pendiente") | H15: =IF(C15=0,IF(I15>0,1,0),D15/C15) | I15: =COUNTIFS(Checklist!$A$5:$A$137,"11.*",Checklist!$J$5:$J$137,1,Checklist!$E$5:$E$137,"No aplica")
A16: 12 | B16: Evaluación Curricular | C16: =COUNTIFS(Checklist!$A$5:$A$137,"12.*",Checklist!$J$5:$J$137,1,Checklist!$E$5:$E$137,"<>No aplica") | D16: =COUNTIFS(Checklist!$A$5:$A$137,"12.*",Checklist!$J$5:$J$137,1,Checklist!$E$5:$E$137,"Entregado") | E16: =COUNTIFS(Checklist!$A$5:$A$137,"12.*",Checklist!$J$5:$J$137,1,Checklist!$E$5:$E$137,"Parcial") | F16: =COUNTIFS(Checklist!$A$5:$A$137,"12.*",Checklist!$J$5:$J$137,1,Checklist!$E$5:$E$137,"Observado") | G16: =COUNTIFS(Checklist!$A$5:$A$137,"12.*",Checklist!$J$5:$J$137,1,Checklist!$E$5:$E$137,"Pendiente") | H16: =IF(C16=0,IF(I16>0,1,0),D16/C16) | I16: =COUNTIFS(Checklist!$A$5:$A$137,"12.*",Checklist!$J$5:$J$137,1,Checklist!$E$5:$E$137,"No aplica")
A17: 13 | B17: Reglamentación | C17: =COUNTIFS(Checklist!$A$5:$A$137,"13.*",Checklist!$J$5:$J$137,1,Checklist!$E$5:$E$137,"<>No aplica") | D17: =COUNTIFS(Checklist!$A$5:$A$137,"13.*",Checklist!$J$5:$J$137,1,Checklist!$E$5:$E$137,"Entregado") | E17: =COUNTIFS(Checklist!$A$5:$A$137,"13.*",Checklist!$J$5:$J$137,1,Checklist!$E$5:$E$137,"Parcial") | F17: =COUNTIFS(Checklist!$A$5:$A$137,"13.*",Checklist!$J$5:$J$137,1,Checklist!$E$5:$E$137,"Observado") | G17: =COUNTIFS(Checklist!$A$5:$A$137,"13.*",Checklist!$J$5:$J$137,1,Checklist!$E$5:$E$137,"Pendiente") | H17: =IF(C17=0,IF(I17>0,1,0),D17/C17) | I17: =COUNTIFS(Checklist!$A$5:$A$137,"13.*",Checklist!$J$5:$J$137,1,Checklist!$E$5:$E$137,"No aplica")
A18: 14 | B18: Infraestructura y equipamiento | C18: =COUNTIFS(Checklist!$A$5:$A$137,"14.*",Checklist!$J$5:$J$137,1,Checklist!$E$5:$E$137,"<>No aplica") | D18: =COUNTIFS(Checklist!$A$5:$A$137,"14.*",Checklist!$J$5:$J$137,1,Checklist!$E$5:$E$137,"Entregado") | E18: =COUNTIFS(Checklist!$A$5:$A$137,"14.*",Checklist!$J$5:$J$137,1,Checklist!$E$5:$E$137,"Parcial") | F18: =COUNTIFS(Checklist!$A$5:$A$137,"14.*",Checklist!$J$5:$J$137,1,Checklist!$E$5:$E$137,"Observado") | G18: =COUNTIFS(Checklist!$A$5:$A$137,"14.*",Checklist!$J$5:$J$137,1,Checklist!$E$5:$E$137,"Pendiente") | H18: =IF(C18=0,IF(I18>0,1,0),D18/C18) | I18: =COUNTIFS(Checklist!$A$5:$A$137,"14.*",Checklist!$J$5:$J$137,1,Checklist!$E$5:$E$137,"No aplica")
A19: 15 | B19: Mobiliario, equipamiento y materiales | C19: =COUNTIFS(Checklist!$A$5:$A$137,"15.*",Checklist!$J$5:$J$137,1,Checklist!$E$5:$E$137,"<>No aplica") | D19: =COUNTIFS(Checklist!$A$5:$A$137,"15.*",Checklist!$J$5:$J$137,1,Checklist!$E$5:$E$137,"Entregado") | E19: =COUNTIFS(Checklist!$A$5:$A$137,"15.*",Checklist!$J$5:$J$137,1,Checklist!$E$5:$E$137,"Parcial") | F19: =COUNTIFS(Checklist!$A$5:$A$137,"15.*",Checklist!$J$5:$J$137,1,Checklist!$E$5:$E$137,"Observado") | G19: =COUNTIFS(Checklist!$A$5:$A$137,"15.*",Checklist!$J$5:$J$137,1,Checklist!$E$5:$E$137,"Pendiente") | H19: =IF(C19=0,IF(I19>0,1,0),D19/C19) | I19: =COUNTIFS(Checklist!$A$5:$A$137,"15.*",Checklist!$J$5:$J$137,1,Checklist!$E$5:$E$137,"No aplica")
A20: 16 | B20: Disposiciones de ejecución | C20: =COUNTIFS(Checklist!$A$5:$A$137,"16.*",Checklist!$J$5:$J$137,1,Checklist!$E$5:$E$137,"<>No aplica") | D20: =COUNTIFS(Checklist!$A$5:$A$137,"16.*",Checklist!$J$5:$J$137,1,Checklist!$E$5:$E$137,"Entregado") | E20: =COUNTIFS(Checklist!$A$5:$A$137,"16.*",Checklist!$J$5:$J$137,1,Checklist!$E$5:$E$137,"Parcial") | F20: =COUNTIFS(Checklist!$A$5:$A$137,"16.*",Checklist!$J$5:$J$137,1,Checklist!$E$5:$E$137,"Observado") | G20: =COUNTIFS(Checklist!$A$5:$A$137,"16.*",Checklist!$J$5:$J$137,1,Checklist!$E$5:$E$137,"Pendiente") | H20: =IF(C20=0,IF(I20>0,1,0),D20/C20) | I20: =COUNTIFS(Checklist!$A$5:$A$137,"16.*",Checklist!$J$5:$J$137,1,Checklist!$E$5:$E$137,"No aplica")
B21: TOTAL | C21: =SUM(C5:C20) | D21: =SUM(D5:D20) | E21: =SUM(E5:E20) | F21: =SUM(F5:F20) | G21: =SUM(G5:G20) | H21: =IF(C21=0,IF(I21>0,1,0),D21/C21) | I21: =SUM(I5:I20)
