Workbook

Sheet Resumen
A1: Revisión del documento unificado del Rediseño Curricular
A2: Calificación frente a la Resolución HCU N.º 032/2025, términos de coherencia, correcciones aplicadas (incluye datos de matrícula 2026) y coherencia pendiente.
A4: Calificación global | B4: 78 / 100, Bueno: cumple de forma sustancial, con observaciones subsanables antes de la evaluación ex ante
A5: Ponderación | B5: Promedio simple (50 %) de dos componentes. (a) Puntajes de los 22 puntos presentes ponderados por su peso en el reglamento (sobre 100): 1=4, 2=5, 3=9, 4.1=5, 4.2=7, 4.3=6, 4.4=8, 4.6=4, 4.7=4, 4.8=5, 5=6, 6=5, 7=4, 8=5, 9=3, 10=2, 11=4, 12=4, 13=3, 14=2, 15=1, 16=4; resultado 78.0. (b) Promedio simple de los 78 requisitos puntuados, sin contar los 6 marcados «Pendiente 4.5» o «No aplica»; resultado 77.2. Escala: 90-100 Excelente; 80-89 Muy bueno; 70-79 Bueno; 60-69 Suficiente; <60 Insuficiente. El punto 4.5 no se penaliza.
A6: Síntesis | B6: El documento es sólido en justificación, referentes disciplinares, malla y créditos (6.000 h, 300 créditos, verificados), estrategias y evaluación curricular, y aplica de forma coherente las decisiones adoptadas (malla definitiva, 874 HIP, Reglamento de Modalidades). Las brechas principales son cuantitativas y de coherencia institucional: faltan las horas mínimas de prácticas e interacción social, el mínimo y máximo de estudiantes por paralelo, la sigla, carga y créditos de las modalidades de graduación y los plazos de reincorporación; no se demuestra la alineación con la misión, visión y Modelo Educativo de la UMSA; faltan el cuadro comparativo del Art. 13, los costos de implementación y varios reglamentos. Hay inconsistencias internas (120 créditos, capacidades, cronograma de extinción). Quedan pendientes de 4.5: unidades de competencia, planes de asignatura y evaluación por elemento.
A8: Hoja | B8: Concepto | C8: Cantidad | D8: Corregidos
A9: Términos de coherencia (aplicados) | B9: Plan de Estudios 2027 o Plan 2027 → Rediseño Curricular | C9: =COUNTIFS(Términos!D:D,"Plan 2027/2024",Términos!G:G,"Rediseño*") | D9: =COUNTIFS(Términos!D:D,"Plan 2027/2024",Términos!G:G,"Rediseño*",Términos!H:H,"Corregido")
A10: Términos de coherencia (aplicados) | B10: Troncal o troncales → Área Contable y de Auditoría | C10: =COUNTIF(Términos!D:D,"Troncal") | D10: =COUNTIFS(Términos!D:D,"Troncal",Términos!H:H,"Corregido")
A11: Términos de coherencia (aplicados) | B11: Contextual o contextuales → Área Contextual | C11: =COUNTIF(Términos!D:D,"Contextual") | D11: =COUNTIFS(Términos!D:D,"Contextual",Términos!H:H,"Corregido")
A12: Términos de coherencia (aplicados) | B12: Contador Público Autorizado fuera del título → Contador Público | C12: =COUNTIFS(Términos!D:D,"Contador Público Autorizado",Términos!G:G,"Contador Público") | D12: =COUNTIFS(Términos!D:D,"Contador Público Autorizado",Términos!G:G,"Contador Público",Términos!H:H,"Corregido")
A13: Términos de coherencia (aplicados) | B13: Menciones que se mantienen o que hay que revisar | C13: =COUNTIF(Términos!G:G,"Mantener*")+COUNTIF(Términos!G:G,"Revisar*")
A14: Cumplimiento HCU 032/2025 | B14: Requisitos que se cumplen | C14: =COUNTIF(Requisitos!D:D,"Cumple")
A15: Cumplimiento HCU 032/2025 | B15: Requisitos que se cumplen en parte | C15: =COUNTIF(Requisitos!D:D,"Cumple parcialmente") | D15: =COUNTIFS(Requisitos!D:D,"Cumple parcialmente",Requisitos!H:H,"Corregido")
A16: Cumplimiento HCU 032/2025 | B16: Requisitos que no se cumplen | C16: =COUNTIF(Requisitos!D:D,"No cumple") | D16: =COUNTIFS(Requisitos!D:D,"No cumple",Requisitos!H:H,"Corregido")
A17: Cumplimiento HCU 032/2025 | B17: Requisitos que dependen del punto 4.5 | C17: =COUNTIF(Requisitos!D:D,"Pendiente*")
A18: Cumplimiento HCU 032/2025 | B18: Promedio de los puntos | C18: =ROUND(AVERAGE(Puntos!C:C),1)
A19: Coherencia entre puntos | B19: Observaciones de severidad alta | C19: =COUNTIF(Coherencia!D:D,"Alta") | D19: =COUNTIFS(Coherencia!D:D,"Alta",Coherencia!G:G,"Corregido")
A20: Coherencia entre puntos | B20: Observaciones de severidad media | C20: =COUNTIF(Coherencia!D:D,"Media") | D20: =COUNTIFS(Coherencia!D:D,"Media",Coherencia!G:G,"Corregido")
A21: Coherencia entre puntos | B21: Observaciones de severidad baja | C21: =COUNTIF(Coherencia!D:D,"Baja") | D21: =COUNTIFS(Coherencia!D:D,"Baja",Coherencia!G:G,"Corregido")
A22: Correcciones aplicadas | B22: Cambios hechos en el Word revisado | C22: =COUNTA(Correcciones!A:A)-3

Sheet Requisitos
A1: Cumplimiento de la Resolución HCU N.º 032/2025 por requisito
A2: Puntaje de 0 a 100. El punto 4.5 se integrará después: sus requisitos figuran como pendientes.
A3: Artículo | B3: Requisito | C3: Punto | D3: Estado | E3: Puntaje | F3: Evidencia | G3: Recomendación | H3: Seguimiento | I3: Observaciones
A4: Art. 3, par. III | B4: Coherencia con la visión, misión, principios y valores de la UMSA (Estatuto Orgánico, PEI y Modelo Educativo) y sello identitario del egresado | C4: 2, 4.1, 4.3 | D4: Cumple parcialmente | E4: 55 | F4: 4.1 afirma «en concordancia con el Modelo Educativo de la UMSA», pero 4.1.2 cita el Modelo Educativo del SUB (CEUB, 2023); el modelo UMSA (Res. HCU N.º 057/2025) solo aparece en 12.1.1. No se transcribe ni contrasta la misión/visión de la UMSA. | G4: Incorporar un cuadro de alineación misión, visión y principios UMSA ↔ Carrera ↔ perfil, citando Estatuto Orgánico, PEI-UMSA 2026-2030 y Res. HCU N.º 057/2025. | H4: Pendiente
A5: Art. 5, par. I | B5: Rediseño: reformulación del perfil de egreso con base en el contexto y el mercado laboral, con actualización de la estructura curricular y de los planes de asignatura | C5: 3, 4.2.7, 4.4 | D5: Cumple | E5: 90 | F5: 3: «La adopción del perfil del Contador Público … reformula el perfil de egreso»; nuevo perfil en 4.2.7 y nueva malla en 4.4.3. La actualización de planes de asignatura queda en 4.5 (pendiente). | G5: Integrar el punto 4.5 para completar la actualización de los 43 planes de asignatura. | H5: Pendiente
A6: Art. 5, par. II | B6: Rediseño obligatorio cada siete años, por declaración de necesidad | C6: 1.13, 3 | D6: Cumple | E6: 95 | F6: 3: «Su vigencia de trece años supera el plazo de siete años fijado por la UMSA»; 1.13: Res. HCF N.º 1057/2026 aprueba el Diagnóstico y la Declaratoria de Necesidad. | G6: — | H6: Pendiente
A7: Art. 15, par. II, num. 1 a 3 | B7: Procedimiento: declaratoria de necesidad por el Honorable Consejo de Carrera, Asamblea Docente Estudiantil, Comisión Académica (Director, 5 docentes, 5 estudiantes), secretarios y subcomisiones paritarias | C7: 1.13, 3.2.1, 4.3.1 | D7: Cumple parcialmente | E7: 75 | F7: 3.2.1: Res. HCF N.º 1057/2026 (declaratoria) y Res. HCF N.º 1126/2026 (Comisión «integrada por el Director de Carrera, cinco docentes y cinco estudiantes»); Asamblea del 4/9/2026. No se cita la resolución del HCC que declara la necesidad ni la conformación de secretarios y subcomisiones. | G7: Citar la resolución del Honorable Consejo de Carrera y el acta de Asamblea; anexar la conformación de subcomisiones y el informe de la Comisión Académica (Art. 15.II.4). | H7: Pendiente
A8: Art. 16, par. I | B8: Aplicación del rediseño en la gestión siguiente a su aprobación | C8: 1.13, 16.2 | D8: Cumple | E8: 90 | F8: 1.13: «se aplicará conforme al Artículo 16»; 16.2: aprobación en 2026 e inicio del primer año en 2027. | G8: Prever un escenario alternativo si la aprobación del HCU no concluye en 2026. | H8: Pendiente
A9: Art. 8, par. II, num. 1 | B9: Identificación del Programa/Carrera: facultad, carrera, creación, resoluciones de planes anteriores, grados, sedes, diplomas, títulos, modalidad y otras características | C9: 1 | D9: Cumple | E9: 95 | F9: 1.1 a 1.13 cubren todos los elementos, con resoluciones (HCU N.º 438/2012, 290/2016, 426/2024) y cuadro año–grado–título. | G9: Unificar la cita del Reglamento General de Títulos y Grados (1.6 «XIII Congreso» frente a 3.2.1 «XI Congreso, 2009»). | H9: Pendiente
A10: Art. 12, Identificación, criterios 1 y 2 | B10: Descripción clara del grado terminal y de los grados intermedios; denominaciones intermedias no similares a la terminal | C10: 1.5–1.11, 5.4.1 | D10: Cumple | E10: 95 | F10: Cuadro de 1.6: TUM en Contabilidad–Auxiliar Contable; TS en Contabilidad General–Contador General; Licenciatura en Contaduría Pública–Contador Público Autorizado. Denominaciones diferenciadas y requisitos coherentes con el Reglamento de Modalidades (13.1.4). | G10: — | H10: Pendiente
A11: Art. 12, Identificación, criterio 3 | B11: Determinación precisa de la modalidad de enseñanza | C11: 1.12 | D11: Cumple | E11: 95 | F11: 1.12: «modalidad presencial, bajo régimen anual, en dos turnos … plataforma virtual … sin sustituir las horas presenciales». | G11: — | H11: Pendiente
A12: Art. 8, par. II, num. 2 | B12: Antecedentes: datos generales, misión y visión, plan de desarrollo, objetivos, caracterización, organigrama y estadísticas | C12: 2 | D12: Cumple | E12: 88 | F12: 2.1 a 2.7 presentes, con estadísticas 2021-2025 (Cuadros 4 a 11). El organigrama vigente es el de 2013 (Res. HCU N.º 139/2013); el nuevo queda pendiente (13.1.2). | G12: Incluir el organigrama propuesto para la implementación del rediseño. | H12: Pendiente
A13: Art. 12, Antecedentes, criterio 1 | B13: Misión y visión de la Carrera alineadas y armonizadas con las de la UMSA | C13: 2.2 | D13: Cumple parcialmente | E13: 50 | F13: 2.2 presenta visión, misión y valores de la Carrera sin contrastarlos con los de la UMSA; el Cuadro 12 (3.2.1) solo afirma «formulados de manera articulada». | G13: Añadir un cuadro comparativo misión/visión UMSA–Carrera que muestre elementos comunes (excelencia, compromiso social, emprendimiento, sociedad justa e inclusiva). | H13: Pendiente
A14: Art. 12, Antecedentes, criterio 2 | B14: Plan de desarrollo de la Carrera alineado y armonizado con el de la UMSA | C14: 2.3, 3.2.1 | D14: Cumple parcialmente | E14: 60 | F14: 2.3 es un párrafo: el plan «forma parte del plan estratégico Institucional de la Facultad» (Res. HCF N.º 1013/2026); 3.2.1 menciona «concordancia vertical con el PEI-UMSA 2026-2030», sin mapear los ejes de 2.4.1 a objetivos ni metas UMSA. | G14: Incorporar una matriz ejes de la Carrera–OE del PEI facultativo–PEI UMSA con metas e indicadores (pendiente conocido: PEI 2026-2030). | H14: Pendiente
A15: Art. 8, par. II, num. 3 | B15: Justificación: resultados de planes anteriores, políticas y normas, contexto económico y mercado laboral, ciencia y tecnología, contextualización de la oferta | C15: 3 | D15: Cumple | E15: 92 | F15: 3.1 a 3.5 desarrollan los cinco análisis con fuentes (Ipsos CIESMORI 2025, BID 2022, FODA IICCFA 2025, CTNAC, WEF) y cierran con el Cuadro 31 de necesidades de formación. | G15: — | H15: Pendiente
... A30: Art. 12, Estructura curricular, criterio 1 | B30: La competencia debe ser coherente con el perfil profesional | C30: 4.4.2 | D30: Cumple | E30: 90 | F30: La «Competencia global de la Carrera» reproduce los componentes de la declaración del perfil (4.2.7). | G30: — | H30: Pendiente
A31: Art. 8, num. 4.4; Art. 12, Estructura curricular, criterio 2 | B31: Mapa de competencias con unidades de competencia coherentes con la competencia y el perfil | C31: 4.4.2 | D31: Pendiente 4.5 | F31: 4.4.2: «La unidad de competencia y los elementos de competencia de cada asignatura se establecen en los planes de asignatura del punto 4.5». Solo hay competencias por área (Cuadro 3). | G31: pendiente: 4.5. Aun así, el Art. 8 pide el mapa en 4.4: incluir en 4.4.2 un cuadro con las 43 unidades de competencia por área. | H31: Pendiente
A32: Art. 12, Estructura curricular, criterio 3 | B32: Organización de las asignaturas según las áreas de formación detectadas | C32: 4.4.1 | D32: Cumple | E32: 88 | F32: Seis áreas en dos bloques; Cuadro 1 verificado (4.000 y 2.000 horas; 29 y 14 asignaturas). Ejes transversales en Cuadro 2, con el inglés como extracurricular. | G32: Precisar la ubicación del eje de inglés técnico dentro de la carga del plan. | H32: Pendiente
A33: Art. 8, num. 4.4; Art. 12, Estructura curricular, criterios 4 y 5 | B33: Malla con sigla, nombre, carga horaria, créditos y prerrequisitos, por ciclos y año, y relación por nivel de formación | C33: 4.4.3 | D33: Cumple | E33: 97 | F33: Cuadros 4 a 8 completos y coherentes: 60 créditos y 1.800 h de trabajo por año; 1.040/1.200/1.280/1.280/1.200 h presenciales; coinciden con la malla definitiva. | G33: Añadir una representación gráfica de la malla con ciclos y flujo de prerrequisitos. | H33: Pendiente
A34: Art. 12, Estructura curricular, criterio 6 | B34: La caracterización anualizada del plan debe guardar correspondencia con la competencia profesional | C34: 4.3.5, 4.4.3 | D34: Cumple parcialmente | E34: 70 | F34: Se declara el régimen anual, pero no se justifica su correspondencia con la competencia; el Plan 2013 tenía asignaturas semestrales (PS/SS) que ahora son anuales. | G34: Justificar la anualización frente a la competencia y al estudiante que trabaja. | H34: Pendiente
A35: Art. 8, num. 4.4 | B35: Cuadro de asignación de cargas horarias presenciales y no presenciales (según formato) | C35: 4.4.4 | D35: Cumple | E35: 85 | F35: Cuadro 9 por año: 6.000 h presenciales + 3.000 no presenciales = 9.000 h, 300 créditos. El detalle por asignatura (HP, HAA, HTG, HIP, HE) se remite a 4.5. | G35: Incluir un cuadro por asignatura según el formato universitario. | H35: Pendiente
A36: Art. 8, num. 8; RGTyG Art. 28; Res. HCU N.º 351/2021 | B36: Carga horaria máxima y sistema de créditos | C36: 4.4.3, 8.3, 8.5 | D36: Cumple | E36: 92 | F36: 6.000 h académicas («el máximo fijado por el Artículo 28»); 300 créditos, 60 por año, 1 crédito = 30 h. 8.2 suma horas académicas de 45 min con horas no presenciales para llegar a 45 h semanales, y 8.4 expresa las HIP «en horas cronológicas». | G36: Unificar la unidad de medida (académica o cronológica) en 8.2, 8.4 y 4.4.4. | H36: Pendiente
A37: Art. 8, num. 4.5; Art. 12, Planes de asignatura (criterios 1 a 7) | B37: Identificación y justificación, UC y EC, criterios y evidencias por EC, estrategias, cronograma por EC, evaluación por EC y UC, bibliografía | C37: 4.5 | D37: Pendiente 4.5 | F37: Punto 4.5 no incluido en esta versión. | G37: pendiente: 4.5. Al integrarlo, verificar la justificación y el cronograma por elementos de competencia, que el Art. 12 exige y que según los datos de referencia los itinerarios no traen. | H37: Pendiente
A38: Art. 9, par. II | B38: Estructura de los planes de asignatura en la complementación curricular | C38: 4.5 | D38: No aplica | F38: Rige la complementación anual (Art. 7); el rediseño se evalúa por el Art. 8 num. 4.5 y el Art. 12. | G38: Prever el formato del Art. 9 (horas y créditos por EC, Gantt semanal) para la primera complementación de 2027. | H38: Pendiente
A39: Art. 12, Estrategias, criterio 1 | B39: Diferenciar las estrategias de aprendizaje del estudiante de las de enseñanza del docente | C39: 4.6.1, 4.6.2 | D39: Cumple | E39: 95 | F39: Cuadro 1 (estrategias del estudiante) separado de 4.6.2 (acciones del docente); métodos (Cuadro 2) y recursos (Cuadro 3). | G39: — | H39: Pendiente
A40: Art. 12, Estrategias, criterio 2 | B40: Coherencia de las estrategias con EC, UC, perfil y modelo educativo | C40: 4.6, 4.5 | D40: Pendiente 4.5 | F40: La coherencia general con el perfil y el modelo se enuncia (4.6); la coherencia por EC y UC depende de los itinerarios. | G40: pendiente: 4.5. | H40: Pendiente
A41: Art. 12, Estrategias, criterio 3 | B41: Contemplar actividades autónomas y colectivas | C41: 4.6.1, 4.6.4 | D41: Cumple | E41: 95 | F41: Columna «Tipo de actividad: Autónoma / Colectiva» en el Cuadro 1 y tipología de 4.6.4. | G41: — | H41: Pendiente
A42: Art. 12, Evaluación, criterio 1 | B42: Evaluación concebida como retroalimentación para la mejora continua | C42: 4.7 | D42: Cumple | E42: 90 | F42: 4.7: «la evaluación se concibe como retroalimentación para la mejora continua»; evaluación diagnóstica, formativa y sumativa; rúbricas y portafolio. | G42: — | H42: Pendiente
A43: Art. 12, Evaluación, criterio 2 | B43: Estrategias de evaluación coherentes con el Reglamento del Régimen Académico Estudiantil | C43: 4.7, 5.3.1 | D43: Cumple | E43: 80 | F43: Escala 1-100 y aprobación con 51 «conforme a los Artículos 54 y 55 del reglamento» (5.3.1); diagnóstica no ponderada (Art. 28, en 5.2.2). | G43: Precisar las instancias de recuperación, segunda instancia y revisión de calificaciones del RRAE. | H43: Pendiente
A44: Art. 12, Evaluación y Admisión | B44: Especificar la nota o la cantidad de créditos para aprobar la asignatura | C44: 4.7.4, 5.3.1 | D44: Cumple | E44: 95 | F44: «Nota mínima de aprobación: cincuenta y uno (51) puntos sobre cien». | G44: — | H44: Pendiente
A45: Art. 12, Planes de asignatura, criterio 6 | B45: Evaluación descrita por cada elemento y unidad de competencia | C45: 4.5, 4.7.2 | D45: Pendiente 4.5 | F45: 4.7.2 anuncia evidencias por EC «conforme al Artículo 9»; la concreción está en los itinerarios. | G45: pendiente: 4.5. | H45: Pendiente
A46: Art. 8, num. 4.8; Art. 12, Prácticas preprofesionales | B46: Prácticas preprofesionales incluidas en el plan de estudios | C46: 4.8 | D46: Cumple parcialmente | E46: 75 | F46: Objetivos, cuatro niveles (Cuadro 1), ámbitos, doble tutoría, plan e informe y reconocimiento de experiencia laboral. | G46: Identificar las asignaturas que acogen las prácticas en 3.°, 4.° y 5.° año. | H46: Pendiente
A47: Art. 12, Prácticas preprofesionales | B47: Cantidad de horas de prácticas preprofesionales en empresa o institución pública o privada | C47: 4.8.3 | D47: No cumple | E47: 30 | F47: 4.8.3: «La carga horaria mínima, los requisitos de habilitación y el procedimiento de acreditación se establecerán en el Reglamento de Prácticas Preprofesionales», que según 13.1.2 está por «Elaborar». | G47: Fijar en el plan las horas mínimas por año (3.° a 5.°), su imputación dentro de las 3.000 h no presenciales y su acreditación. | H47: Pendiente
A48: Art. 8, num. 5 | B48: Perfil del postulante | C48: 5.1 | D48: Cumple | E48: 92 | F48: 5.1 describe la base cognitiva, aptitudes y valores, y la brecha del bachiller con su atención. | G48: — | H48: Pendiente
A49: Art. 12, Admisión, criterio 1 | B49: Modalidades de admisión planificadas según la misión UMSA y de la Carrera, los objetivos y el perfil | C49: 5.2 | D49: Cumple parcialmente | E49: 75 | F49: PSA, CPF y Admisión Especial (Res. HCU N.º 565/2024) bien documentadas; medidas 5.2.2 (pensamiento crítico, competencias digitales). El vínculo con la misión y el perfil queda implícito. | G49: Relacionar explícitamente los contenidos de PSA y CPF con el perfil de ingreso, la misión y el perfil profesional. | H49: Pendiente
A50: Art. 12, Admisión, criterio 2 | B50: Costos de PSA y CPF pertinentes a los indicadores socioeconómicos | C50: 5.2 | D50: Cumple | E50: 85 | F50: Art. 6 del Reglamento de Admisión: modalidades «gratuitas o que, de tener un costo, este no exceda el importe que demande su realización». | G50: Indicar el costo vigente y su relación con los ingresos familiares (48,9 % de estudiantes trabaja). | H50: Pendiente
A51: Art. 8, num. 5; Art. 12, Admisión, criterio 4 | B51: Condiciones de permanencia, licencias, suspensiones, plazo máximo de reincorporación y abandono | C51: 5.3.2 | D51: Cumple parcialmente | E51: 60 | F51: Se definen permanencia, licencia, abandono y readmisión; pero «Los plazos máximos de suspensión y de reincorporación … se establecen en el reglamento específico de la UMSA». Persisten referencias al 5.3.5 eliminado (pendiente conocido). | G51: Consignar en el plan los plazos máximos de suspensión y reincorporación aplicables. | H51: Pendiente
A52: Art. 12, Admisión, criterio 5 | B52: Modalidades de graduación con sigla, denominación, carga horaria y créditos | C52: 5.4, 13.1.4 | D52: Cumple parcialmente | E52: 40 | F52: Siete modalidades de licenciatura y dos técnicas con denominación y requisitos coherentes con el Reglamento (13.1.4). Solo el trabajo dirigido (1.280 h) y el diplomado (800 h/20 créditos) tienen carga; ninguna tiene sigla ni créditos de pregrado. | G52: Añadir un cuadro de modalidades con sigla, carga horaria y créditos, y su relación con los 300 créditos del plan. | H52: Pendiente
A53: Art. 8, num. 6; Art. 12, Investigación, criterio 1 | B53: Políticas y líneas de investigación o innovación tecnológica especificadas | C53: 6.1, 6.2 | D53: Cumple | E53: 82 | F53: Política basada en la Res. HCU N.º 90/2021; ocho líneas (LI-1 a LI-8) en cuatro grandes áreas. Las líneas no tienen descripción ni sublíneas, y no se indica su aprobación por el Comité Científico (Art. 11 del reglamento citado). | G53: Describir cada línea con sublíneas y asignaturas vinculadas, e indicar la resolución que las aprueba. | H53: Pendiente
A54: Art. 12, Investigación, criterio 2 | B54: Tesis, proyectos de grado y trabajo dirigido responden a las líneas de investigación | C54: 6.1.3, 13.1.4 | D54: Cumple parcialmente | E54: 65 | F54: 6.1.3 los declara «vinculados a las líneas … del punto 6.2», pero el Reglamento de Modalidades (Art. 11, Banco de Temas) solo los alinea «a las necesidades del sector productivo…», sin exigir la adscripción a una LI. | G54: Incluir en los Arts. 11, 16, 32 y 49 del Reglamento la adscripción obligatoria del perfil a una línea LI-1 a LI-8. | H54: Pendiente
A55: Art. 8, num. 8; Art. 12, Investigación, criterio 3 | B55: Horas de investigación de los estudiantes en los institutos de la Carrera o la Facultad | C55: 8.4, 6.1.3, 13.2.2 | D55: Cumple parcialmente | E55: 65 | F55: 8.4: 874 HIP (9,7 % de 9.000 h) distribuidas en las 43 asignaturas (Cuadros 3 y 4, sumas verificadas); no se establece qué parte se realiza en el IICCFA. 13.2.2 solo prevé un «Registro de horas de investigación». | G55: Precisar las horas que se cumplen o acreditan en el Instituto y su mecanismo de registro. | H55: Pendiente
A56: Art. 12, Investigación, criterio 4 | B56: Planes de asignatura con investigaciones alineadas a la unidad de competencia | C56: 4.5, 8.4 | D56: Pendiente 4.5 | F56: 8.4 asigna HIP a cada asignatura, lo que es un indicio favorable; la alineación por UC está en los itinerarios. | G56: pendiente: 4.5. | H56: Pendiente
A57: Art. 8, num. 7; Art. 12, Interacción social, criterios 1 y 3 | B57: Políticas y líneas de interacción social y de extensión universitaria | C57: 7.1, 7.2 | D57: Cumple | E57: 80 | F57: 7.1.1 y 7.1.2 (tres líneas: consultoría social contable, transferencia, vinculación); 7.2.1 y 7.2.2 (cinco líneas de extensión). La consultoría social se plantea en futuro: «se pretende la creación». | G57: Asignar responsables, metas e indicadores a cada línea. | H57: Pendiente
A58: Art. 12, Interacción social, criterio 2 | B58: Cantidad de horas de interacción social demostrables por estudiante | C58: 7, 13.1.2 | D58: No cumple | E58: 20 | F58: El punto 7 no fija horas; 13.1.2 remite a un Reglamento de Interacción Social por «Elaborar» con «Horas mínimas» (y a un 7.1.3 inexistente, pendiente conocido). | G58: Fijar horas mínimas, actividades válidas y evidencias de acreditación en el punto 7. | H58: Pendiente
A59: Art. 8, num. 8; Art. 12, Organización, criterio 1 | B59: Número de semanas lectivas por año, en concordancia con el calendario académico del HCU | C59: 8.1 | D59: Cumple | E59: 95 | F59: «40 semanas lectivas … en concordancia con el calendario académico aprobado por el Honorable Consejo Universitario». | G59: — | H59: Pendiente
A60: Art. 8, num. 8 | B60: Horas cronológicas por semana, total de horas planificadas, carga en investigación y sistema de créditos | C60: 8.2–8.5 | D60: Cumple | E60: 88 | F60: Cuadros 1 a 5 coherentes con la malla (6.000/3.000/9.000 h; 300 créditos; 874 HIP). 8 y 8.5 remiten al «sistema de créditos del punto 4.3.5», que trata la duración. | G60: Corregir la remisión (los créditos están en 4.4.3–4.4.4) y unificar unidades. | H60: Pendiente
A61: Art. 8, num. 8; Art. 12, Organización, criterio 2 | B61: Número mínimo y máximo de estudiantes por asignatura o paralelo, según reglamentación | C61: 8.6 | D61: No cumple | E61: 25 | F61: 8.6 solo presenta el diagnóstico (106 por paralelo) y delega en el Director. 11.1.1 afirma que «el punto 8.6 fija una meta intermedia de 80 … y una meta objetivo de 60», cifras que no figuran en 8.6. | G61: Fijar en 8.6 los mínimos y máximos por tipo de actividad (teoría, laboratorio, gabinete) y armonizarlos con 11.1.1 y 11.2.3. | H61: Pendiente
A62: Art. 8, num. 9; Art. 12, Material bibliográfico | B62: Bibliografía especializada y actualizada según los planes de asignatura y el número proyectado de estudiantes | C62: 9.1 | D62: Cumple parcialmente | E62: 70 | F62: Cuadro 2 por asignatura (3.108 ejemplares; 14,7 % desde 2015; 1 ejemplar por 8 inscripciones). Contradicción: CPA-102 y CPA-505 figuran como «Actualizada» (Cuadro 2) y «Sin títulos» (Cuadro 3). La política 9.1.4 no tiene metas cuantitativas. | G62: Plan de adquisiciones por asignatura y año con cantidades y costos; contrastar con la bibliografía de los itinerarios (pendiente: 4.5). | H62: Pendiente
A63: Art. 8, num. 9 | B63: Revistas especializadas, sistemas de información e internet | C63: 9.2–9.4 | D63: Cumple | E63: 80 | F63: Sin suscripciones propias; acceso por Scopus, Research4Life, SciELO, Dialnet y PERI; 385 y 165 Mbps. | G63: Gestionar acceso a la base de normas IFRS con material de pago (guías de implementación). | H63: Pendiente
A64: Art. 8, num. 10; Art. 12, Recursos educativos, criterio 1 | B64: Material multimedia adecuado, suficiente y actualizado según las estrategias | C64: 10 | D64: Cumple parcialmente | E64: 70 | F64: Los 12 componentes están descritos. Brechas: ERP y herramientas CAAT «No disponible» (Cuadro 3); 106 puestos de laboratorio frente a 3.143 inscritos; datos discordantes (20 frente a 27 equipos en el Monoblock; «3184 estudiantes»). | G64: Cuantificar requerimientos por asignatura y año, y corregir las cifras discordantes. | H64: Pendiente
A65: Art. 12, Recursos educativos, criterio 2 | B65: Garantizar el acceso de estudiantes y docentes a sistemas informáticos, internet y wifi | C65: 9.4, 10.12, 15 | D65: Cumple parcialmente | E65: 70 | F65: Doble enlace de internet y Moodle; pero 15 constata que «La señal de la red inalámbrica es débil en ambos edificios» y 10.12 señala límites de Moodle. | G65: Fijar metas de cobertura wifi y de capacidad concurrente de la plataforma, con plazos. | H65: Pendiente
A66: Art. 8, num. 11 | B66: Infraestructura, equipamiento y soporte informático; recursos humanos; política presupuestaria y financiera | C66: 11 | D66: Cumple | E66: 80 | F66: 11.1 a 11.3 con diagnóstico, requerimientos (Cuadros 6 y 9), ejecución presupuestaria 2020-2026, lineamientos, fuentes, fases y riesgos. | G66: Completar el plazo en blanco del «Aula multipropósito» (Cuadro 6). | H66: Pendiente
A67: Art. 11, par. V | B67: Consideración del alcance económico: avances tecnológicos y evaluación de costos humanos y económicos | C67: 3.4, 11 | D67: Cumple parcialmente | E67: 55 | F67: Avances tecnológicos bien sustentados (3.4). Los requerimientos (75 paralelos adicionales, laboratorios, software, ítems) no tienen costo estimado ni fuente asignada. | G67: Presupuesto plurianual 2027-2031 con costos por requerimiento y su fuente de financiamiento. | H67: Pendiente
A68: Art. 12, Implementación | B68: Sistema de monitoreo de la implementación (planes de asignatura, logro de EC/UC, recursos, estrategias, investigación formativa, interacción social) | C68: 11, 12.1.4 | D68: Cumple parcialmente | E68: 72 | F68: El monitoreo está en 12.1.4 (Formularios 1 y 2), no en 11, que solo prevé el seguimiento de la ejecución financiera (11.3.2). Los formularios no cubren la pertinencia de los recursos, la investigación formativa ni la interacción social. | G68: Incluir en 11 una matriz de monitoreo con indicadores, responsables y frecuencia para los seis aspectos del Art. 12. | H68: Pendiente
... A87: Art. 11, par. IX | B87: Articulación en ciclos formativos con postgrado | C87: 1.6, 5.4, 7.2.1 | D87: Cumple | E87: 92 | F87: TUM (2.° año), TS (3.° año), Licenciatura y graduación vía diplomado articulada con la Unidad de Postgrado. | G87: — | H87: Pendiente

Sheet Puntos
A1: Calificación por punto del índice
A2: Completitud y calidad de cada punto frente a lo que pide la Resolución HCU N.º 032/2025.
A3: Punto | B3: Título | C3: Puntaje | D3: Fortalezas | E3: Brechas | F3: Recomendación | G3: Seguimiento | H3: Observaciones
A4: 1 | B4: Identificación del programa/carrera | C4: 92 | D4: Todos los elementos del Art. 8 num. 1 con respaldo de resoluciones; cuadro año–grado–título; nivel de innovación y declaratoria identificados. | E4: Cita discordante del Reglamento General de Títulos y Grados (XIII frente a XI Congreso); no se menciona la resolución del HCC de declaratoria. | F4: Unificar las citas normativas y añadir la resolución del Consejo de Carrera. | G4: Pendiente
A5: 2 | B5: Antecedentes | C5: 78 | D5: Datos generales completos; estadísticas docentes y estudiantiles 2021-2025 bien analizadas; descripción del organigrama y del personal. | E5: No se demuestra la alineación de la misión, la visión ni el plan de desarrollo con los de la UMSA (Art. 12); plan de desarrollo en un solo párrafo; organigrama nuevo pendiente. | F5: Cuadros de alineación misión/visión y ejes–PEI UMSA; organigrama propuesto. | G5: Pendiente
A6: 3 | B6: Justificación de la innovación curricular | C6: 86 | D6: Evidencia sólida y triangulada (Ipsos, BID, FODA, CTNAC, WEF); Cuadro 12 frente a los criterios del Art. 11; síntesis de necesidades (Cuadro 31). | E6: No se resaltan las asignaturas que ya no existen ni se describe el Plan 1999; la comparación nacional se reduce a títulos; necesidades departamentales poco desagregadas. | F6: Cuadro de asignaturas suprimidas o transformadas y comparación curricular con universidades nacionales. | G6: Pendiente
A7: 4.1 | B7: Fundamentos curriculares | C7: 75 | D7: Cinco fundamentos explícitos; epistemología plural bien articulada; fundamento psicológico con roles definidos. | E7: No usa el Modelo Educativo UMSA (Res. HCU N.º 057/2025); falta el modelo didáctico; repeticiones (párrafo del 46 %, tabla IES, valores de 2.2.3) y un dato sin fuente. | F7: Reescribir 4.1.4 con los modelos UMSA y depurar duplicados. | G7: Pendiente
A8: 4.2 | B8: Referentes disciplinares | C8: 88 | D8: Objeto y objetivo claros; caracterización detallada de roles y funciones; perfil y atributos por dimensión vinculados a evidencia. | E8: No se vincula con la misión UMSA; el perfil promete inglés técnico sin respaldo curricular. | F8: Matriz necesidad → atributo → asignatura y vínculo con la misión UMSA. | G8: Pendiente
A9: 4.3 | B9: Plan de estudios propuesto | C9: 85 | D9: Modelo por competencias con cinco niveles de desagregación; principios del Art. 12 bien explicitados; objetivos ligados a brechas; duración y ciclos claros. | E9: Coherencia sustentada en el SUB y no en el Modelo UMSA; anualización sin justificar; brechas citadas sin dato (objetivos 2 y 9). | F9: Fundamentar con la Res. HCU N.º 057/2025 y justificar el régimen anual. | G9: Pendiente
A10: 4.4 | B10: Estructura curricular | C10: 82 | D10: Malla completa y verificada (sigla, horas, créditos, prerrequisitos); cuadro de áreas exacto; cargas presenciales y no presenciales por año. | E10: Mapa sin unidades de competencia (pendiente: 4.5); inglés solo extracurricular; sin cuadro de cargas por asignatura ni malla gráfica. | F10: Incluir las 43 UC en 4.4.2 y el cuadro de cargas por asignatura. | G10: Pendiente
A11: 4.6 | B11: Estrategias de aprendizaje y de enseñanza | C11: 88 | D11: Clara diferenciación estudiante/docente; actividades autónomas y colectivas; métodos activos y recursos tipificados. | E11: La coherencia por elemento de competencia depende de 4.5; los recursos no se cuantifican. | F11: Verificar la coherencia con los itinerarios al integrar 4.5. | G11: Pendiente
A12: 4.7 | B12: Evaluación de aprendizajes | C12: 82 | D12: Evaluación diagnóstica, formativa y sumativa; evidencias de desempeño, producto y conocimiento; nota mínima de 51. | E12: Poca precisión sobre instancias del RRAE (recuperación, segunda instancia); ponderación solo cualitativa; título duplicado. | F12: Detallar instancias y un rango orientativo de ponderación de las evidencias prácticas. | G12: Pendiente
A13: 4.8 | B13: Prácticas preprofesionales | C13: 55 | D13: Niveles progresivos, doble tutoría, ámbitos con convenio y reconocimiento de la experiencia laboral. | E13: No fija horas mínimas (exigidas por el Art. 12); no identifica las asignaturas que las acogen; remite a un reglamento aún por elaborar. | F13: Definir horas por año, asignaturas vinculadas y acreditación dentro del plan. | G13: Pendiente
A14: 5 | B14: Admisión, promoción y graduación | C14: 72 | D14: Admisión bien normada (Res. HCU N.º 565/2024); cursos de temporada y mesas de examen definidos; modalidades coherentes con el Reglamento de Graduación. | E14: Modalidades sin sigla, carga horaria ni créditos; plazos de suspensión y reincorporación no fijados; referencias al 5.3.5 eliminado. | F14: Cuadro de modalidades con sigla, horas y créditos; consignar plazos. | G14: Pendiente
A15: 6 | B15: Investigación | C15: 72 | D15: Política alineada con la UMSA; tres niveles de articulación; ocho líneas en cuatro grandes áreas. | E15: Horas en el Instituto no definidas; líneas sin descripción ni aprobación; el reglamento de graduación no exige adscripción a líneas. | F15: Describir líneas, fijar horas en el IICCFA y ligar los trabajos de grado a las LI. | G15: Pendiente
... A25: 16 | B25: Disposiciones de ejecución | C25: 75 | D25: Cuadro completo de 43 equivalencias (conteos verificados); principios de transitabilidad; cronograma 2026-2032; política de extinción con plazo. | E25: Sin horas en las equivalencias; sin reglamento de extinción; incoherencias del cronograma con 16.3 y con 4.5; salida de TUM no programada. | F25: Añadir horas, anexar el reglamento y armonizar el cronograma. | G25: Pendiente

Sheet Términos
A1: Términos de coherencia, por punto y página
A2: Ya aplicados en el Word revisado (Seguimiento = Corregido). «Mantener» indica menciones que no se cambian. Página según el Word antes del cambio.
A3: Punto | B3: Página | C3: Ubicación | D3: Categoría | E3: Término | F3: Contexto | G3: Cambiar a | H3: Seguimiento | I3: Observaciones
A4: 1.2 | B4: 12 | C4: Tabla | D4: Contador Público Autorizado | E4: Contador Público Autorizado | F4: …ca y del título en provisión nacional de Auditor Financiero por el de Contador Público Autorizado.… | G4: Mantener: se refiere al título en provisión nacional | H4: No aplica
A5: 1.4 | B5: 13 | C5: Tabla | D5: Plan 2027/2024 | E5: Plan de Estudios 2024 | F5: Plan de Estudios 2024… | G5: Mantener: alude al Plan de Estudios 2024 abrogado (Res. HCU N.º 016/2025), no al rediseño | H5: No aplica
A6: 1.6 | B6: 14 | C6: Tabla | D6: Contador Público Autorizado | E6: Contador Público Autorizado | F6: Contador Público Autorizado… | G6: Mantener: se refiere al título en provisión nacional | H6: No aplica
A7: 1.10 | B7: 14 | C7: Texto | D7: Contador Público Autorizado | E7: Contador Público Autorizado | F7: Título en provisión nacional de Contador Público Autorizado, conforme a la Resolución del Honorable Consejo Universitario N.º 438… | G7: Mantener: se refiere al título en provisión nacional | H7: No aplica
A8: 2.1 | B8: 17 | C8: Tabla | D8: Contador Público Autorizado | E8: Contador Público Autorizado | F8: Contador Público Autorizado… | G8: Mantener: se refiere al título en provisión nacional | H8: No aplica
A9: 2.7.1 | B9: 26 | C9: Tabla | D9: Contextual | E9: Contextual | F9: Área Contextual… | G9: Mantener: ya dice «Área Contextual» | H9: No aplica
A10: 2.7.1 | B10: 26 | C10: Tabla | D10: Contextual | E10: Contextual | F10: Total Área Contextual… | G10: Mantener: ya dice «Área Contextual» | H10: No aplica
A11: 2.7.1 | B11: 26 | C11: Texto | D11: Contextual | E11: contextual | F11: … área contable y de auditoría concentran 73 cargas horarias y el área contextual 35, lo que refleja la distribución de las asignaturas por áreas.… | G11: Área Contextual (o «del Área Contextual») | H11: Corregido | I11: Aplicado en el Word revisado
A12: 2.7.1 | B12: 26 | C12: Tabla | D12: Contextual | E12: Contextual | F12: Área Contextual… | G12: Mantener: ya dice «Área Contextual» | H12: No aplica
A13: 2.7.1 | B13: 27 | C13: Tabla | D13: Contextual | E13: Contextual | F13: Total Área Contextual… | G13: Mantener: ya dice «Área Contextual» | H13: No aplica
A14: 2.7.1 | B14: 27 | C14: Tabla | D14: Contextual | E14: Contextual | F14: Área Contextual… | G14: Mantener: ya dice «Área Contextual» | H14: No aplica
A15: 2.7.1 | B15: 27 | C15: Tabla | D15: Contextual | E15: Contextual | F15: Total Área Contextual… | G15: Mantener: ya dice «Área Contextual» | H15: No aplica
A16: 2.7.1 | B16: 27 | C16: Texto | D16: Contextual | E16: contextuales | F16: …pliar su cobertura a más asignaturas del área contable y de las áreas contextuales de Economía, Administración y Derecho. Las solicitudes de incremento … | G16: Área Contextual (o «del Área Contextual») | H16: Corregido | I16: Aplicado en el Word revisado
A17: 3.1.1 | B17: 31 | C17: Texto | D17: Troncal | E17: troncales | F17: …, 43 asignaturas y 6.000 horas académicas. De las asignaturas, 29 son troncales, el 67,44 %, en las áreas de Información Financiera y de Servicios de… | G17: Área Contable y de Auditoría (ajustar artículo y número: «asignaturas del Área Contable y de Auditoría») | H17: Corregido | I17: Aplicado en el Word revisado
A18: 3.1.1 | B18: 31 | C18: Texto | D18: Contextual | E18: contextuales | F18: …ión Financiera y de Servicios de Atestación y No Atestación, y 14 son contextuales, el 32,56 %, en las áreas de Administración, Derecho, Economía y Mate… | G18: Área Contextual (o «del Área Contextual») | H18: Corregido | I18: Aplicado en el Word revisado
A19: 3.1.1 | B19: 33 | C19: Tabla | D19: Troncal | E19: troncal | F19: Subtotal troncal… | G19: Área Contable y de Auditoría (ajustar artículo y número: «asignaturas del Área Contable y de Auditoría») | H19: Corregido | I19: Aplicado en el Word revisado
A20: 3.1.1 | B20: 33 | C20: Tabla | D20: Contextual | E20: contextual | F20: Subtotal contextual… | G20: Área Contextual (o «del Área Contextual») | H20: Corregido | I20: Aplicado en el Word revisado
A21: 3.1.1 | B21: 33 | C21: Texto | D21: Contextual | E21: contextuales | F21: La estructura muestra un rasgo que condiciona el rediseño: las áreas contextuales se concentran en los tres primeros años y desaparecen en cuarto y qui… | G21: Área Contextual (o «del Área Contextual») | H21: Corregido | I21: Aplicado en el Word revisado
A22: 3.1.1 | B22: 33 | C22: Texto | D22: Contextual | E22: contextuales | F22: …ebería aplicarlos. El rediseño debe articular verticalmente las áreas contextuales con los problemas contables, conforme al principio de interdisciplina… | G22: Área Contextual (o «del Área Contextual») | H22: Corregido | I22: Aplicado en el Word revisado
A23: 3.5.2 | B23: 47 | C23: Tabla | D23: Contador Público Autorizado | E23: Contador Público Autorizado | F23: Contador Público Autorizado… | G23: Mantener: se refiere al título en provisión nacional | H23: No aplica
A24: 3.5.2 | B24: 47 | C24: Tabla | D24: Contador Público Autorizado | E24: Contador Público Autorizado | F24: Contador Público Autorizado… | G24: Mantener: se refiere al título en provisión nacional | H24: No aplica
A25: 3.5.2 | B25: 47 | C25: Tabla | D25: Contador Público Autorizado | E25: Contador Público Autorizado | F25: Contador Público Autorizado… | G25: Mantener: se refiere al título en provisión nacional | H25: No aplica
A26: 3.5.2 | B26: 47 | C26: Tabla | D26: Contador Público Autorizado | E26: Contador Público Autorizado | F26: Contador Público Autorizado, desde la Resolución HCU N.º 438/2012… | G26: Mantener: se refiere al título en provisión nacional | H26: No aplica
A27: 3.5.2 | B27: 47 | C27: Texto | D27: Contador Público Autorizado | E27: Contador Público Autorizado | F27: Las cuatro universidades otorgan el título de Contador Público Autorizado. Sin embargo, el perfil de egreso del Plan 2013 de la UMSA conserva l… | G27: Mantener: se refiere al título en provisión nacional | H27: No aplica
A28: 4.1.1 | B28: 55 | C28: Texto | D28: Contador Público Autorizado | E28: Contador Público Autorizado | F28: …nes y los seres humanos son unidades complejas multidimensionales. El Contador Público Autorizado debe reconocer que la información contable no es únicamente cuantitat… | G28: Contador Público | H28: Corregido | I28: Aplicado en el Word revisado
A29: 4.1.1 | B29: 55 | C29: Texto | D29: Contador Público Autorizado | E29: Contador Público Autorizado | F29: … la incertidumbre y constante evolución del mundo de los negocios, el Contador Público Autorizado aplica su juicio crítico para unir la unidad con la multiplicidad en … | G29: Contador Público | H29: Corregido | I29: Aplicado en el Word revisado
A30: 4.2.6 | B30: 70 | C30: Texto | D30: Contador Público Autorizado | E30: Contador Público Autorizado | F30: Cuadro 3. Matriz resumen de las competencias del Contador Público Autorizado… | G30: Contador Público | H30: Corregido | I30: Aplicado en el Word revisado
A31: 4.3.3 | B31: 78 | C31: Texto | D31: Contador Público Autorizado | E31: Contador Público Autorizado | F31: …cenciatura en Contaduría Pública y al título en provisión nacional de Contador Público Autorizado, en modalidad presencial y régimen anual, con una duración de cinco a… | G31: Mantener: se refiere al título en provisión nacional | H31: No aplica
A32: 4.4.1 | B32: 82 | C32: Texto | D32: Contextual | E32: contextual | F32: …table y de auditoría, que forman el núcleo de la profesión, y el área contextual, que aportan el sustento multidisciplinario.… | G32: Área Contextual (o «del Área Contextual») | H32: Corregido | I32: Aplicado en el Word revisado
A33: 4.4.1 | B33: 82 | C33: Tabla | D33: Contextual | E33: Contextual | F33: Área Contextual… | G33: Mantener: ya dice «Área Contextual» | H33: No aplica
A34: 4.4.1 | B34: 82 | C34: Texto | D34: Contextual | E34: contextual | F34: Área contextual:… | G34: Área Contextual (o «del Área Contextual») | H34: Corregido | I34: Aplicado en el Word revisado
A35: 5.4.1 | B35: 106 | C35: Tabla | D35: Contador Público Autorizado | E35: Contador Público Autorizado | F35: Contador Público Autorizado… | G35: Mantener: se refiere al título en provisión nacional | H35: No aplica
A36: 9.1.1 | B36: 127 | C36: Texto | D36: Plan 2027/2024 | E36: Plan 2024 | F36: …erios distintos de clasificación de las modalidades de graduación. El Plan 2024 consignaba 5.702 libros y 3.046 trabajos académicos, lo que muestra u… | G36: Mantener: alude al Plan de Estudios 2024 abrogado (Res. HCU N.º 016/2025), no al rediseño | H36: No aplica
A37: 9.1.1 | B37: 127 | C37: Texto | D37: Plan 2027/2024 | E37: Plan 2024 | F37: … institucional de la UMSA, que ofrece documentos a texto completo; el Plan 2024 registró 2.806 documentos digitales de la Carrera en ese repositorio.… | G37: Mantener: alude al Plan de Estudios 2024 abrogado (Res. HCU N.º 016/2025), no al rediseño | H37: No aplica
A38: 11.2.1 | B38: 148 | C38: Texto | D38: Contador Público Autorizado | E38: Contador Público Autorizado | F38: …egundo, el área de Servicios de Aseguramiento, núcleo profesional del Contador Público Autorizado, tiene solo 12 titulares de 45 designaciones. Tercero, solo dos carga… | G38: Contador Público | H38: Corregido | I38: Aplicado en el Word revisado
A39: 11.2.1 | B39: 148 | C39: Texto | D39: Troncal | E39: troncales | F39: …con 79 ítems de auxiliares de docencia, que priorizan las asignaturas troncales. El Instituto de Investigaciones dispone de 320 horas mensuales y su … | G39: Área Contable y de Auditoría (ajustar artículo y número: «asignaturas del Área Contable y de Auditoría») | H39: Corregido | I39: Aplicado en el Word revisado
A40: 11.2.2 | B40: 149 | C40: Texto | D40: Contador Público Autorizado | E40: Contador Público Autorizado | F40: …en Contaduría Pública / Auditoría con Título en Provisión Nacional de Contador Público Autorizado / Auditor Financiero. … | G40: Mantener: se refiere al título en provisión nacional | H40: No aplica
A41: 11.2.2 | B41: 149 | C41: Texto | D41: Contador Público Autorizado | E41: Contador Público Autorizado | F41: …en Contaduría Pública / Auditoría con Título en Provisión Nacional de Contador Público Autorizado / Auditor Financiero con Posgrado en el área de Informática / TIC; o … | G41: Mantener: se refiere al título en provisión nacional | H41: No aplica
A42: 11.2.2 | B42: 150 | C42: Texto | D42: Contador Público Autorizado | E42: Contador Público Autorizado | F42: …en Contaduría Pública / Auditoría con Título en Provisión Nacional de Contador Público Autorizado / Auditor Financiero con Posgrado en el área de Investigación; o Lice… | G42: Mantener: se refiere al título en provisión nacional | H42: No aplica
A43: 11.2.2 | B43: 150 | C43: Texto | D43: Contador Público Autorizado | E43: Contador Público Autorizado | F43: …en Contaduría Pública / Auditoría con Título en Provisión Nacional de Contador Público Autorizado / Auditor Financiero.… | G43: Mantener: se refiere al título en provisión nacional | H43: No aplica
A44: 11.2.2 | B44: 150 | C44: Texto | D44: Contador Público Autorizado | E44: Contador Público Autorizado | F44: …en Contaduría Pública / Auditoría con Título en Provisión Nacional de Contador Público Autorizado / Auditor Financiero con Posgrado en Auditoría de Sistemas / Ciberseg… | G44: Mantener: se refiere al título en provisión nacional | H44: No aplica
A45: 11.2.2 | B45: 150 | C45: Texto | D45: Contador Público Autorizado | E45: Contador Público Autorizado | F45: …en Contaduría Pública / Auditoría con Título en Provisión Nacional de Contador Público Autorizado / Auditor Financiero con Posgrado en Sostenibilidad, ESG, NIEA 3000 o… | G45: Mantener: se refiere al título en provisión nacional | H45: No aplica
A46: 11.2.2 | B46: 150 | C46: Texto | D46: Contador Público Autorizado | E46: Contador Público Autorizado | F46: …en Contaduría Pública / Auditoría con Título en Provisión Nacional de Contador Público Autorizado / Auditor Financiero con Posgrado en Auditoría Forense, Peritaje o De… | G46: Mantener: se refiere al título en provisión nacional | H46: No aplica
A47: 11.2.2 | B47: 150 | C47: Texto | D47: Contador Público Autorizado | E47: Contador Público Autorizado | F47: …en Contaduría Pública / Auditoría con Título en Provisión Nacional de Contador Público Autorizado / Auditor Financiero con Posgrado en el área de investigación Científ… | G47: Mantener: se refiere al título en provisión nacional | H47: No aplica
A48: 11.2.2 | B48: 150 | C48: Texto | D48: Contador Público Autorizado | E48: Contador Público Autorizado | F48: …en Contaduría Pública / Auditoría con Título en Provisión Nacional de Contador Público Autorizado / Auditor Financiero.… | G48: Mantener: se refiere al título en provisión nacional | H48: No aplica
A49: 11.2.2 | B49: 150 | C49: Texto | D49: Contador Público Autorizado | E49: Contador Público Autorizado | F49: …en Contaduría Pública / Auditoría con Título en Provisión Nacional de Contador Público Autorizado / Auditor Financiero.… | G49: Mantener: se refiere al título en provisión nacional | H49: No aplica
A50: 11.2.2 | B50: 151 | C50: Texto | D50: Contador Público Autorizado | E50: Contador Público Autorizado | F50: …en Contaduría Pública / Auditoría con Título en Provisión Nacional de Contador Público Autorizado / Auditor Financiero o Licenciatura en Economía con Título en Provisi… | G50: Mantener: se refiere al título en provisión nacional | H50: No aplica
A51: 11.3.1 | B51: 152 | C51: Texto | D51: Plan 2027/2024 | E51: Plan 2027 | F51: … evaluar la capacidad financiera que respaldará la implementación del Plan 2027, se analizó la ejecución presupuestaria de gastos de la Carrera desde… | G51: Rediseño Curricular (ajustar artículo: «el Rediseño Curricular», «del Rediseño Curricular») | H51: Corregido | I51: Aplicado en el Word revisado
A52: 11.3.2 | B52: 153 | C52: Texto | D52: Plan 2027/2024 | E52: Plan 2027 | F52: …upuesto inercial y una ejecución baja. La política presupuestaria del Plan 2027 se rige por los siguientes lineamientos:… | G52: Rediseño Curricular (ajustar artículo: «el Rediseño Curricular», «del Rediseño Curricular») | H52: Corregido | I52: Aplicado en el Word revisado
A53: 13 | B53: 163 | C53: Texto | D53: Plan 2027/2024 | E53: Plan de Estudios 2027 | F53: Este punto identifica la normativa universitaria que rige el Plan de Estudios 2027, establece los reglamentos internos que la Carrera debe mantener, act… | G53: Rediseño Curricular (ajustar artículo: «el Rediseño Curricular», «del Rediseño Curricular») | H53: Corregido | I53: Aplicado en el Word revisado
A54: 13.1.1 | B54: 163 | C54: Texto | D54: Plan 2027/2024 | E54: Plan 2027 | F54: Cuadro 1. Normativa universitaria aplicable al Plan 2027… | G54: Rediseño Curricular (ajustar artículo: «el Rediseño Curricular», «del Rediseño Curricular») | H54: Corregido | I54: Aplicado en el Word revisado
A55: 13.1.1 | B55: 164 | C55: Texto | D55: Plan 2027/2024 | E55: Plan de Estudios 2024 | F55: Fuente: elaboración con base en la normativa citada en el Plan de Estudios 2024, el Diagnóstico 2026, los puntos 5 a 12 y las Resoluciones HCU N.º 13… | G55: Mantener: alude al Plan de Estudios 2024 abrogado (Res. HCU N.º 016/2025), no al rediseño | H55: No aplica
A56: 13.1.2 | B56: 164 | C56: Texto | D56: Plan 2027/2024 | E56: Plan 2027 | F56: La implementación del Plan 2027 requiere actualizar los reglamentos internos vigentes y elaborar los … | G56: Rediseño Curricular (ajustar artículo: «el Rediseño Curricular», «del Rediseño Curricular») | H56: Corregido | I56: Aplicado en el Word revisado
A57: 13.1.2 | B57: 164 | C57: Texto | D57: Plan 2027/2024 | E57: Plan 2027 | F57: Cuadro 2. Reglamentos internos para la implementación del Plan 2027… | G57: Rediseño Curricular (ajustar artículo: «el Rediseño Curricular», «del Rediseño Curricular») | H57: Corregido | I57: Aplicado en el Word revisado
A58: 13.1.3 | B58: 165 | C58: Texto | D58: Plan 2027/2024 | E58: Plan 2027 | F58: … 60 días calendario, ocho semanas, en las carreras anualizadas. En el Plan 2027, el estudiante puede nivelar o adelantar hasta dos asignaturas por te… | G58: Rediseño Curricular (ajustar artículo: «el Rediseño Curricular», «del Rediseño Curricular») | H58: Corregido | I58: Aplicado en el Word revisado
A59: 13.1.3 | B59: 165 | C59: Texto | D59: Troncal | E59: troncales | F59: …aturas por temporada; se habilitan las asignaturas contextuales y las troncales de hasta 80 horas anuales, y las troncales de mayor carga solo pueden… | G59: Área Contable y de Auditoría (ajustar artículo y número: «asignaturas del Área Contable y de Auditoría») | H59: Corregido | I59: Aplicado en el Word revisado
A60: 13.1.3 | B60: 165 | C60: Texto | D60: Troncal | E60: troncales | F60: …naturas contextuales y las troncales de hasta 80 horas anuales, y las troncales de mayor carga solo pueden cursarse para recuperar una asignatura rep… | G60: Área Contable y de Auditoría (ajustar artículo y número: «asignaturas del Área Contable y de Auditoría») | H60: Corregido | I60: Aplicado en el Word revisado
A61: 13.1.3 | B61: 165 | C61: Texto | D61: Contextual | E61: contextuales | F61: …tar hasta dos asignaturas por temporada; se habilitan las asignaturas contextuales y las troncales de hasta 80 horas anuales, y las troncales de mayor c… | G61: Área Contextual (o «del Área Contextual») | H61: Corregido | I61: Aplicado en el Word revisado
A62: 13.1.4 | B62: 166 | C62: Texto | D62: Contador Público Autorizado | E62: Contador Público Autorizado - CPA | F62: …ional Ordinaria de Universidades del SUB (Ratificación del modelo del Contador Público Autorizado - CPA)… | G62: Mantener: es el nombre de la Resolución N.º 07/2024 (decisión de la comisión) | H62: No aplica
A63: 13.1.4 | B63: 166 | C63: Texto | D63: Plan 2027/2024 | E63: Plan de Estudios 2027 | F63: De conformidad con el Plan de Estudios 2027 y la estructura de titulación de la Carrera de Contaduría Pública, se… | G63: Rediseño Curricular (ajustar artículo: «el Rediseño Curricular», «del Rediseño Curricular») | H63: Corregido | I63: Aplicado en el Word revisado
A64: 13.1.4 | B64: 166 | C64: Texto | D64: Contador Público Autorizado | E64: Contador Público Autorizado (CPA) | F64: …Licenciado(a) en Contaduría Pública y Título en Provisión Nacional de Contador Público Autorizado (CPA), tras el cumplimiento de 6.000 horas académicas (43 asignaturas) y la… | G64: Mantener: se refiere al título en provisión nacional | H64: No aplica
A65: 13.1.4 | B65: 166 | C65: Texto | D65: Plan 2027/2024 | E65: Plan de Estudios 2027 | F65: …tricto apego al catálogo del Sistema de la Universidad Boliviana y al Plan de Estudios 2027, se reconocen oficialmente las siguientes modalidades:… | G65: Rediseño Curricular (ajustar artículo: «el Rediseño Curricular», «del Rediseño Curricular») | H65: Corregido | I65: Aplicado en el Word revisado
A66: 13.1.4 | B66: 167 | C66: Texto | D66: Troncal | E66: troncales | F66: …cnico Superior: Evaluación comprensiva sobre las ocho (8) asignaturas troncales del ciclo intermedio (Primer a Tercer año).… | G66: Área Contable y de Auditoría (ajustar artículo y número: «asignaturas del Área Contable y de Auditoría») | H66: Corregido | I66: Aplicado en el Word revisado
A67: 13.1.4 | B67: 175 | C67: Texto | D67: Contador Público Autorizado | E67: Contador Público Autorizado (CPA) | F67: … Contaduría Pública y del Título Profesional en Provisión Nacional de Contador Público Autorizado (CPA).… | G67: Mantener: se refiere al título en provisión nacional | H67: No aplica
A68: 13.1.4 | B68: 181 | C68: Texto | D68: Contador Público Autorizado | E68: Contador Público Autorizado (CPA) | F68: … Contaduría Pública y del Título Profesional en Provisión Nacional de Contador Público Autorizado (CPA).… | G68: Mantener: se refiere al título en provisión nacional | H68: No aplica
A69: 13.1.4 | B69: 181 | C69: Texto | D69: Contador Público Autorizado | E69: Contador Público Autorizado (CPA) | F69: …és (UMSA). Su finalidad es aplicar las competencias profesionales del Contador Público Autorizado (CPA) en la solución de problemas reales del entorno institucional.… | G69: Contador Público | H69: Corregido | I69: Aplicado en el Word revisado
A70: 13.1.4 | B70: 188 | C70: Texto | D70: Contador Público Autorizado | E70: Contador Público Autorizado (CPA) | F70: … Contaduría Pública y del Título Profesional en Provisión Nacional de Contador Público Autorizado (CPA).… | G70: Mantener: se refiere al título en provisión nacional | H70: No aplica
A71: 13.1.4 | B71: 193 | C71: Texto | D71: Contador Público Autorizado | E71: Contador Público Autorizado (CPA) | F71: … Contaduría Pública y del Título Profesional en Provisión Nacional de Contador Público Autorizado (CPA).… | G71: Mantener: se refiere al título en provisión nacional | H71: No aplica
A72: 13.1.4 | B72: 195 | C72: Texto | D72: Contador Público Autorizado | E72: Contador Público Autorizado (CPA) | F72: … Contaduría Pública y del Título Profesional en Provisión Nacional de Contador Público Autorizado (CPA).… | G72: Mantener: se refiere al título en provisión nacional | H72: No aplica
A73: 13.1.4 | B73: 197 | C73: Texto | D73: Contador Público Autorizado | E73: Contador Público Autorizado (CPA) | F73: … Contaduría Pública y del Título Profesional en Provisión Nacional de Contador Público Autorizado (CPA).… | G73: Mantener: se refiere al título en provisión nacional | H73: No aplica
A74: 13.1.4 | B74: 197 | C74: Texto | D74: Contador Público Autorizado | E74: Contador Público Autorizado (CPA) | F74: …n Contaduría Pública y el Título Profesional en Provisión Nacional de Contador Público Autorizado (CPA).… | G74: Mantener: se refiere al título en provisión nacional | H74: No aplica
A75: 13.1.4 | B75: 199 | C75: Texto | D75: Plan 2027/2024 | E75: Plan de Estudios 2027 | F75: … de estudios, o podrán acogerse voluntariamente a las modalidades del Plan de Estudios 2027 mediante homologación ante la Dirección de Carrera.… | G75: Rediseño Curricular (ajustar artículo: «el Rediseño Curricular», «del Rediseño Curricular») | H75: Corregido | I75: Aplicado en el Word revisado
A76: 13.1.4 | B76: 200 | C76: Texto | D76: Contador Público Autorizado | E76: Contador Público Autorizado - CPA | F76: …e la UMSA, siendo de aplicación obligatoria para el Plan de Estudios (Contador Público Autorizado - CPA).… | G76: Rediseño Curricular de la Licenciatura en Contaduría Pública (frase completa: «para el Rediseño Curricular de la Licenciatura en Contaduría Pública») | H76: Corregido | I76: Aplicado en el Word revisado
A77: 13.2.2 | B77: 200 | C77: Texto | D77: Plan 2027/2024 | E77: Plan 2027 | F77: …glamento interno del Instituto se actualizará para articularlo con el Plan 2027 con base en los siguientes lineamientos:… | G77: Rediseño Curricular (ajustar artículo: «el Rediseño Curricular», «del Rediseño Curricular») | H77: Corregido | I77: Aplicado en el Word revisado
A78: 14.4 | B78: 208 | C78: Texto | D78: Plan 2027/2024 | E78: Plan de Estudios 2024 | F78: Fuente: Plan de Estudios 2024.… | G78: Mantener: alude al Plan de Estudios 2024 abrogado (Res. HCU N.º 016/2025), no al rediseño | H78: No aplica
A79: 14.6 | B79: 209 | C79: Texto | D79: Plan 2027/2024 | E79: Plan de Estudios 2024 | F79: Fuente: Plan de Estudios 2024. Todos los ambientes son de uso exclusivo de la Carrera.… | G79: Mantener: alude al Plan de Estudios 2024 abrogado (Res. HCU N.º 016/2025), no al rediseño | H79: No aplica
A80: 16 | B80: 220 | C80: Texto | D80: Plan 2027/2024 | E80: Plan de Estudios 2027 | F80: …esoluciones HCC N.º 162/2012, HCF N.º 929/2012 y HCU N.º 025/2013, al Plan de Estudios 2027: el cuadro de convalidación y homologación de asignaturas para estudi… | G80: Rediseño Curricular (ajustar artículo: «el Rediseño Curricular», «del Rediseño Curricular») | H80: Corregido | I80: Aplicado en el Word revisado
A81: 16.1.1 | B81: 220 | C81: Texto | D81: Plan 2027/2024 | E81: Plan 2027 | F81: …tura aprobada en el Plan 2013 conserva su validez y se reconoce en el Plan 2027 mediante homologación o convalidación.… | G81: Rediseño Curricular (ajustar artículo: «el Rediseño Curricular», «del Rediseño Curricular») | H81: Corregido | I81: Aplicado en el Word revisado
A82: 16.1.1 | B82: 220 | C82: Texto | D82: Plan 2027/2024 | E82: Plan 2027 | F82: …ia en el Plan 2013, con la asignación de la cátedra equivalente en el Plan 2027.… | G82: Rediseño Curricular (ajustar artículo: «el Rediseño Curricular», «del Rediseño Curricular») | H82: Corregido | I82: Aplicado en el Word revisado
A83: 16.1.1 | B83: 220 | C83: Texto | D83: Plan 2027/2024 | E83: Plan 2027 | F83: Implantación gradual. El Plan 2027 se aplica año por año desde 2027, y el Plan 2013 se extingue de forma… | G83: Rediseño Curricular (ajustar artículo: «el Rediseño Curricular», «del Rediseño Curricular») | H83: Corregido | I83: Aplicado en el Word revisado
A84: 16.1.3 | B84: 220 | C84: Texto | D84: Plan 2027/2024 | E84: Plan 2027 | F84: 16.1.3Cuadro de equivalencias entre el Plan 2013 y el Plan 2027… | G84: Rediseño Curricular (ajustar artículo: «el Rediseño Curricular», «del Rediseño Curricular») | H84: Corregido | I84: Aplicado en el Word revisado
A85: 16.1.3 | B85: 220 | C85: Texto | D85: Plan 2027/2024 | E85: Plan 2027 | F85: …quivalente. Las 43 asignaturas del Plan 2013 tienen equivalente en el Plan 2027:… | G85: Rediseño Curricular (ajustar artículo: «el Rediseño Curricular», «del Rediseño Curricular») | H85: Corregido | I85: Aplicado en el Word revisado
A86: 16.1.3 | B86: 220 | C86: Texto | D86: Plan 2027/2024 | E86: Plan de Estudios 2027 | F86: Cuadro 1. Equivalencias entre el Plan de Estudios 2013 y el Plan de Estudios 2027… | G86: Rediseño Curricular (ajustar artículo: «el Rediseño Curricular», «del Rediseño Curricular») | H86: Corregido | I86: Aplicado en el Word revisado
A87: 16.1.3 | B87: 220 | C87: Tabla | D87: Plan 2027/2024 | E87: Plan 2027 | F87: Asignatura equivalente del Plan 2027… | G87: Rediseño Curricular (ajustar artículo: «el Rediseño Curricular», «del Rediseño Curricular») | H87: Corregido | I87: Aplicado en el Word revisado
A88: 16.1.3 | B88: 222 | C88: Texto | D88: Plan 2027/2024 | E88: Plan 2027 | F88: …a de sus contenidos: CPA-102, CPA-305, CPA-505, CPA-506 y MAT-201 del Plan 2027.… | G88: Rediseño Curricular (ajustar artículo: «el Rediseño Curricular», «del Rediseño Curricular») | H88: Corregido | I88: Aplicado en el Word revisado
A89: 16.1.4 | B89: 222 | C89: Texto | D89: Plan 2027/2024 | E89: Plan 2027 | F89: El estudiante del Plan 2013 puede migrar voluntariamente al Plan 2027 en cualquier momento de la transición, con el reconocimiento de todas… | G89: Rediseño Curricular (ajustar artículo: «el Rediseño Curricular», «del Rediseño Curricular») | H89: Corregido | I89: Aplicado en el Word revisado
A90: 16.1.4 | B90: 222 | C90: Texto | D90: Plan 2027/2024 | E90: Plan 2027 | F90: …e fueron aprobadas; el estudiante que migra cursa las asignaturas del Plan 2027 que no tienen equivalente aprobado, con sujeción a sus prerrequisitos… | G90: Rediseño Curricular (ajustar artículo: «el Rediseño Curricular», «del Rediseño Curricular») | H90: Corregido | I90: Aplicado en el Word revisado
A91: 16.1.4 | B91: 222 | C91: Texto | D91: Plan 2027/2024 | E91: Plan 2027 | F91: …entes titulares conservan su cátedra en la asignatura equivalente del Plan 2027. Cuando la carga horaria de la asignatura disminuye, la diferencia se… | G91: Rediseño Curricular (ajustar artículo: «el Rediseño Curricular», «del Rediseño Curricular») | H91: Corregido | I91: Aplicado en el Word revisado
... A98: 16.3 | B98: 224 | C98: Texto | D98: Plan 2027/2024 | E98: Plan 2027 | F98: …de ese plan. Vencido el plazo, se gradúa mediante las modalidades del Plan 2027 o el PETAENG, conforme al punto 13.1.4.… | G98: Rediseño Curricular (ajustar artículo: «el Rediseño Curricular», «del Rediseño Curricular») | H98: Corregido | I98: Aplicado en el Word revisado

Sheet Correcciones
A1: Correcciones aplicadas en el Word revisado
A2: Cada cambio hecho sobre el Prefinal. La columna Seguimiento sirve para dar la conformidad de la comisión.
A3: Punto | B3: Tipo | C3: Antes | D3: Después | E3: Contexto | F3: Seguimiento | G3: Observaciones
A4: Todos | B4: Estructura y formato | D4: Se quitaron las líneas de título «Diseño Curricular / nombre del punto» al inicio de cada punto (22 pares). | F4: En proceso
A5: Todos | B5: Estructura y formato | D5: Se agregaron 24 páginas separadoras: puntos 1 a 16 y 4.1 a 4.8, con una página reservada para 4.5 Planes de asignatura. | F5: En proceso
A6: Todos | B6: Estructura y formato | D6: Se agregó el Índice (hasta el nivel 1.1.1) y el Índice de cuadros agrupado por punto, como campos de Word que se actualizan al abrir el archivo. | F6: En proceso
A7: Todos | B7: Estructura y formato | D7: Numeración de páginas continua: se quitó el reinicio en 1 de las 21 secciones. | F7: En proceso
A8: Todos | B8: Estructura y formato | D8: Los títulos numerados tienen nivel de esquema (aparecen en el panel de navegación de Word) y los títulos de cuadro usan el estilo TituloCuadro. | F8: En proceso
A9: 1.6 | B9: Denominación del grado (Reglamento 08, Art. 4) | C9: Técnico Universitario Superior en Contabilidad General | D9: Técnico Superior en Contabilidad General | E9: La Resolución del Honorable Consejo Universitario N.º 290/2016 aprueba la denominación de Técnico Universitario Superior | F9: En proceso
A10: 1.6 | B10: Denominación del grado (Reglamento 08, Art. 4) | C10: Técnico Universitario Superior en Contabilidad General | D10: Técnico Superior en Contabilidad General | E10: Técnico Universitario Superior en Contabilidad General | F10: En proceso
A11: 1.6 | B11: Descripción del grado intermedio TUM | C11: Al concluir el segundo año de formación académica, el estudiante puede acceder además al grado de Técnico Universitario Medio en Contabilidad. La Resolución del Honorable Consejo Universitario N.º 426/2024, de 24 de julio de 2024, incluye este grado en el Cuadro General de Grados de la UMSA y establece que el requisito ineludible para la extensión del Diploma Académico y del Título Profesional de | D11: Salida Intermedia Técnico Universitario Medio: Conduce a la obtención del Diploma Académico de Técnico Universitario Medio en Contabilidad y Título en Provisión Nacional de Auxiliar Contable, de aprobación directa tras concluir y aprobar la totalidad de las dieciséis (16) asignaturas correspondientes a primero y segundo año en un periodo continuo de dos (2) gestiones académicas, en estricto cumpli | F11: En proceso
A12: 1.9 | B12: Denominación del grado (Reglamento 08, Art. 4) | C12: Técnico Universitario Superior en Contabilidad General | D12: Técnico Superior en Contabilidad General | E12: Técnico Universitario Superior en Contabilidad General, conforme a la Resolución del Honorable Consejo Universitario N.º | F12: En proceso
A13: 2 | B13: Numeración de cuadros | C13: Cuadro 3. Personal administrativo de planta | D13: Cuadro 1. Personal administrativo de planta | F13: En proceso
A14: 2 | B14: Numeración de cuadros | C14: Cuadro 4. Personal administrativo a contrato | D14: Cuadro 2. Personal administrativo a contrato | F14: En proceso
A15: 2 | B15: Numeración de cuadros | C15: Cuadro 5. Personal de las unidades dependientes de la Carrera | D15: Cuadro 3. Personal de las unidades dependientes de la Carrera | F15: En proceso
A16: 2 | B16: Numeración de cuadros | C16: Cuadro 6. Docentes por categoría | D16: Cuadro 4. Docentes por categoría | F16: En proceso
A17: 2 | B17: Numeración de cuadros | C17: Cuadro 7. Carga horaria de los docentes por áreas, expresada en cantidad de docentes | D17: Cuadro 5. Carga horaria de los docentes por áreas, expresada en cantidad de docentes | F17: En proceso
A18: 2 | B18: Numeración de cuadros | C18: Cuadro 8. Docentes sin duplicidad entre áreas | D18: Cuadro 6. Docentes sin duplicidad entre áreas | F18: En proceso
A19: 2 | B19: Numeración de cuadros | C19: Sumatoria total según el Cuadro 7 | D19: Sumatoria total según el Cuadro 5 | F19: En proceso
A20: 2 | B20: Numeración de cuadros | C20: Los Cuadros 7 y 8 permiten establecer lo siguiente: | D20: Los Cuadros 5 y 6 permiten establecer lo siguiente: | F20: En proceso
A21: 2 | B21: Numeración de cuadros | C21: Cuadro 9. Docentes por áreas y categoría, expresado en cantidad de asignaturas | D21: Cuadro 7. Docentes por áreas y categoría, expresado en cantidad de asignaturas | F21: En proceso
A22: 2 | B22: Numeración de cuadros | C22: Cuadro 10. Docentes por áreas y categoría, expresado en porcentaje | D22: Cuadro 8. Docentes por áreas y categoría, expresado en porcentaje | F22: En proceso
A23: 2 | B23: Numeración de cuadros | C23: Fuente: elaboración propia con base en el Cuadro 9. | D23: Fuente: elaboración propia con base en el Cuadro 7. | F23: En proceso
A24: 2 | B24: Numeración de cuadros | C24: Según los Cuadros 9 y 10, existen 85 designaciones de docentes titulares, equivalentes al 46,45 %, y 98 de docentes inte | D24: Según los Cuadros 7 y 8, existen 85 designaciones de docentes titulares, equivalentes al 46,45 %, y 98 de docentes inter | F24: En proceso
... A31: 2 | B31: Numeración de cuadros | C31: Según el Cuadro 13, el promedio de estudiantes por paralelo se mantiene entre 104 y 109 en el periodo 2023 a 2026, una c | D31: Según el Cuadro 11, el promedio de estudiantes por paralelo se mantiene entre 104 y 109 en el periodo 2023 a 2026, una c | F31: En proceso
A32: 2.1 | B32: Denominación del grado (Reglamento 08, Art. 4) | C32: Técnico Universitario Superior en Contabilidad General | D32: Técnico Superior en Contabilidad General | E32: Técnico Universitario Superior en Contabilidad General y título en provisión nacional de Contador General; Técnico Unive | F32: En proceso
A33: 2.1 | B33: Ortografía | C33: titulo en provisión | D33: título en provisión | E33: Técnico Superior en Contabilidad General y título en provisión nacional de Contador General; Técnico Universitario Medio | F33: En proceso
A34: 2.1 | B34: Datos de matrícula, gestión 2026 | C34: Estudiantes matriculados, gestión 2025 | D34: Estudiantes matriculados, gestión 2026 | F34: En proceso
A35: 2.1 | B35: Datos de matrícula, gestión 2026 | C35: 4.283 | D35: 4.296: 3.743 antiguos y 553 nuevos, en la sede de La Paz | F35: En proceso
A36: 2.1 | B36: Datos de matrícula, gestión 2026 | C36: Estudiantes inscritos, gestión 2025 | D36: Estudiantes inscritos, gestión 2026 | F36: En proceso
A37: 2.1 | B37: Datos de matrícula, gestión 2026 | C37: 3.247: 3.143 en la sede de La Paz y 104 en las sedes desconcentradas | D37: 3.116 en la sede de La Paz; las sedes desconcentradas registraron 104 inscritos en 2025 | F37: En proceso
A38: 2.3 | B38: Ortografía | C38: Contaduría publica | D38: Contaduría Pública | E38: El Plan Estratégico Institucional de la Carrera de Contaduría publica forma parte del plan estratégico Institucional de | F38: En proceso
A39: 2.6 | B39: Ortografía | C39: kardixtas | D39: kardexistas | E39: Apoyo académico y administrativo: Encargado de Kárdex, con una encargada de Kárdex I y dos kardixtas académicos; dos enc | F39: En proceso
A40: 2.6.1 | B40: Datos de matrícula, gestión 2026 | C40: Con una población de 4.283 estudiantes matriculados y 3.143 inscritos en la gestión 2025, el personal administrativo disponible permite atender la demanda académica y administrativa, aunque esa capacidad se sostiene principalmente con personal contratado. El funcionamiento adecuado de la Carrera dep | D40: Con una población de 4.296 estudiantes matriculados y 3.116 inscritos en la gestión 2026, el personal administrativo disponible permite atender la demanda académica y administrativa, aunque esa capacidad se sostiene principalmente con personal contratado. El funcionamiento adecuado de la Carrera dep | F40: En proceso
A41: 2.7.1 | B41: Ortografía | C41: Auditoria | D41: Auditoría | E41: Área Contable y de Auditoria | F41: En proceso
A42: 2.7.1 | B42: Ortografía | C42: Auditoria | D42: Auditoría | E42: Total Área Contable y de Auditoria | F42: En proceso
A43: 2.7.1 | B43: Ortografía | C43: auditoria | D43: auditoría | E43: El área contable y de auditoria concentran 73 cargas horarias y el área contextual 35, lo que refleja la distribución de | F43: En proceso
A44: 2.7.1 | B44: Ortografía | C44: Auditoria | D44: Auditoría | E44: Área Contable y de Auditoria | F44: En proceso
A45: 2.7.1 | B45: Ortografía | C45: Auditoria | D45: Auditoría | E45: Total Área Contable y de Auditoria | F45: En proceso
A46: 2.7.1 | B46: Ortografía | C46: Auditoria | D46: Auditoría | E46: Área Contable y de Auditoria | F46: En proceso
A47: 2.7.1 | B47: Ortografía | C47: Auditoria | D47: Auditoría | E47: Total Área Contable y de Auditoria | F47: En proceso
A48: 2.7.1 | B48: Ortografía | C48: auditoria | D48: auditoría | E48: Como apoyo a la docencia, durante las gestiones 2023 a 2026 la Carrera contó con una asignación constante de 79 ítems de | F48: En proceso
A49: 2.7.1 | B49: Término: Área Contextual | C49: El área contable y de auditoría concentran 73 cargas horarias y el área contextual 35, lo que refleja la distribución de las asignaturas por áreas. | D49: El área contable y de auditoría concentran 73 cargas horarias y el Área Contextual 35, lo que refleja la distribución de las asignaturas por áreas. | F49: En proceso
A50: 2.7.1 | B50: Término: Área Contextual | C50: Como apoyo a la docencia, durante las gestiones 2023 a 2026 la Carrera contó con una asignación constante de 79 ítems de auxiliares de docencia, equivalentes a 1.580 horas de apoyo académico por gestión. Estas auxiliaturas priorizan las asignaturas del área contable y de auditoría; sin embargo, es n | D50: Como apoyo a la docencia, durante las gestiones 2023 a 2026 la Carrera contó con una asignación constante de 79 ítems de auxiliares de docencia, equivalentes a 1.580 horas de apoyo académico por gestión. Estas auxiliaturas priorizan las asignaturas del área contable y de auditoría; sin embargo, es n | F50: En proceso
A51: 2.7.2 | B51: Datos de matrícula, gestión 2026 | D51: Columna 2026 agregada: 2026 | 4.296 | 3.116 | 1.180 | F51: En proceso
A52: 2.7.2 | B52: Datos de matrícula, gestión 2026 | C52: Los estudiantes matriculados disminuyeron de 4.705 en 2021, año base, a 4.283 en 2025, lo que representa una reducción del 8,97 %. | D52: Los estudiantes matriculados disminuyeron de 4.705 en 2021, año base, a 4.296 en 2026, lo que representa una reducción del 8,69 %. | F52: En proceso
A53: 2.7.2 | B53: Datos de matrícula, gestión 2026 | C53: Los estudiantes inscritos se mantuvieron estables en el mismo periodo, con una variación de 3.152 a 3.143, equivalente a una disminución del 0,29 %. | D53: Los estudiantes inscritos se mantuvieron estables en el mismo periodo, con una variación de 3.152 a 3.116, equivalente a una disminución del 1,14 %. | F53: En proceso
A54: 2.7.2 | B54: Datos de matrícula, gestión 2026 | C54: La diferencia corresponde a estudiantes que obtuvieron su matrícula universitaria pero no se inscribieron en ninguna asignatura durante el año. Esta cifra se redujo de 1.553 en 2021 a 1.140 en 2025, que representan el 26,62 % del total de matriculados. | D54: La diferencia corresponde a estudiantes que obtuvieron su matrícula universitaria pero no se inscribieron en ninguna asignatura durante el año. Esta cifra se redujo de 1.553 en 2021 a 1.180 en 2026, aunque aumentó respecto de los 1.140 de 2025, y representa el 27,47 % del total de matriculados. | F54: En proceso
A55: 2.7.2 | B55: Datos de matrícula, gestión 2026 | C55: Las cifras de inscritos del Cuadro 9 corresponden a la sede de La Paz. Si se suman los 104 estudiantes de las sedes desconcentradas, la Carrera registró 3.247 inscritos en la gestión 2025, de los cuales 1.830 son mujeres, el 56 %, y 1.417 varones, el 44 %. Además, 1.589 estudiantes, el 48,9 %, reali | D55: Las cifras de inscritos del Cuadro 9 corresponden a la sede de La Paz. Si se suman los 104 estudiantes de las sedes desconcentradas, la Carrera registró 3.247 inscritos en la gestión 2025, de los cuales 1.830 son mujeres, el 56 %, y 1.417 varones, el 44 %. Además, 1.589 estudiantes, el 48,9 %, reali | F55: En proceso
A56: 3.1.1 | B56: Término: Área Contable y de Auditoría | C56: El Plan de Estudios 2013 fue aprobado por el Primer Congreso Académico de la Carrera y por las Resoluciones HCC N.º 162/2012, HCF N.º 929/2012 y HCU N.º 025/2013, y rige desde febrero de 2013. Comprende cinco años, 43 asignaturas y 6.000 horas académicas. De las asignaturas, 29 son troncales, el 67, | D56: El Plan de Estudios 2013 fue aprobado por el Primer Congreso Académico de la Carrera y por las Resoluciones HCC N.º 162/2012, HCF N.º 929/2012 y HCU N.º 025/2013, y rige desde febrero de 2013. Comprende cinco años, 43 asignaturas y 6.000 horas académicas. De las asignaturas, 29 son del Área Contable | F56: En proceso
A57: 3.1.1 | B57: Término: Área Contable y de Auditoría | C57: Subtotal troncal | D57: Subtotal Área Contable y de Auditoría | F57: En proceso
A58: 3.1.1 | B58: Término: Área Contextual | C58: El Plan de Estudios 2013 fue aprobado por el Primer Congreso Académico de la Carrera y por las Resoluciones HCC N.º 162/2012, HCF N.º 929/2012 y HCU N.º 025/2013, y rige desde febrero de 2013. Comprende cinco años, 43 asignaturas y 6.000 horas académicas. De las asignaturas, 29 son del Área Contable | D58: El Plan de Estudios 2013 fue aprobado por el Primer Congreso Académico de la Carrera y por las Resoluciones HCC N.º 162/2012, HCF N.º 929/2012 y HCU N.º 025/2013, y rige desde febrero de 2013. Comprende cinco años, 43 asignaturas y 6.000 horas académicas. De las asignaturas, 29 son del Área Contable | F58: En proceso
A59: 3.1.1 | B59: Término: Área Contextual | C59: Subtotal contextual | D59: Subtotal Área Contextual | F59: En proceso
A60: 3.1.1 | B60: Término: Área Contextual | C60: La estructura muestra un rasgo que condiciona el rediseño: las áreas contextuales se concentran en los tres primeros años y desaparecen en cuarto y quinto, mientras que el bloque de aseguramiento se concentra en los dos últimos años, con 11 de sus 13 asignaturas en quinto. La formación es secuencial | D60: La estructura muestra un rasgo que condiciona el rediseño: las asignaturas del Área Contextual se concentran en los tres primeros años y desaparecen en cuarto y quinto, mientras que el bloque de aseguramiento se concentra en los dos últimos años, con 11 de sus 13 asignaturas en quinto. La formación | F60: En proceso
A61: 3.1.1 | B61: Término: Área Contextual | C61: La estructura muestra un rasgo que condiciona el rediseño: las asignaturas del Área Contextual se concentran en los tres primeros años y desaparecen en cuarto y quinto, mientras que el bloque de aseguramiento se concentra en los dos últimos años, con 11 de sus 13 asignaturas en quinto. La formación | D61: La estructura muestra un rasgo que condiciona el rediseño: las asignaturas del Área Contextual se concentran en los tres primeros años y desaparecen en cuarto y quinto, mientras que el bloque de aseguramiento se concentra en los dos últimos años, con 11 de sus 13 asignaturas en quinto. La formación | F61: En proceso
A62: 3.1.2 | B62: Datos de matrícula, gestión 2026 | D62: Columna 2026 agregada: 2026 | 4.296 | 3.116 | 1.180 | 72,53 | F62: En proceso
A63: 3.1.2 | B63: Datos de matrícula, gestión 2026 | C63: Cuadro 5. Matrícula e inscripción estudiantil, 2021-2025 | D63: Cuadro 5. Matrícula e inscripción estudiantil, 2021-2026 | F63: En proceso
A64: 3.1.2 | B64: Datos de matrícula, gestión 2026 | C64: Matriculados e inscritos, 2025 | D64: Matriculados e inscritos, 2026 | F64: En proceso
A65: 3.1.2 | B65: Datos de matrícula, gestión 2026 | C65: 4.283 y 3.143 | D65: 4.296 y 3.116 | F65: En proceso
A66: 3.1.2 | B66: Datos de matrícula, gestión 2026 | C66: La matrícula cayó 8,97 % desde 2021 | D66: La matrícula cayó 8,69 % desde 2021 | F66: En proceso
A67: 3.1.2 | B67: Datos de matrícula, gestión 2026 | C67: 33,01 % en 2021 y 26,62 % en 2025 | D67: 33,01 % en 2021 y 27,47 % en 2026 | F67: En proceso
A68: 3.2.1 | B68: Denominación del grado (Reglamento 08, Art. 4) | C68: Técnico Universitario Superior | D68: Técnico Superior | E68: Grados intermedios de Técnico Universitario Medio y Técnico Universitario Superior, y articulación con los diplomados y | F68: En proceso
A69: 3.2.1 | B69: Ortografía | C69: curgricular | D69: curricular | E69: El rediseño es el instrumento curgricular para cumplir el OE 1.3 y respalda las metas de acreditación de la Carrera | F69: En proceso
A70: 3.4.4 | B70: Ortografía | C70: auditoria | D70: auditoría | E70: Aplicaciones para auditoria y finanzas | F70: En proceso
A71: 4.1.1 | B71: Término: Contador Público | C71: Lo Multidimensional: Las organizaciones y los seres humanos son unidades complejas multidimensionales. El Contador Público Autorizado debe reconocer que la información contable no es únicamente cuantitativa-financiera, sino que integra dimensiones éticas, ambientales, tecnológicas, jurídicas y socio | D71: Lo Multidimensional: Las organizaciones y los seres humanos son unidades complejas multidimensionales. El Contador Público debe reconocer que la información contable no es únicamente cuantitativa-financiera, sino que integra dimensiones éticas, ambientales, tecnológicas, jurídicas y sociológicas. | F71: En proceso
A72: 4.1.1 | B72: Término: Contador Público | C72: Lo Complejo: Existe complejidad cuando los constituyentes de un todo son inseparables y existe un tejido interdependiente e inter-retroactivo entre el objeto de conocimiento y su entorno. Frente a la incertidumbre y constante evolución del mundo de los negocios, el Contador Público Autorizado aplica | D72: Lo Complejo: Existe complejidad cuando los constituyentes de un todo son inseparables y existe un tejido interdependiente e inter-retroactivo entre el objeto de conocimiento y su entorno. Frente a la incertidumbre y constante evolución del mundo de los negocios, el Contador Público aplica su juicio | F72: En proceso
A73: 4.1.4 | B73: Ortografía | C73: Adminisión | D73: Admisión | E73: IES 1 Requisitos de Ingreso al Programa: Garantiza la equidad, transparencia y meritocracia en los procesos de selección | F73: En proceso
A74: 4.2.6 | B74: Término: Contador Público | C74: Cuadro 3. Matriz resumen de las competencias del Contador Público Autorizado | D74: Cuadro 3. Matriz resumen de las competencias del Contador Público | F74: En proceso
A75: 4.3.2 | B75: Denominación del grado (Reglamento 08, Art. 4) | C75: Técnico Universitario Superior | D75: Técnico Superior | E75: los grados intermedios de Técnico Universitario Medio y Técnico Universitario Superior, y la articulación de la graduaci | F75: En proceso
A76: 4.3.4 | B76: Ortografía | C76: Sector Publico | D76: Sector Público | E76: Incorporar los contenidos emergentes de mayor demanda: Normas del Sector Publico, NIIF y NIIF de Sostenibilidad, asegura | F76: En proceso
A77: 4.3.5 | B77: Nombre de asignatura (malla definitiva) | C77: Auditoría Interna, Control Interno y Gestión de Riesgos | D77: Auditoría Interna, Control Interno, Gestión de Riesgos y Gobierno Corporativo | E77: CPA-302 Contabilidad de Costos y Gestión, CPA-305 Sistemas Contables ERP y Análisis de Datos, CPA-406 Ética e Independen | F77: En proceso
A78: 4.3.5 | B78: Nombre de asignatura (malla definitiva) | C78: Auditoría Forense, Peritaje y Prevención de Delitos Económicos | D78: Auditoría Forense y Prevención de Delitos Económicos | E78: CPA-501 Auditoría Operativa, CPA-502 Gabinete de Auditoría Financiera, CPA-504 Auditoría Gubernamental, CPA-508 Auditorí | F78: En proceso
A79: 4.4.1 | B79: Ortografía | C79: Auditoria | D79: Auditoría | E79: Área Contable y de Auditoria | F79: En proceso
A80: 4.4.1 | B80: Ortografía | C80: Auditoria | D80: Auditoría | E80: Área Contable y de Auditoria | F80: En proceso
A81: 4.4.1 | B81: Término: Área Contextual | C81: De acuerdo con el modelo curricular por competencias del Sistema de la Universidad Boliviana y con la IES 2 de la IFAC, el Rediseño Curricular organiza sus 43 asignaturas en seis áreas de conocimiento agrupadas en dos bloques: el área contable y de auditoría, que forman el núcleo de la profesión, y | D81: De acuerdo con el modelo curricular por competencias del Sistema de la Universidad Boliviana y con la IES 2 de la IFAC, el Rediseño Curricular organiza sus 43 asignaturas en seis áreas de conocimiento agrupadas en dos bloques: el área contable y de auditoría, que forman el núcleo de la profesión, y | F81: En proceso
A82: 4.4.1 | B82: Término: Área Contextual | C82: Área contextual: | D82: Área Contextual: | F82: En proceso
A83: 4.4.3 | B83: Nombre de asignatura (malla definitiva) | C83: Álgebra Lineal y Programación Operativa Aplicada a los Negocios | D83: Álgebra Lineal y Modelación para Negocios | E83: Álgebra Lineal y Programación Operativa Aplicada a los Negocios | F83: En proceso
A84: 4.4.3 | B84: Nombre de asignatura (malla definitiva) | C84: Contabilidad y Presupuestos Gubernamental | D84: Presupuesto y Contabilidad Gubernamental | E84: Contabilidad y Presupuestos Gubernamental | F84: En proceso
A85: 4.4.3 | B85: Nombre de asignatura (malla definitiva) | C85: Auditoría Interna, Control Interno y Gestión de Riesgos | D85: Auditoría Interna, Control Interno, Gestión de Riesgos y Gobierno Corporativo | E85: Auditoría Interna, Control Interno y Gestión de Riesgos | F85: En proceso
A86: 4.4.3 | B86: Nombre de asignatura (malla definitiva) | C86: Auditoría de Proyectos Públicos y Privados | D86: Auditoría de Entidades Sin Fines de Lucro – Proyectos Privados y Públicos | E86: Auditoría de Proyectos Públicos y Privados | F86: En proceso
A87: 4.4.3 | B87: Nombre de asignatura (malla definitiva) | C87: Auditoría Forense, Peritaje y Prevención de Delitos Económicos | D87: Auditoría Forense y Prevención de Delitos Económicos | E87: Auditoría Forense, Peritaje y Prevención de Delitos Económicos | F87: En proceso
A88: 5 | B88: Formato | C88: Texto en color rojo (Cuadro 4 de mesas, Cuadro 5 de grados, examen por ciclos y listas de ciclos) | D88: Color automático | F88: En proceso
A89: 5 | B89: Estructura y formato | D89: Se eliminó el comentario de la Lic. Carlos Gonzales Alanes y el color rojo del punto 5, tras revisar los nombres de las asignaturas. | F89: En proceso
A90: 5.4.1 | B90: Denominación del grado (Reglamento 08, Art. 4) | C90: Técnico Universitario Superior | D90: Técnico Superior | E90: Técnico Universitario Superior | F90: En proceso
A91: 5.4.1 | B91: Denominación del grado (Reglamento 08, Art. 4) | C91: Técnico Universitario Superior en Contabilidad General | D91: Técnico Superior en Contabilidad General | E91: Técnico Universitario Superior en Contabilidad General | F91: En proceso
A92: 5.4.1 | B92: Descripción del grado intermedio TUM | C92: Aprobación de todas las asignaturas del Primer y Segundo año, 16 asignaturas, en el tiempo determinado (dos años continuos bajo modalidad anual) | D92: Aprobación directa tras concluir y aprobar la totalidad de las dieciséis (16) asignaturas correspondientes a primero y segundo año en un periodo continuo de dos (2) gestiones académicas, en estricto cumplimiento de la Resolución HCU Nº 426/2024 | F92: En proceso
A93: 5.4.2 | B93: Nombre de asignatura (malla definitiva) | C93: Presupuestos y Contabilidad Gubernamental | D93: Presupuesto y Contabilidad Gubernamental | E93: Presupuestos y Contabilidad Gubernamental | F93: En proceso
A94: 5.4.2 | B94: Nombre de asignatura (malla definitiva) | C94: Auditoría Interna, Control Interno y Gestión de Riesgos | D94: Auditoría Interna, Control Interno, Gestión de Riesgos y Gobierno Corporativo | E94: Auditoría Interna, Control Interno y Gestión de Riesgos | F94: En proceso
A95: 5.4.2 | B95: Nombre de asignatura (malla definitiva) | C95: Auditoría de Proyectos: Público y Privado | D95: Auditoría de Entidades Sin Fines de Lucro – Proyectos Privados y Públicos | E95: Auditoría de Proyectos: Público y Privado | F95: En proceso
A96: 5.4.2 | B96: Nombre de asignatura (malla definitiva) | C96: Auditoría de Entidades Financieras | D96: Auditoría de Entidades Financieras y Servicios Relacionados | E96: Auditoría de Entidades Financieras | F96: En proceso
A97: 5.4.2 | B97: Alineación con el Reglamento de Modalidades de Graduación | C97: ), el estudiante que concluya las 43 asignaturas del presente plan, podrá optar por una de las siguientes seis modalidades | D97: ) y con el Reglamento de Modalidades de Graduación de la Carrera incorporado en el punto 13.1.4, el estudiante que concluya las 43 asignaturas del presente plan podrá optar por una de las siguientes siete modalidades | E97: En estricta concordancia con el Reglamento General de Tipos y Modalidades de Graduación del SUB (aprobado en los congres | F97: En proceso
A98: 5.4.2 | B98: Alineación con el Reglamento de Modalidades de Graduación | C98: dedicación exclusiva durante un periodo máximo de 8 meses. | D98: dedicación exclusiva durante un periodo máximo de ocho (8) meses, con un mínimo de 1.280 horas de trabajo efectivo, conforme a los Artículos 46 y 47 del Reglamento de Modalidades de Graduación. | E98: Requisitos Específicos: El estudiante debe tener un promedio académico acumulado no menor a sesenta (60) puntos y dedica | F98: En proceso
A99: 5.4.2 | B99: Alineación con el Reglamento de Modalidades de Graduación (escala del trabajo dirigido, Art. 55) | C99: Aprobado – Buena | D99: Aprobado – Bueno | F99: En proceso
A100: 5.4.2 | B100: Alineación con el Reglamento de Modalidades de Graduación (escala del trabajo dirigido, Art. 55) | C100: Sobresaliente – Con recomendación de publicación | D100: Aprobado – Sobresaliente | F100: En proceso
A101: 5.4.2 | B101: Alineación con el Reglamento de Modalidades de Graduación (escala del trabajo dirigido, Art. 55) | C101: Excelente – Con mención honorífica y recomendación de publicación | D101: Excelente – Excelencia | F101: En proceso
A102: 5.4.2 | B102: Alineación con el Reglamento de Modalidades de Graduación | C102: como mínimo tres (3) veces al año | D102: como mínimo cuatro (4) veces al año, cada convocatoria en tres (3) semanas continuas, una por ciclo | E102: Las asignaturas sujetas a evaluación, corresponden a las áreas de información financiera y aseguramiento, distribuidas e | F102: En proceso
A103: 5.4.2 | B103: Alineación con el Reglamento de Modalidades de Graduación | C103: 24 horas de anticipación al examen. | D103: 24 horas de anticipación al examen. El postulante debe aprobar los tres ciclos en un plazo máximo de doce (12) meses calendario desde su inscripción al primer ciclo, y quien repruebe tres (3) veces un mismo ciclo queda inhabilitado para esta modalidad, conforme a los Artículos 60 a 67 del Reglamento de Modalidades de Graduación. | E103: Las asignaturas sujetas a evaluación, corresponden a las áreas de información financiera y aseguramiento, distribuidas e | F103: En proceso
A104: 5.4.2 | B104: Alineación con el Reglamento de Modalidades de Graduación | C104: Ciclo Servicios | D104: Ciclo de Servicios | E104: Ciclo Servicios de Aseguramiento | F104: En proceso
A105: 5.4.2 | B105: Alineación con el Reglamento de Modalidades de Graduación (Art. 72) | C105: Haber aprobado el 100% de las 43 asignaturas en primera instancia (sin haber recurrido a exámenes de mesa ni haber reprobado ninguna materia). | D105: Haber aprobado el 100% de las 43 asignaturas en evaluaciones ordinarias de primera instancia, sin haber reprobado, abandonado ni cursado asignaturas en segundo turno, exámenes extraordinarios de mesa o cursos de verano destinados a subsanar reprobaciones. | F105: En proceso
A106: 5.4.2 | B106: Alineación con el Reglamento de Modalidades de Graduación (Art. 72) | C106: Haber concluido el plan de estudios dentro del tiempo reglamentario de la carrera (5 años continuos). | D106: Haber concluido el plan de estudios en el tiempo reglamentario de cinco (5) gestiones académicas anuales continuas, sin suspensiones voluntarias, abandonos temporales ni postergaciones de matrícula. | F106: En proceso
...

Sheet Coherencia
A1: Coherencia pendiente entre puntos
A2: Lo que un punto dice distinto de otro. El Reglamento de Modalidades de Graduación (13.1.4) y la malla definitiva prevalecen.
A3: Tema | B3: Puntos | C3: Tipo | D3: Severidad | E3: Detalle | F3: Corrección propuesta | G3: Seguimiento | H3: Observaciones
A4: Población habilitada para el PETAENG | B4: 5.4.2 / 13.1.4 (Art. 5 y Art. 83) / 16.3 | C4: Contradicción | D4: Alta | E4: El punto 5.4.2 dice que «el estudiante que concluya las 43 asignaturas del presente plan podrá optar por una de las siguientes siete modalidades» y entre ellas incluye el PETAENG, «dirigido exclusivamente a estudiantes egresados que hayan concluido el plan de estudios y tengan [...] tres (3) años de antigüedad». El Art. 83 del Reglamento lo limita a los egresados «que hayan concluido el 100% de la Malla Curricular de planes de estudio anteriores». El Art. 5 lo describe sin esa restricción («egresados con una antigüedad igual o mayor a tres (3) años»), y el 16.3 lo trata como salida para egresados del Plan 2013. | F4: Alinear el 5.4.2 con el Art. 83: presentar el PETAENG como modalidad excepcional para egresados de planes anteriores, separada de las seis modalidades del nuevo plan, y cambiar «siete» por «seis más el PETAENG para planes anteriores». Para que el propio Reglamento sea coherente, agregar en el Art. 5 «de planes de estudio anteriores». | G4: Pendiente
A5: Créditos exigidos para el Técnico Superior | B5: 13.1.4 (Art. 88) / 4.4.3 / 4.4.4 / 8.5 | C5: Dato distinto | D5: Alta | E5: El Art. 88 del Reglamento exige «Haber aprobado la totalidad de las veinticuatro (24) asignaturas correspondientes a primer, segundo y tercer año del Plan de Estudios (120 créditos)». Según la malla (4.4.3, 4.4.4 y 8.5), cada año suma 60 créditos, de modo que las 24 asignaturas de 1.° a 3.° año suman 180 créditos y 3.520 horas presenciales. Los 120 créditos corresponden solo a 1.° y 2.° año, es decir, a las 16 asignaturas del Técnico Universitario Medio. | F5: En el Art. 88 del 13.1.4, cambiar «(120 créditos)» por «(180 créditos)» o eliminar el paréntesis. Como el Reglamento prevalece, la corrección debe hacerse en su propio texto. | G5: Pendiente
A6: Plazo de graduación de egresados del Plan 2013 | B6: 16.3 / 13.1.4 (Disposición Transitoria Primera) | C6: Contradicción | D6: Alta | E6: El punto 16.3 dice «El estudiante que concluya el Plan 2013 dispone de un plazo de hasta tres años calendario desde su egreso para graduarse conforme a la reglamentación de ese plan. Vencido el plazo, se gradúa mediante las modalidades del Plan 2027 o el PETAENG, conforme al punto 13.1.4». El Reglamento (13.1.4, Disposición Transitoria Primera) no fija ningún plazo: los estudiantes de planes anteriores «mantendrán el derecho a graduarse bajo las modalidades vigentes al momento de su conclusión de estudios, o podrán acogerse voluntariamente a las modalidades del Plan de Estudios 2027 mediante homologación». El 16.3 remite además al 13.1.4 para una regla que este no contiene. | F6: Corregir el 16.3 para que repita la Disposición Transitoria Primera: quitar el plazo de tres años y la graduación obligatoria por el nuevo plan o el PETAENG, y decir que el egresado del Plan 2013 conserva las modalidades vigentes cuando concluyó o puede acogerse de forma voluntaria a las del nuevo plan mediante homologación. Si la comisión quiere un plazo, primero debe incorporarlo al Reglamento. | G6: Pendiente
A7: Congreso que aprobó el Reglamento General de Títulos y Grados | B7: 1.6 / 3.2.1 (Cuadro 11) / 5.4.1 / 13.1.1 | C7: Dato distinto | D7: Media | E7: El punto 1.6 cita el «Reglamento General de Títulos y Grados aprobado en el XIII Congreso Nacional de Universidades». El Cuadro 11 del 3.2.1 cita el «Reglamento General de Títulos y Grados, XI Congreso Nacional de Universidades, 2009». Los puntos 5.4.1 y 13.1.1 lo citan sin indicar el congreso. | F7: Verificar la edición vigente y usar en todos los puntos la misma denominación, congreso y año (por ejemplo: «Reglamento General de Títulos y Grados del Sistema de la Universidad Boliviana, aprobado en el [XI/XIII] Congreso Nacional de Universidades»). | G7: Pendiente
A8: Denominación del área de aseguramiento | B8: 2.7.1 (Cuadros 5, 7 y 8) / 3.1.2 (Cuadro 4) / 3.5.5 / 11.2.1 (Cuadro 7) / 4.4.1 | C8: Dato distinto | D8: Media | E8: Los mismos datos docentes de 2026 llaman al área «Servicios de Atestación y No Atestación» en los Cuadros 5, 7 y 8 del 2.7.1 («73,33 % en el área de Atestación» en el Cuadro 4 del 3.1.2, y «docentes a tiempo completo en el área de Atestación» en la decisión del 3.5.5). El Cuadro 7 del 11.2.1, con las mismas cifras (33 interinos, 12 titulares, 45 designaciones), la llama «Servicios de Aseguramiento», que es el nombre del área en el rediseño (4.4.1). | F8: Usar «Servicios de Aseguramiento» en el 2.7.1, el 3.1.2 y el 3.5.5 para los datos actuales y para el nuevo plan. «Servicios de Atestación y No Atestación» debe quedar solo como nombre del área del Plan 2013 (3.1.1, Cuadro 3), con una nota de equivalencia. | G8: Pendiente
A9: Gabinetes de auditoría en el nuevo plan | B9: 3.5.3 / 3.1.1 (Cuadro 10) / 4.8.2 (Cuadro 1) / 4.4.3 | C9: Dato distinto | D9: Media | E9: El punto 3.5.3 dice que el rediseño suma «la amplitud de su bloque de aseguramiento, con ocho gabinetes especializados, financiero, tributario, gubernamental, de sistemas, ambiental, de proyectos, forense y de entidades financieras». El Cuadro 1 del 4.8.2 ubica «Gabinetes y simulación profesional» en «4.° y 5.°». En la malla (4.4.3) solo CPA-502 es un gabinete; las demás asignaturas pasan a llamarse «Auditoría Tributaria», «Auditoría Gubernamental», etc., y en cuarto año no hay ningún gabinete. | F9: En el 3.5.3, hablar de «nueve asignaturas especializadas de aseguramiento en quinto año (CPA-501 a CPA-509), entre ellas el Gabinete de Auditoría Financiera». En el 4.8.2, cambiar a «Gabinete y asignaturas de aseguramiento | 4.° y 5.°» o limitar el gabinete a 5.°. | G9: Pendiente
A10: Tratamiento del inglés técnico | B10: 4.4.1 (Cuadro 2) / 4.3.1 / 3.1.1 (Cuadro 10) / 3.5.4 (Cuadro 30) / 4.2.7 | C10: Contradicción | D10: Media | E10: El punto 4.3.1 dice que «Cinco ejes atraviesan todas las áreas y años de estudio: [...] el inglés técnico». El Cuadro 2 del 4.4.1 lo limita a «las asignaturas de los últimos años» y, en nota, lo califica de «(*) Materia extracurricular propuesta». El Cuadro 10 del 3.1.1 dice «Se incorpora [...] inglés técnico contable» y el Cuadro 30 del 3.5.4, «Inglés técnico progresivo». La malla no tiene ninguna asignatura de inglés, pero el perfil (4.2.7) declara «conocimiento del inglés técnico contable». | F10: Definir una sola fórmula y repetirla en el 3, el 4.3.1 y el 4.4.1. Por ejemplo: «eje transversal que se incorpora progresivamente mediante bibliografía, casos y guías en inglés en los planes de asignatura, complementado con un curso extracurricular que no forma parte de la malla». Además, armonizar «todos los años» con «últimos años». | G10: Pendiente
A11: Componentes horarios de los planes de asignatura | B11: 4.4.4 / 8.4 / 4.5 | C11: Dato distinto | D11: Media | E11: El punto 4.4.4 dice que «La distinción de horas teóricas, prácticas y de laboratorio se consigna en cada plan de asignatura». Pero los planes del 4.5 y el 8.4 distribuyen las horas en presenciales (HP), aprendizaje autónomo (HAA), trabajo en grupo (HTG), investigación y práctica (HIP) y evaluación (HE), y no en horas teóricas, prácticas y de laboratorio. | F11: Redactar el 4.4.4 así: «La distribución de las horas de trabajo de cada asignatura en horas presenciales (HP), de aprendizaje autónomo (HAA), de trabajo en grupo (HTG), de investigación y práctica (HIP) y de evaluación (HE) se consigna en cada plan de asignatura del punto 4.5». | G11: Pendiente
A12: Remisiones al punto 5.3.5 eliminado | B12: 5.3.1 / 13.1.2 (Cuadro 2) / 14.9 | C12: Pendiente conocido | D12: Media | E12: El 5.3.1 remite a «la tutoría del punto 5.3.5», el Cuadro 2 del 13.1.2 da «Reglamento de Tutoría Académica [...] | Punto 5.3.5» y el 14.9 menciona el «sistema de alerta temprana del punto 5.3.5». La comisión eliminó ese punto. | F12: Pendiente ya identificado: quitar o reorientar las tres remisiones. | G12: Pendiente
A13: Remisión del sistema de créditos | B13: 8 (introducción) / 8.5 / 4.3.5 / 4.4.3 / 4.4.4 | C13: Referencia rota | D13: Media | E13: La introducción del punto 8 remite «al sistema de créditos del punto 4.3.5», y el 8.5 dice «El plan aplica el Sistema de Créditos Académicos de la UMSA, desarrollado en el punto 4.3.5». Pero el 4.3.5 trata de la «Duración de la carrera»; los créditos se desarrollan en los puntos 4.4.3 (malla con créditos) y 4.4.4 (Cuadro 9). | F13: Cambiar «punto 4.3.5» por «puntos 4.4.3 y 4.4.4» en la introducción del 8 y en el 8.5. | G13: Pendiente
A14: Estudiantes por paralelo (metas) | B14: 11.1.1 / 11.2.3 / 8.6 | C14: Referencia rota | D14: Media | E14: El punto 11.1.1 dice que «el punto 8.6 fija una meta intermedia de 80 estudiantes por paralelo, que requiere 302 paralelos, y una meta objetivo de 60, que requiere 402», y el Cuadro 9 del 11.2.3 cita como fuente «el punto 8.6». Pero el 8.6 no fija ninguna meta: solo dice que «el Director de carrera debe habilitar la cantidad de estudiantes que se pueden inscribir por paralelo». | F14: Incorporar en el 8.6 el mínimo y el máximo de estudiantes por paralelo (meta intermedia de 80 y meta objetivo de 60, con el cálculo de 302 y 402 paralelos), como exige el Art. 12 de la Res. HCU 032/2025, o bien quitar la remisión del 11.1.1 y del 11.2.3. | G14: Pendiente
A15: Capacidad de aulas y pabellones | B15: 11.1.2 (Cuadros 3 y 4) / 14.1 / 15 (Cuadros 1 y 2) | C15: Dato distinto | D15: Media | E15: Los Cuadros 3 y 4 del 11.1.2 y el 14.1 dan para el Nava Morales 974 plazas (Aula 2: 142; Aula 3: 90; Aula 4: 130; Aula 6: 78; Aula 7: 150; Aula 8: 138) y para los pabellones del Monoblock «1.100 plazas» (320/320/240/220). El relevamiento del punto 15 da otras cifras: Aula 2: 136; Aula 3: 94; Aula 4: 134; Aula 6: 80; Aula 7: 148; Aula 8: 120, y «Total pabellones | 1.776» asientos (606/606/300/264). Las pizarras de los pabellones también difieren: 6 en cada uno según el 14.1, y 6/8/4/6 según el 15. | F15: Conciliar con el relevamiento de octubre de 2026 y usar una sola cifra de capacidad por ambiente en los puntos 11.1.2, 14.1 y 15 (o explicar que el 15 cuenta asientos y el 11 la capacidad útil). Recalcular los m² por estudiante. | G15: Pendiente
... A49: Cursos de temporada y mesas de examen para rezagados del Plan 2013 | B49: 16.3 / 13.1.3 / 5.3.4 / 3.1.1 | C49: Dato distinto | D49: Baja | E49: El punto 16.3 permite habilitar «cursos de temporada y mesas de examen de sus asignaturas [del Plan 2013] para los estudiantes rezagados, conforme al punto 13.1.3». El 13.1.3 (como el 5.3.4) solo habilita mesas para ocho asignaturas del nuevo plan (ADM-101, [...] CPA-406), y el 3.1.1 señala que el Plan 2013 «no regula [...] la Mesa de Examen». | F49: Precisar en el 16.3 qué asignaturas del Plan 2013 pueden ofrecerse (por ejemplo, las equivalentes a las habilitadas en los puntos 5.3.3 y 5.3.4 según el Cuadro 1 del 16.1.3), o remitir a esas equivalencias. | G49: Pendiente
